{"v":"5.5.10","fr":29.9700012207031,"ip":0,"op":450.000018328876,"w":750,"h":600,"nm":"tut_fish_salmon_fillet_anim_375x300","ddd":0,"assets":[{"id":"comp_0","layers":[{"ddd":0,"ind":1,"ty":4,"nm":"dot","sr":1,"ks":{"o":{"a":0,"k":100,"ix":11},"r":{"a":0,"k":0,"ix":10},"p":{"a":0,"k":[60,60,0],"ix":2},"a":{"a":0,"k":[-8.25,26.75,0],"ix":1},"s":{"a":1,"k":[{"i":{"x":[0.667,0.667,0.667],"y":[1,1,1]},"o":{"x":[0.167,0.167,0.167],"y":[0.167,0.167,0]},"t":0,"s":[201.315,201.315,100]},{"i":{"x":[0.667,0.667,0.667],"y":[1,1,1]},"o":{"x":[0.333,0.333,0.333],"y":[0,0,0]},"t":6,"s":[278.673,278.673,100]},{"i":{"x":[0.667,0.667,0.667],"y":[1,1,1]},"o":{"x":[0.333,0.333,0.333],"y":[0,0,0]},"t":20,"s":[201.315,201.315,100]},{"i":{"x":[0.667,0.667,0.667],"y":[1,1,1]},"o":{"x":[0.333,0.333,0.333],"y":[0,0,0]},"t":25,"s":[201.315,201.315,100]},{"i":{"x":[0.667,0.667,0.667],"y":[1,1,1]},"o":{"x":[0.333,0.333,0.333],"y":[0,0,0]},"t":33,"s":[278.673,278.673,100]},{"i":{"x":[0.667,0.667,0.667],"y":[1,1,1]},"o":{"x":[0.333,0.333,0.333],"y":[0,0,0]},"t":47,"s":[201.315,201.315,100]},{"i":{"x":[0.667,0.667,0.667],"y":[1,1,1]},"o":{"x":[0.333,0.333,0.333],"y":[0,0,0]},"t":51,"s":[201.315,201.315,100]},{"i":{"x":[0.667,0.667,0.667],"y":[1,1,1]},"o":{"x":[0.333,0.333,0.333],"y":[0,0,0]},"t":59,"s":[278.673,278.673,100]},{"i":{"x":[0.715,0.715,0.833],"y":[1,1,7.036]},"o":{"x":[0.384,0.384,0.333],"y":[0,0,0]},"t":73,"s":[201.315,201.315,100]},{"i":{"x":[0.756,0.756,0.833],"y":[0.995,0.995,12.23]},"o":{"x":[0.347,0.347,0.167],"y":[0,0,-6.841]},"t":88,"s":[505.186,505.186,100]},{"t":105.000004276738,"s":[0,0,100]}],"ix":6}},"ao":0,"shapes":[{"ty":"gr","it":[{"d":1,"ty":"el","s":{"a":0,"k":[22.5,22.5],"ix":2},"p":{"a":0,"k":[0,0],"ix":3},"nm":"Ellipse Path 1","mn":"ADBE Vector Shape - Ellipse","hd":false},{"ty":"fl","c":{"a":0,"k":[0.772549019608,0.172549019608,0.81568627451,1],"ix":4},"o":{"a":0,"k":100,"ix":5},"r":1,"bm":0,"nm":"Fill 1","mn":"ADBE Vector Graphic - Fill","hd":false},{"ty":"tr","p":{"a":0,"k":[-8.25,26.75],"ix":2},"a":{"a":0,"k":[0,0],"ix":1},"s":{"a":0,"k":[28.727,28.727],"ix":3},"r":{"a":0,"k":0,"ix":6},"o":{"a":0,"k":100,"ix":7},"sk":{"a":0,"k":0,"ix":4},"sa":{"a":0,"k":0,"ix":5},"nm":"Transform"}],"nm":"Ellipse 1","np":2,"cix":2,"bm":0,"ix":1,"mn":"ADBE Vector Group","hd":false}],"ip":0,"op":120.0000048877,"st":0,"bm":0},{"ddd":0,"ind":2,"ty":0,"nm":"ring Temperature pulse animation","refId":"comp_1","sr":1,"ks":{"o":{"a":1,"k":[{"i":{"x":[0.833],"y":[0.833]},"o":{"x":[0.167],"y":[0.167]},"t":76,"s":[100]},{"t":84.0000034213901,"s":[0]}],"ix":11},"r":{"a":0,"k":0,"ix":10},"p":{"a":0,"k":[60,60,0],"ix":2},"a":{"a":0,"k":[60,60,0],"ix":1},"s":{"a":0,"k":[100,100,100],"ix":6}},"ao":0,"w":120,"h":120,"ip":51.0000020772726,"op":951.000038735024,"st":51.0000020772726,"bm":0},{"ddd":0,"ind":3,"ty":0,"nm":"ring Temperature pulse animation","refId":"comp_1","sr":1,"ks":{"o":{"a":1,"k":[{"i":{"x":[0.833],"y":[0.833]},"o":{"x":[0.167],"y":[0.167]},"t":51,"s":[100]},{"t":59.0000024031193,"s":[0]}],"ix":11},"r":{"a":0,"k":0,"ix":10},"p":{"a":0,"k":[60,60,0],"ix":2},"a":{"a":0,"k":[60,60,0],"ix":1},"s":{"a":0,"k":[100,100,100],"ix":6}},"ao":0,"w":120,"h":120,"ip":25.0000010182709,"op":925.000037676022,"st":25.0000010182709,"bm":0},{"ddd":0,"ind":4,"ty":0,"nm":"ring Temperature pulse animation","refId":"comp_1","sr":1,"ks":{"o":{"a":1,"k":[{"i":{"x":[0.833],"y":[0.833]},"o":{"x":[0.167],"y":[0.167]},"t":25,"s":[100]},{"t":33.0000013441176,"s":[0]}],"ix":11},"r":{"a":0,"k":0,"ix":10},"p":{"a":0,"k":[60,60,0],"ix":2},"a":{"a":0,"k":[60,60,0],"ix":1},"s":{"a":0,"k":[100,100,100],"ix":6}},"ao":0,"w":120,"h":120,"ip":0,"op":900.000036657751,"st":0,"bm":0}]},{"id":"comp_1","layers":[{"ddd":0,"ind":1,"ty":4,"nm":"ring","sr":1,"ks":{"o":{"a":0,"k":90.909,"ix":11},"r":{"a":0,"k":0,"ix":10},"p":{"a":0,"k":[60,60,0],"ix":2},"a":{"a":0,"k":[-8.25,26.75,0],"ix":1},"s":{"a":1,"k":[{"i":{"x":[0.833,0.833,0.833],"y":[0.833,0.833,0.833]},"o":{"x":[0.167,0.167,0.167],"y":[0.167,0.167,0.167]},"t":0,"s":[142.995,142.995,100]},{"t":31.0000012626559,"s":[1260.687,1260.687,100]}],"ix":6}},"ao":0,"shapes":[{"ty":"gr","it":[{"d":1,"ty":"el","s":{"a":0,"k":[22.5,22.5],"ix":2},"p":{"a":0,"k":[0,0],"ix":3},"nm":"Ellipse Path 1","mn":"ADBE Vector Shape - Ellipse","hd":false},{"ty":"st","c":{"a":1,"k":[{"i":{"x":[0.833],"y":[0.833]},"o":{"x":[0.167],"y":[0.167]},"t":0,"s":[0.776470648074,0.176470588235,0.819607902976,1]},{"t":31.0000012626559,"s":[1,1,1,1]}],"ix":3},"o":{"a":0,"k":100,"ix":4},"w":{"a":0,"k":1,"ix":5},"lc":1,"lj":1,"ml":4,"bm":0,"nm":"Stroke 1","mn":"ADBE Vector Graphic - Stroke","hd":false},{"ty":"tr","p":{"a":0,"k":[-8.25,26.75],"ix":2},"a":{"a":0,"k":[0,0],"ix":1},"s":{"a":0,"k":[33.845,33.845],"ix":3},"r":{"a":0,"k":0,"ix":6},"o":{"a":0,"k":100,"ix":7},"sk":{"a":0,"k":0,"ix":4},"sa":{"a":0,"k":0,"ix":5},"nm":"Transform"}],"nm":"Ellipse 1","np":2,"cix":2,"bm":0,"ix":1,"mn":"ADBE Vector Group","hd":false}],"ip":0,"op":900.000036657751,"st":0,"bm":0}]},{"id":"comp_2","layers":[{"ddd":0,"ind":1,"ty":0,"nm":"probe_insert_v4_still","refId":"comp_3","sr":1,"ks":{"o":{"a":1,"k":[{"i":{"x":[0.833],"y":[0.833]},"o":{"x":[0.167],"y":[0.167]},"t":460,"s":[100]},{"t":480.000019550801,"s":[2]}],"ix":11},"r":{"a":0,"k":-31,"ix":10},"p":{"a":0,"k":[295,363.5,0],"ix":2},"a":{"a":0,"k":[375,100,0],"ix":1},"s":{"a":0,"k":[100,100,100],"ix":6}},"ao":0,"w":750,"h":200,"ip":391.000015925756,"op":1002.0000408123,"st":102.000004154545,"bm":0},{"ddd":0,"ind":2,"ty":0,"nm":"probe_insert_v4_animation","refId":"comp_4","sr":1,"ks":{"o":{"a":1,"k":[{"i":{"x":[0.833],"y":[0.833]},"o":{"x":[0.167],"y":[0.167]},"t":389,"s":[100]},{"t":429.000017473528,"s":[4]}],"ix":11},"r":{"a":0,"k":-31,"ix":10},"p":{"a":0,"k":[295,363.5,0],"ix":2},"a":{"a":0,"k":[375,100,0],"ix":1},"s":{"a":0,"k":[100,100,100],"ix":6}},"ao":0,"w":750,"h":200,"ip":102.000004154545,"op":1002.0000408123,"st":102.000004154545,"bm":0},{"ddd":0,"ind":3,"ty":4,"nm":"fish salmon steak - full 3","sr":1,"ks":{"o":{"a":1,"k":[{"i":{"x":[0.833],"y":[0.833]},"o":{"x":[0.167],"y":[0.167]},"t":50,"s":[100]},{"i":{"x":[0.833],"y":[0.833]},"o":{"x":[0.167],"y":[0.167]},"t":76,"s":[0]},{"i":{"x":[0.833],"y":[0.833]},"o":{"x":[0.167],"y":[0.167]},"t":253,"s":[0]},{"i":{"x":[0.833],"y":[0.833]},"o":{"x":[0.167],"y":[0.167]},"t":389,"s":[3]},{"t":429.000017473528,"s":[100]}],"ix":11},"r":{"a":0,"k":0,"ix":10},"p":{"a":0,"k":[433.278,292.444,0],"ix":2},"a":{"a":0,"k":[114.5,81.5,0],"ix":1},"s":{"a":0,"k":[200,200,100],"ix":6}},"ao":0,"shapes":[{"ty":"gr","it":[{"ind":0,"ty":"sh","ix":1,"ks":{"a":0,"k":{"i":[[0,0],[1.979,-3.424],[-0.196,-3.05],[3.887,-12.555],[3.513,-5.401],[6.687,-8.827],[5.938,-1.529],[3.89,-4.061],[0.458,-2.699],[-0.874,-7.775]],"o":[[-1.873,1.623],[-2.426,4.244],[0.339,5.261],[-3.941,12.751],[-5.723,8.8],[-2.871,3.817],[-0.787,0.203],[-1.283,1.339],[-0.684,4.032],[0,0]],"v":[[26.933,-61.498],[21.155,-53.928],[17.811,-42.987],[12.488,-16.264],[0.958,10.727],[-18.176,27.168],[-35.078,34.931],[-43.405,39.713],[-46.598,46.851],[-48.309,62.748]],"c":false},"ix":2},"nm":"Path 1","mn":"ADBE Vector Shape - Group","hd":false},{"ty":"st","c":{"a":0,"k":[1,1,1,1],"ix":3},"o":{"a":0,"k":40,"ix":4},"w":{"a":0,"k":1.427,"ix":5},"lc":1,"lj":1,"ml":4,"bm":0,"nm":"Stroke 1","mn":"ADBE Vector Graphic - Stroke","hd":false},{"ty":"tr","p":{"a":0,"k":[149.251,87.251],"ix":2},"a":{"a":0,"k":[0,0],"ix":1},"s":{"a":0,"k":[100,100],"ix":3},"r":{"a":0,"k":0,"ix":6},"o":{"a":0,"k":100,"ix":7},"sk":{"a":0,"k":0,"ix":4},"sa":{"a":0,"k":0,"ix":5},"nm":"Transform"}],"nm":"Group 1","np":2,"cix":2,"bm":0,"ix":1,"mn":"ADBE Vector Group","hd":false},{"ty":"gr","it":[{"ind":0,"ty":"sh","ix":1,"ks":{"a":0,"k":{"i":[[0,0],[1.034,-5.457],[1.177,-5.208],[4.53,-10.396],[4.708,-8.186]],"o":[[-0.553,3.46],[-1.337,7.098],[-1.319,5.813],[-4.44,10.201],[0,0]],"v":[[14.324,-41.864],[11.943,-28.489],[8.171,-10.031],[-0.603,14.284],[-9.575,32.864]],"c":false},"ix":2},"nm":"Path 1","mn":"ADBE Vector Shape - Group","hd":false},{"ty":"st","c":{"a":0,"k":[1,1,1,1],"ix":3},"o":{"a":0,"k":40,"ix":4},"w":{"a":0,"k":1.427,"ix":5},"lc":1,"lj":1,"ml":4,"bm":0,"nm":"Stroke 1","mn":"ADBE Vector Graphic - Stroke","hd":false},{"ty":"tr","p":{"a":0,"k":[182.19,69.489],"ix":2},"a":{"a":0,"k":[0,0],"ix":1},"s":{"a":0,"k":[100,100],"ix":3},"r":{"a":0,"k":0,"ix":6},"o":{"a":0,"k":100,"ix":7},"sk":{"a":0,"k":0,"ix":4},"sa":{"a":0,"k":0,"ix":5},"nm":"Transform"}],"nm":"Group 2","np":2,"cix":2,"bm":0,"ix":2,"mn":"ADBE Vector Group","hd":false},{"ty":"gr","it":[{"ind":0,"ty":"sh","ix":1,"ks":{"a":0,"k":{"i":[[0,0],[1.48,-5.671],[0.838,-3.655],[7.597,-13.428],[1.997,-4.636],[2.346,-1.92],[5.95,-2.8],[1.659,-6.67]],"o":[[-0.286,1.748],[-1.855,7.151],[-0.981,4.334],[-8.917,15.765],[-0.892,2.069],[-6.66,5.451],[-8.8,3.825],[0,0]],"v":[[27.138,-58.301],[24.49,-47.174],[20.45,-30.964],[7.584,-4.321],[-8.787,26.281],[-15.853,34.272],[-37.463,43.148],[-49.513,60.926]],"c":false},"ix":2},"nm":"Path 1","mn":"ADBE Vector Shape - Group","hd":false},{"ty":"st","c":{"a":0,"k":[1,1,1,1],"ix":3},"o":{"a":0,"k":40,"ix":4},"w":{"a":0,"k":1.427,"ix":5},"lc":1,"lj":1,"ml":4,"bm":0,"nm":"Stroke 1","mn":"ADBE Vector Graphic - Stroke","hd":false},{"ty":"tr","p":{"a":0,"k":[157.874,84.055],"ix":2},"a":{"a":0,"k":[0,0],"ix":1},"s":{"a":0,"k":[100,100],"ix":3},"r":{"a":0,"k":0,"ix":6},"o":{"a":0,"k":100,"ix":7},"sk":{"a":0,"k":0,"ix":4},"sa":{"a":0,"k":0,"ix":5},"nm":"Transform"}],"nm":"Group 3","np":2,"cix":2,"bm":0,"ix":3,"mn":"ADBE Vector Group","hd":false},{"ty":"gr","it":[{"ind":0,"ty":"sh","ix":1,"ks":{"a":0,"k":{"i":[[0,0],[0.411,-2.835],[-0.232,-3.852],[-0.356,-3.603],[0.125,-1.195],[3.032,-4.048],[0,0],[2.122,-4.619],[3.923,-15.836],[1.569,-7.686]],"o":[[-1.284,1.123],[-0.321,2.354],[0.035,0.642],[0.196,1.979],[-0.303,2.889],[0,0],[-6.348,8.221],[-2.122,4.618],[-1.944,7.936],[0,0]],"v":[[21.574,-61.137],[19.032,-55.199],[18.899,-45.89],[19.487,-39.523],[19.594,-34.762],[14.592,-24.356],[5.47,-12.238],[-7.236,7.022],[-38.554,37.704],[-45.074,61.137]],"c":false},"ix":2},"nm":"Path 1","mn":"ADBE Vector Shape - Group","hd":false},{"ty":"st","c":{"a":0,"k":[1,1,1,1],"ix":3},"o":{"a":0,"k":40,"ix":4},"w":{"a":0,"k":1.427,"ix":5},"lc":1,"lj":1,"ml":4,"bm":0,"nm":"Stroke 1","mn":"ADBE Vector Graphic - Stroke","hd":false},{"ty":"tr","p":{"a":0,"k":[135.859,95.477],"ix":2},"a":{"a":0,"k":[0,0],"ix":1},"s":{"a":0,"k":[100,100],"ix":3},"r":{"a":0,"k":0,"ix":6},"o":{"a":0,"k":100,"ix":7},"sk":{"a":0,"k":0,"ix":4},"sa":{"a":0,"k":0,"ix":5},"nm":"Transform"}],"nm":"Group 4","np":2,"cix":2,"bm":0,"ix":4,"mn":"ADBE Vector Group","hd":false},{"ty":"gr","it":[{"ind":0,"ty":"sh","ix":1,"ks":{"a":0,"k":{"i":[[0,0],[-0.125,-1.944],[-0.232,-2.747],[1.035,-4.583],[0.767,-1.427],[1.213,-1.23],[2.835,-4.922]],"o":[[-0.16,1.034],[0.089,1.141],[0.393,5.671],[-0.624,2.71],[-0.553,1.034],[-3.62,3.656],[0,0]],"v":[[7.066,-24.075],[7.013,-19.608],[7.494,-13.776],[6.531,1.605],[4.445,7.811],[0.671,11.083],[-8.762,23.45]],"c":false},"ix":2},"nm":"Path 1","mn":"ADBE Vector Shape - Group","hd":false},{"ty":"st","c":{"a":0,"k":[1,1,1,1],"ix":3},"o":{"a":0,"k":40,"ix":4},"w":{"a":0,"k":1.427,"ix":5},"lc":1,"lj":1,"ml":4,"bm":0,"nm":"Stroke 1","mn":"ADBE Vector Graphic - Stroke","hd":false},{"ty":"tr","p":{"a":0,"k":[202.262,65.343],"ix":2},"a":{"a":0,"k":[0,0],"ix":1},"s":{"a":0,"k":[100,100],"ix":3},"r":{"a":0,"k":0,"ix":6},"o":{"a":0,"k":100,"ix":7},"sk":{"a":0,"k":0,"ix":4},"sa":{"a":0,"k":0,"ix":5},"nm":"Transform"}],"nm":"Group 5","np":2,"cix":2,"bm":0,"ix":5,"mn":"ADBE Vector Group","hd":false},{"ty":"gr","it":[{"ind":0,"ty":"sh","ix":1,"ks":{"a":0,"k":{"i":[[0,0],[0.642,-8.577],[1.052,-4.672],[3.495,-5.671],[3.442,-5.35],[1.836,-3.21]],"o":[[-0.054,0.339],[-0.589,7.633],[-1.088,4.744],[-0.143,0.214],[-2.461,3.816],[0,0]],"v":[[11.101,-33.17],[10.058,-19.795],[7.597,-1.337],[-0.403,14.16],[-4.655,22.631],[-8.351,28.92]],"c":false},"ix":2},"nm":"Path 1","mn":"ADBE Vector Shape - Group","hd":false},{"ty":"st","c":{"a":0,"k":[1,1,1,1],"ix":3},"o":{"a":0,"k":40,"ix":4},"w":{"a":0,"k":1.427,"ix":5},"lc":1,"lj":1,"ml":4,"bm":0,"nm":"Stroke 1","mn":"ADBE Vector Graphic - Stroke","hd":false},{"ty":"tr","p":{"a":0,"k":[192.903,65.61],"ix":2},"a":{"a":0,"k":[0,0],"ix":1},"s":{"a":0,"k":[100,100],"ix":3},"r":{"a":0,"k":0,"ix":6},"o":{"a":0,"k":100,"ix":7},"sk":{"a":0,"k":0,"ix":4},"sa":{"a":0,"k":0,"ix":5},"nm":"Transform"}],"nm":"Group 6","np":2,"cix":2,"bm":0,"ix":6,"mn":"ADBE Vector Group","hd":false},{"ty":"gr","it":[{"ind":0,"ty":"sh","ix":1,"ks":{"a":0,"k":{"i":[[2.14,-2.943],[2.978,-3.513],[8.043,-7.241],[2.265,-1.016],[27.546,-16.091],[8.333,-5.587],[1.106,-0.928],[6.634,-5.653],[0,0.553],[-0.286,4.297],[-1.98,9.077],[-18.065,24.021],[-2.443,2.443],[-4.066,1.48],[-7.383,-0.606],[-2.318,-0.463],[-0.499,-0.286],[-2.015,-2.746],[-1.284,-3.121],[-0.624,-0.999],[-2.14,-0.784],[-2.14,0.945],[-0.321,0.071],[-0.535,-0.41]],"o":[[-1.23,1.676],[-2.033,2.621],[-8.346,7.49],[-2.657,1.177],[-2.603,1.521],[-7.265,4.871],[-1.302,1.087],[-5.974,4.976],[-0.107,-2.728],[0.57,-8.543],[6.313,-28.855],[2.889,-3.852],[4.334,-4.351],[5.047,-1.837],[2.604,0.232],[1.944,0.411],[3.228,1.783],[1.337,1.837],[1.409,3.406],[1.338,2.104],[1.819,0.678],[1.088,-0.464],[0.696,-0.143],[0.999,0.785]],"v":[[58.297,-36.086],[51.984,-28.301],[35.745,-13.633],[19.579,-0.874],[-36.086,34.904],[-50.248,44.9],[-62.286,52.691],[-75.44,61.551],[-85.651,68.186],[-84.133,57.646],[-76.808,31.218],[-20.241,-48.096],[-12.243,-57.54],[0.357,-66.286],[19.001,-68.133],[26.384,-67.089],[30.049,-66.046],[37.914,-59.251],[41.846,-51.814],[44.895,-45.208],[50.112,-40.874],[56.05,-41.275],[58.163,-42.077],[60.009,-41.676]],"c":true},"ix":2},"nm":"Path 1","mn":"ADBE Vector Shape - Group","hd":false},{"ty":"fl","c":{"a":0,"k":[0.815699977501,0.211799995572,0.133300003351,1],"ix":4},"o":{"a":0,"k":100,"ix":5},"r":1,"bm":0,"nm":"Fill 1","mn":"ADBE Vector Graphic - Fill","hd":false},{"ty":"tr","p":{"a":0,"k":[167.776,93.965],"ix":2},"a":{"a":0,"k":[0,0],"ix":1},"s":{"a":0,"k":[100,100],"ix":3},"r":{"a":0,"k":0,"ix":6},"o":{"a":0,"k":100,"ix":7},"sk":{"a":0,"k":0,"ix":4},"sa":{"a":0,"k":0,"ix":5},"nm":"Transform"}],"nm":"Group 7","np":2,"cix":2,"bm":0,"ix":7,"mn":"ADBE Vector Group","hd":false},{"ty":"gr","it":[{"ind":0,"ty":"sh","ix":1,"ks":{"a":0,"k":{"i":[[0,0],[1.16,9.416],[2.372,8.311],[-6.599,11.252],[-15.176,18.047],[-4.869,2.835],[-7.079,2.497],[-9.059,-1.248],[-4.887,-2.711]],"o":[[0.981,-7.276],[-0.998,-8.061],[-2.105,-7.383],[5.278,-9.006],[1.926,-2.283],[5.564,-3.228],[8.418,-2.96],[6.724,0.927],[0,0]],"v":[[-68.73,70.417],[-68.997,44.066],[-54.053,19.509],[-47.311,-8.444],[-16.63,-49.024],[-6.438,-56.701],[12.527,-65.288],[38.743,-67.856],[56.158,-62.399]],"c":false},"ix":2},"nm":"Path 1","mn":"ADBE Vector Shape - Group","hd":false},{"ty":"st","c":{"a":0,"k":[1,1,1,1],"ix":3},"o":{"a":0,"k":40,"ix":4},"w":{"a":0,"k":1.427,"ix":5},"lc":1,"lj":1,"ml":4,"bm":0,"nm":"Stroke 1","mn":"ADBE Vector Graphic - Stroke","hd":false},{"ty":"tr","p":{"a":0,"k":[120.027,88.152],"ix":2},"a":{"a":0,"k":[0,0],"ix":1},"s":{"a":0,"k":[100,100],"ix":3},"r":{"a":0,"k":0,"ix":6},"o":{"a":0,"k":100,"ix":7},"sk":{"a":0,"k":0,"ix":4},"sa":{"a":0,"k":0,"ix":5},"nm":"Transform"}],"nm":"Group 8","np":2,"cix":2,"bm":0,"ix":8,"mn":"ADBE Vector Group","hd":false},{"ty":"gr","it":[{"ind":0,"ty":"sh","ix":1,"ks":{"a":0,"k":{"i":[[0,0],[13.963,-8.738],[4.334,-3.335],[0.838,-1.123],[4.601,-11.164],[3.513,-10.29],[1.73,-4.743],[0.553,-2.051],[-0.285,-7.169],[-0.998,-3.692]],"o":[[-8.916,1.052],[-5.029,3.157],[-3.834,2.925],[-5.671,7.562],[-1.356,3.281],[-0.089,0.267],[-1.034,2.871],[-1.534,5.76],[0.785,19.599],[0,0]],"v":[[42.675,-74.085],[8.355,-59.398],[-5.689,-49.661],[-12.697,-43.59],[-28.105,-15.501],[-35.408,4.856],[-38.137,12.372],[-40.517,19.754],[-42.39,39.149],[-39.527,75.647]],"c":false},"ix":2},"nm":"Path 1","mn":"ADBE Vector Shape - Group","hd":false},{"ty":"st","c":{"a":0,"k":[1,1,1,1],"ix":3},"o":{"a":0,"k":40,"ix":4},"w":{"a":0,"k":1.427,"ix":5},"lc":1,"lj":1,"ml":4,"bm":0,"nm":"Stroke 1","mn":"ADBE Vector Graphic - Stroke","hd":false},{"ty":"tr","p":{"a":0,"k":[86.402,81.165],"ix":2},"a":{"a":0,"k":[0,0],"ix":1},"s":{"a":0,"k":[100,100],"ix":3},"r":{"a":0,"k":0,"ix":6},"o":{"a":0,"k":100,"ix":7},"sk":{"a":0,"k":0,"ix":4},"sa":{"a":0,"k":0,"ix":5},"nm":"Transform"}],"nm":"Group 9","np":2,"cix":2,"bm":0,"ix":9,"mn":"ADBE Vector Group","hd":false},{"ty":"gr","it":[{"ind":0,"ty":"sh","ix":1,"ks":{"a":0,"k":{"i":[[0,0],[1.195,11.039],[0.107,0.588],[-0.268,1.641],[-0.892,4.12],[-8.222,12.786],[-7.241,8.292],[-2.835,2.318],[-3.923,2.55],[-8.828,1.035],[-10.29,-3.817],[-3.264,-1.854],[-1.213,-1.213]],"o":[[-0.624,-2.336],[-1.266,-11.752],[-1.07,-5.725],[0.891,-2.746],[0.856,-3.994],[8.453,-13.126],[1.052,-1.195],[3.549,-2.907],[11.2,-7.294],[9.041,-1.052],[3.869,1.444],[2.835,1.605],[0,0]],"v":[[-60.089,74.047],[-62.943,52.047],[-65.002,33.536],[-66.206,22.488],[-63.531,12.189],[-49.915,-12.982],[-26.375,-45.109],[-20.544,-50.379],[-9.336,-58.564],[20.705,-71.057],[49.702,-66.91],[60.402,-61.962],[66.474,-57.735]],"c":false},"ix":2},"nm":"Path 1","mn":"ADBE Vector Shape - Group","hd":false},{"ty":"st","c":{"a":0,"k":[1,1,1,1],"ix":3},"o":{"a":0,"k":40,"ix":4},"w":{"a":0,"k":1.427,"ix":5},"lc":1,"lj":1,"ml":4,"bm":0,"nm":"Stroke 1","mn":"ADBE Vector Graphic - Stroke","hd":false},{"ty":"tr","p":{"a":0,"k":[118.538,83.488],"ix":2},"a":{"a":0,"k":[0,0],"ix":1},"s":{"a":0,"k":[100,100],"ix":3},"r":{"a":0,"k":0,"ix":6},"o":{"a":0,"k":100,"ix":7},"sk":{"a":0,"k":0,"ix":4},"sa":{"a":0,"k":0,"ix":5},"nm":"Transform"}],"nm":"Group 10","np":2,"cix":2,"bm":0,"ix":10,"mn":"ADBE Vector Group","hd":false},{"ty":"gr","it":[{"ind":0,"ty":"sh","ix":1,"ks":{"a":0,"k":{"i":[[0,0],[0.606,6.741],[-0.749,6.01],[-3.852,7.419],[-8.791,11.895],[-3.157,1.961],[-4.69,1.016],[-2.621,0.054],[-3.317,-1.837]],"o":[[-1.854,-19.01],[-0.981,-10.86],[0.874,-7.169],[3.638,-7.008],[1.944,-2.621],[3.567,-2.212],[6.349,-1.391],[3.799,-0.089],[0,0]],"v":[[-50.536,64.696],[-34.227,25.444],[-34.574,0.139],[-27.486,-21.743],[-8.842,-50.099],[-1.19,-56.973],[11.195,-61.815],[24.65,-63.982],[35.324,-61.36]],"c":false},"ix":2},"nm":"Path 1","mn":"ADBE Vector Shape - Group","hd":false},{"ty":"st","c":{"a":0,"k":[1,1,1,1],"ix":3},"o":{"a":0,"k":40,"ix":4},"w":{"a":0,"k":1.427,"ix":5},"lc":1,"lj":1,"ml":4,"bm":0,"nm":"Stroke 1","mn":"ADBE Vector Graphic - Stroke","hd":false},{"ty":"tr","p":{"a":0,"k":[122.109,95.7],"ix":2},"a":{"a":0,"k":[0,0],"ix":1},"s":{"a":0,"k":[100,100],"ix":3},"r":{"a":0,"k":0,"ix":6},"o":{"a":0,"k":100,"ix":7},"sk":{"a":0,"k":0,"ix":4},"sa":{"a":0,"k":0,"ix":5},"nm":"Transform"}],"nm":"Group 11","np":2,"cix":2,"bm":0,"ix":11,"mn":"ADBE Vector Group","hd":false},{"ty":"gr","it":[{"ind":0,"ty":"sh","ix":1,"ks":{"a":0,"k":{"i":[[0,0],[16.014,-10.361],[5.225,-3.941],[1.07,-1.141],[5.118,-17.833],[1.337,-6.616],[0.285,-2.675],[0.659,-4.743],[0.499,-5.368],[-0.481,-4.636],[-0.767,-2.871]],"o":[[-8.81,1.034],[-5.546,3.585],[-4.351,3.299],[-6.438,6.866],[-1.783,6.224],[-1.052,5.118],[-0.339,2.996],[-0.5,3.531],[-0.179,2.086],[0.5,4.833],[0,0]],"v":[[44.361,-74.82],[7.124,-57.727],[-9.033,-46.438],[-17.164,-39.778],[-34.499,-2.729],[-39.18,16.532],[-41.186,28.222],[-42.684,39.83],[-44.182,53.18],[-43.727,63.264],[-41.827,74.82]],"c":false},"ix":2},"nm":"Path 1","mn":"ADBE Vector Shape - Group","hd":false},{"ty":"st","c":{"a":0,"k":[1,1,1,1],"ix":3},"o":{"a":0,"k":40,"ix":4},"w":{"a":0,"k":1.427,"ix":5},"lc":1,"lj":1,"ml":4,"bm":0,"nm":"Stroke 1","mn":"ADBE Vector Graphic - Stroke","hd":false},{"ty":"tr","p":{"a":0,"k":[55.559,78.103],"ix":2},"a":{"a":0,"k":[0,0],"ix":1},"s":{"a":0,"k":[100,100],"ix":3},"r":{"a":0,"k":0,"ix":6},"o":{"a":0,"k":100,"ix":7},"sk":{"a":0,"k":0,"ix":4},"sa":{"a":0,"k":0,"ix":5},"nm":"Transform"}],"nm":"Group 12","np":2,"cix":2,"bm":0,"ix":12,"mn":"ADBE Vector Group","hd":false},{"ty":"gr","it":[{"ind":0,"ty":"sh","ix":1,"ks":{"a":0,"k":{"i":[[0,0],[13.571,-9.47],[4.315,-3.656],[0.928,-1.195],[6.741,-17.744],[1.784,-6.045],[0.054,-2.051],[0.695,-3.638],[-1.855,-6.991],[-1.587,-5.154],[-0.571,-2.104]],"o":[[-8.827,1.034],[-4.761,3.335],[-3.621,3.067],[-6.099,7.829],[-2.639,6.955],[-1.712,5.814],[-0.125,3.567],[-0.25,3.371],[0.321,1.195],[1.623,5.278],[0,0]],"v":[[42.029,-74.619],[8.43,-58.863],[-5.185,-48.377],[-12.007,-41.984],[-31.267,-3.625],[-37.9,15.876],[-40.549,27.673],[-41.779,38.48],[-39.372,54.022],[-36.51,63.545],[-33.219,74.619]],"c":false},"ix":2},"nm":"Path 1","mn":"ADBE Vector Shape - Group","hd":false},{"ty":"st","c":{"a":0,"k":[1,1,1,1],"ix":3},"o":{"a":0,"k":40,"ix":4},"w":{"a":0,"k":1.427,"ix":5},"lc":1,"lj":1,"ml":4,"bm":0,"nm":"Stroke 1","mn":"ADBE Vector Graphic - Stroke","hd":false},{"ty":"tr","p":{"a":0,"k":[67.254,78.972],"ix":2},"a":{"a":0,"k":[0,0],"ix":1},"s":{"a":0,"k":[100,100],"ix":3},"r":{"a":0,"k":0,"ix":6},"o":{"a":0,"k":100,"ix":7},"sk":{"a":0,"k":0,"ix":4},"sa":{"a":0,"k":0,"ix":5},"nm":"Transform"}],"nm":"Group 13","np":2,"cix":2,"bm":0,"ix":13,"mn":"ADBE Vector Group","hd":false},{"ty":"gr","it":[{"ind":0,"ty":"sh","ix":1,"ks":{"a":0,"k":{"i":[[-0.78,1.851],[-10.811,0.733],[-10.16,-2.71],[-7.495,-3.696],[-12.757,14.302],[5.194,-21.178],[3.709,-15.836],[0.57,-0.606],[5.047,0.696],[5.885,0.301],[19.724,1.053],[5.814,0.785],[-1.908,10.914],[-3.46,12.359],[-3.763,9.737]],"o":[[-1.524,9.957],[7.58,-0.513],[10.836,2.889],[15.232,7.511],[-5.713,13.508],[0,0.054],[-1.57,6.687],[-2.711,0],[-4.636,-0.66],[-12.49,-1.324],[-23.397,-1.248],[-0.767,-4.744],[1.748,-10.022],[3.442,-12.198],[0.82,-2.12]],"v":[[-42.544,-53.121],[-26.531,-44.352],[0.798,-42.805],[27.843,-31.923],[66.032,-33.684],[29.671,18.345],[21.857,42.18],[17.397,53.12],[9.26,52.077],[-1.556,51.303],[-24.583,48.094],[-65.274,42.795],[-63.562,19.308],[-55.751,-14.263],[-44.944,-47.165]],"c":true},"ix":2},"nm":"Path 1","mn":"ADBE Vector Shape - Group","hd":false},{"ty":"fl","c":{"a":0,"k":[0.956900024414,0.51760002585,0.415699977501,1],"ix":4},"o":{"a":0,"k":100,"ix":5},"r":1,"bm":0,"nm":"Fill 1","mn":"ADBE Vector Graphic - Fill","hd":false},{"ty":"tr","p":{"a":0,"k":[66.032,108.924],"ix":2},"a":{"a":0,"k":[0,0],"ix":1},"s":{"a":0,"k":[100,100],"ix":3},"r":{"a":0,"k":0,"ix":6},"o":{"a":0,"k":100,"ix":7},"sk":{"a":0,"k":0,"ix":4},"sa":{"a":0,"k":0,"ix":5},"nm":"Transform"}],"nm":"Group 14","np":4,"cix":2,"bm":0,"ix":14,"mn":"ADBE Vector Group","hd":false},{"ty":"gr","it":[{"ind":0,"ty":"sh","ix":1,"ks":{"a":0,"k":{"i":[[-4.922,-0.553],[-7.757,-1.159],[-5.207,-0.464],[-12.733,-4.851],[-7.258,-4.084],[3.103,0.107],[4.833,-0.66],[3.05,-1.516],[3.727,-2.889],[5.778,-11.895],[6.242,-25.448],[3.709,-15.836],[0.571,-0.606],[5.047,0.696],[2.408,0.606],[19.723,1.052],[5.814,0.784],[-1.908,10.914],[-3.459,12.359],[-3.763,9.737],[-3.05,3.923],[-3.014,2.889],[-4.102,3.263],[-8.756,2.657],[-4.619,0.285]],"o":[[1.962,0.214],[6.795,1.017],[9.648,0.856],[9.416,3.584],[-1.605,-0.428],[-4.19,-0.125],[-1.748,0.232],[-3.691,1.836],[-10.147,7.847],[-6.99,14.373],[0,0.054],[-1.569,6.687],[-2.711,0],[-4.637,-0.66],[-7.044,-1.837],[-23.398,-1.248],[-0.767,-4.744],[1.748,-10.022],[3.442,-12.198],[4.031,-10.415],[1.07,-1.374],[3.656,-3.477],[11.502,-9.167],[4.779,-1.445],[3.906,-0.25]],"v":[[8.016,-78.734],[22.595,-76.675],[40.598,-74.454],[74.169,-65.894],[99.18,-54.392],[92.118,-55.194],[78.583,-54.392],[71.387,-51.77],[60.259,-44.682],[36.371,-15.069],[-3.477,44.663],[-11.291,68.499],[-15.751,79.439],[-23.887,78.396],[-34.454,76.497],[-54.605,72.163],[-98.422,69.113],[-96.71,45.626],[-88.899,12.055],[-78.092,-20.846],[-67.472,-42.354],[-61.346,-48.748],[-49.71,-58.859],[-19.322,-76.594],[-5.225,-79.189]],"c":true},"ix":2},"nm":"Path 1","mn":"ADBE Vector Shape - Group","hd":false},{"ty":"fl","c":{"a":0,"k":[0.992200006223,0.576499968884,0.486300000957,1],"ix":4},"o":{"a":0,"k":100,"ix":5},"r":1,"bm":0,"nm":"Fill 1","mn":"ADBE Vector Graphic - Fill","hd":false},{"ty":"tr","p":{"a":0,"k":[99.18,82.606],"ix":2},"a":{"a":0,"k":[0,0],"ix":1},"s":{"a":0,"k":[100,100],"ix":3},"r":{"a":0,"k":0,"ix":6},"o":{"a":0,"k":100,"ix":7},"sk":{"a":0,"k":0,"ix":4},"sa":{"a":0,"k":0,"ix":5},"nm":"Transform"}],"nm":"Group 15","np":4,"cix":2,"bm":0,"ix":15,"mn":"ADBE Vector Group","hd":false}],"ip":0,"op":638.000025986273,"st":0,"bm":0},{"ddd":0,"ind":5,"ty":4,"nm":"fish salmon steak - cut 2","sr":1,"ks":{"o":{"a":0,"k":100,"ix":11},"r":{"a":0,"k":0,"ix":10},"p":{"a":0,"k":[421.778,288.444,0],"ix":2},"a":{"a":0,"k":[108.5,79.5,0],"ix":1},"s":{"a":0,"k":[200,200,100],"ix":6}},"ao":0,"shapes":[{"ty":"gr","it":[{"ind":0,"ty":"sh","ix":1,"ks":{"a":1,"k":[{"i":{"x":0.833,"y":0.833},"o":{"x":0.167,"y":0.167},"t":138,"s":[{"i":[[0,0],[0.107,0.588],[-0.268,1.641],[-0.892,4.12],[-8.222,12.786],[-7.241,8.292],[-2.835,2.318],[-3.923,2.551],[-8.828,1.035]],"o":[[6.848,-28.547],[-1.07,-5.725],[0.891,-2.746],[0.856,-3.994],[8.453,-13.126],[1.052,-1.195],[3.549,-2.907],[11.2,-7.293],[0,0]],"v":[[-44.158,70.43],[-42.556,31.789],[-42.754,23.115],[-40.079,12.816],[-26.463,-12.355],[-2.923,-44.482],[2.908,-49.752],[14.117,-57.938],[44.158,-70.43]],"c":false}]},{"i":{"x":0.833,"y":0.833},"o":{"x":0.167,"y":0.167},"t":149,"s":[{"i":[[0,0],[0.107,0.588],[-0.268,1.641],[-0.892,4.12],[-8.222,12.786],[-7.241,8.292],[-2.835,2.318],[-3.923,2.551],[-8.828,1.035]],"o":[[6.137,-28.012],[-1.07,-5.725],[0.891,-2.746],[0.856,-3.994],[8.453,-13.126],[1.052,-1.195],[3.549,-2.907],[11.2,-7.293],[0,0]],"v":[[-44.158,70.43],[-42.556,31.789],[-43.254,23.115],[-42.329,12.816],[-26.463,-12.355],[-2.923,-44.482],[2.908,-49.752],[14.117,-57.938],[44.158,-70.43]],"c":false}]},{"t":170.000006924242,"s":[{"i":[[0,0],[0.107,0.588],[-0.268,1.641],[-0.892,4.12],[-8.222,12.786],[-7.241,8.292],[-2.835,2.318],[-3.923,2.551],[-8.828,1.035]],"o":[[9.387,-25.262],[-1.07,-5.725],[0.891,-2.746],[0.856,-3.994],[8.453,-13.126],[1.052,-1.195],[3.549,-2.907],[11.2,-7.293],[0,0]],"v":[[-44.158,70.43],[-42.556,31.789],[-44.004,21.865],[-41.329,11.566],[-26.463,-12.355],[-2.923,-44.482],[2.908,-49.752],[14.117,-57.938],[44.158,-70.43]],"c":false}]}],"ix":2},"nm":"Path 1","mn":"ADBE Vector Shape - Group","hd":false},{"ty":"st","c":{"a":0,"k":[1,1,1,1],"ix":3},"o":{"a":0,"k":40,"ix":4},"w":{"a":0,"k":1.427,"ix":5},"lc":1,"lj":1,"ml":4,"bm":0,"nm":"Stroke 1","mn":"ADBE Vector Graphic - Stroke","hd":false},{"ty":"tr","p":{"a":0,"k":[95.132,82.861],"ix":2},"a":{"a":0,"k":[0,0],"ix":1},"s":{"a":0,"k":[100,100],"ix":3},"r":{"a":0,"k":0,"ix":6},"o":{"a":0,"k":100,"ix":7},"sk":{"a":0,"k":0,"ix":4},"sa":{"a":0,"k":0,"ix":5},"nm":"Transform"}],"nm":"Group 1","np":2,"cix":2,"bm":0,"ix":1,"mn":"ADBE Vector Group","hd":false},{"ty":"gr","it":[{"ind":0,"ty":"sh","ix":1,"ks":{"a":1,"k":[{"i":{"x":0.833,"y":0.833},"o":{"x":0.167,"y":0.167},"t":138,"s":[{"i":[[0,0],[2.78,-3.596],[-0.275,-3.203],[5.458,-13.187],[5.259,-5.507],[9.39,-9.272],[2.428,-3.615],[1.677,-1.18],[0.852,-0.956],[-1.226,-8.167]],"o":[[-2.629,1.705],[-3.405,4.459],[0.476,5.526],[-5.534,13.393],[-2.554,2.679],[-4.031,4.009],[-0.501,0.768],[-1.903,1.33],[-3.18,3.577],[0,0]],"v":[[37.777,-64.836],[29.664,-56.885],[24.969,-45.393],[17.495,-17.324],[1.307,11.026],[-16.61,28.952],[-26.3,40.388],[-29.568,43.31],[-33.7,46.738],[-36.552,64.836]],"c":false}]},{"i":{"x":0.833,"y":0.833},"o":{"x":0.167,"y":0.167},"t":149,"s":[{"i":[[0,0],[2.78,-3.596],[-0.275,-3.203],[5.458,-13.187],[5.259,-5.507],[9.39,-9.272],[2.428,-3.615],[1.677,-1.18],[0.852,-0.956],[-1.226,-8.167]],"o":[[-2.629,1.705],[-3.405,4.459],[0.476,5.526],[-5.534,13.393],[-2.554,2.679],[-4.031,4.009],[-0.501,0.768],[-1.903,1.33],[-3.18,3.577],[0,0]],"v":[[37.777,-64.836],[29.664,-56.885],[24.969,-45.393],[17.495,-17.324],[1.807,11.026],[-16.61,28.952],[-24.8,40.638],[-28.068,43.81],[-32.2,46.988],[-36.552,64.836]],"c":false}]},{"t":170.000006924242,"s":[{"i":[[0,0],[2.78,-3.596],[-0.275,-3.203],[5.458,-13.187],[5.259,-5.507],[9.39,-9.272],[2.428,-3.615],[1.677,-1.18],[0.852,-0.956],[-1.226,-8.167]],"o":[[-2.629,1.705],[-3.405,4.459],[0.476,5.526],[-5.534,13.393],[-2.554,2.679],[-4.031,4.009],[-0.501,0.768],[-1.903,1.33],[-3.18,3.577],[0,0]],"v":[[37.777,-64.836],[29.664,-56.885],[24.969,-45.393],[21.245,-17.324],[3.806,11.026],[-15.36,28.952],[-25.05,40.388],[-28.318,43.31],[-32.45,46.738],[-36.552,64.836]],"c":false}]}],"ix":2},"nm":"Path 1","mn":"ADBE Vector Shape - Group","hd":false},{"ty":"st","c":{"a":0,"k":[1,1,1,1],"ix":3},"o":{"a":0,"k":40,"ix":4},"w":{"a":0,"k":1.427,"ix":5},"lc":1,"lj":1,"ml":4,"bm":0,"nm":"Stroke 1","mn":"ADBE Vector Graphic - Stroke","hd":false},{"ty":"tr","p":{"a":0,"k":[105.762,77.079],"ix":2},"a":{"a":0,"k":[0,0],"ix":1},"s":{"a":0,"k":[100,100],"ix":3},"r":{"a":0,"k":0,"ix":6},"o":{"a":0,"k":100,"ix":7},"sk":{"a":0,"k":0,"ix":4},"sa":{"a":0,"k":0,"ix":5},"nm":"Transform"}],"nm":"Group 2","np":2,"cix":2,"bm":0,"ix":2,"mn":"ADBE Vector Group","hd":false},{"ty":"gr","it":[{"ind":0,"ty":"sh","ix":1,"ks":{"a":1,"k":[{"i":{"x":0.833,"y":0.833},"o":{"x":0.167,"y":0.167},"t":0,"s":[{"i":[[0,0],[1.453,-5.732],[1.653,-5.469],[6.36,-10.921],[6.611,-8.598]],"o":[[-0.776,3.634],[-1.878,7.455],[-1.853,6.107],[-6.235,10.714],[0,0]],"v":[[19.554,-41.817],[16.737,-29.828],[11.441,-10.441],[-0.878,15.099],[-20.147,44.067]],"c":false}]},{"i":{"x":0.833,"y":0.833},"o":{"x":0.167,"y":0.167},"t":138,"s":[{"i":[[0,0],[1.453,-5.732],[1.653,-5.469],[6.36,-10.921],[6.611,-8.598]],"o":[[-0.776,3.634],[-1.878,7.455],[-1.853,6.107],[-6.235,10.714],[0,0]],"v":[[20.148,-44.067],[16.737,-29.828],[11.441,-10.441],[-0.878,15.099],[-20.147,44.067]],"c":false}]},{"i":{"x":0.833,"y":0.833},"o":{"x":0.167,"y":0.167},"t":149,"s":[{"i":[[0,0],[1.453,-5.732],[1.653,-5.469],[6.36,-10.921],[6.611,-8.598]],"o":[[-0.776,3.634],[-1.878,7.455],[-1.853,6.107],[-6.235,10.714],[0,0]],"v":[[20.148,-44.067],[16.737,-29.828],[11.441,-10.441],[-0.878,15.099],[-20.147,44.067]],"c":false}]},{"i":{"x":0.833,"y":0.833},"o":{"x":0.167,"y":0.167},"t":170,"s":[{"i":[[0,0],[1.453,-5.732],[1.653,-5.469],[6.36,-10.921],[6.611,-8.598]],"o":[[-0.776,3.634],[-1.878,7.455],[-1.853,6.107],[-6.235,10.714],[0,0]],"v":[[20.148,-44.067],[16.737,-29.828],[11.441,-10.441],[-0.878,15.099],[-20.147,44.067]],"c":false}]},{"t":663.000027004544,"s":[{"i":[[0,0],[1.453,-5.732],[1.653,-5.469],[6.36,-10.921],[6.611,-8.598]],"o":[[-0.776,3.634],[-1.878,7.455],[-1.853,6.107],[-6.235,10.714],[0,0]],"v":[[19.71,-41.692],[16.737,-29.828],[11.441,-10.441],[-0.878,15.099],[-20.147,44.067]],"c":false}]}],"ix":2},"nm":"Path 1","mn":"ADBE Vector Shape - Group","hd":false},{"ty":"st","c":{"a":0,"k":[1,1,1,1],"ix":3},"o":{"a":0,"k":40,"ix":4},"w":{"a":0,"k":1.427,"ix":5},"lc":1,"lj":1,"ml":4,"bm":0,"nm":"Stroke 1","mn":"ADBE Vector Graphic - Stroke","hd":false},{"ty":"tr","p":{"a":0,"k":[152.005,58.086],"ix":2},"a":{"a":0,"k":[0,0],"ix":1},"s":{"a":0,"k":[100,100],"ix":3},"r":{"a":0,"k":0,"ix":6},"o":{"a":0,"k":100,"ix":7},"sk":{"a":0,"k":0,"ix":4},"sa":{"a":0,"k":0,"ix":5},"nm":"Transform"}],"nm":"Group 3","np":2,"cix":2,"bm":0,"ix":3,"mn":"ADBE Vector Group","hd":false},{"ty":"gr","it":[{"ind":0,"ty":"sh","ix":1,"ks":{"a":1,"k":[{"i":{"x":0.833,"y":0.833},"o":{"x":0.167,"y":0.167},"t":138,"s":[{"i":[[0,0],[2.079,-5.956],[1.177,-3.84],[10.667,-14.105],[2.805,-4.87],[2.554,-2.548],[3.281,-3.072],[2.329,-7.005]],"o":[[-0.401,1.836],[-2.604,7.512],[-1.377,4.552],[-12.52,16.559],[-1.252,2.173],[-1.502,1.479],[-6.26,6.144],[0,0]],"v":[[38.119,-61.592],[34.4,-49.904],[28.729,-32.877],[10.662,-4.892],[-12.325,27.251],[-18.035,34.332],[-25.209,41.159],[-38.119,61.592]],"c":false}]},{"i":{"x":0.833,"y":0.833},"o":{"x":0.167,"y":0.167},"t":149,"s":[{"i":[[0,0],[2.079,-5.956],[1.177,-3.84],[10.667,-14.105],[2.805,-4.87],[2.554,-2.548],[3.281,-3.072],[2.329,-7.005]],"o":[[-0.401,1.836],[-2.604,7.512],[-1.377,4.552],[-12.52,16.559],[-1.252,2.173],[-1.502,1.479],[-6.26,6.144],[0,0]],"v":[[38.119,-61.592],[34.4,-49.904],[28.729,-32.877],[10.662,-4.892],[-12.325,27.251],[-18.035,34.332],[-25.209,41.159],[-38.119,61.592]],"c":false}]},{"t":170.000006924242,"s":[{"i":[[0,0],[2.079,-5.956],[1.177,-3.84],[10.667,-14.105],[2.805,-4.87],[2.554,-2.548],[3.281,-3.072],[2.329,-7.005]],"o":[[-0.401,1.836],[-2.604,7.512],[-1.377,4.552],[-12.52,16.559],[-1.252,2.173],[-1.502,1.479],[-6.26,6.144],[0,0]],"v":[[38.119,-61.592],[34.4,-49.904],[28.729,-32.877],[14.412,-4.892],[-7.325,27.251],[-15.535,34.332],[-22.709,41.159],[-38.119,61.592]],"c":false}]}],"ix":2},"nm":"Path 1","mn":"ADBE Vector Shape - Group","hd":false},{"ty":"st","c":{"a":0,"k":[1,1,1,1],"ix":3},"o":{"a":0,"k":40,"ix":4},"w":{"a":0,"k":1.427,"ix":5},"lc":1,"lj":1,"ml":4,"bm":0,"nm":"Stroke 1","mn":"ADBE Vector Graphic - Stroke","hd":false},{"ty":"tr","p":{"a":0,"k":[117.816,73.835],"ix":2},"a":{"a":0,"k":[0,0],"ix":1},"s":{"a":0,"k":[100,100],"ix":3},"r":{"a":0,"k":0,"ix":6},"o":{"a":0,"k":100,"ix":7},"sk":{"a":0,"k":0,"ix":4},"sa":{"a":0,"k":0,"ix":5},"nm":"Transform"}],"nm":"Group 4","np":2,"cix":2,"bm":0,"ix":4,"mn":"ADBE Vector Group","hd":false},{"ty":"gr","it":[{"ind":0,"ty":"sh","ix":1,"ks":{"a":1,"k":[{"i":{"x":0.833,"y":0.833},"o":{"x":0.167,"y":0.167},"t":138,"s":[{"i":[[0,0],[0.576,-2.979],[-0.325,-4.047],[-0.5,-3.784],[0.175,-1.255],[4.257,-4.252],[0,0],[2.98,-4.852],[5.509,-16.633],[2.203,-8.073]],"o":[[-1.803,1.18],[-0.451,2.472],[0.05,0.674],[0.276,2.079],[-0.426,3.034],[0,0],[-8.914,8.635],[-2.98,4.851],[-2.729,8.336],[0,0]],"v":[[30.292,-64.216],[26.724,-57.978],[26.536,-48.2],[27.362,-41.513],[27.513,-36.512],[20.489,-25.582],[7.681,-12.854],[-10.16,7.376],[-22.893,39.603],[-30.292,64.216]],"c":false}]},{"i":{"x":0.833,"y":0.833},"o":{"x":0.167,"y":0.167},"t":149,"s":[{"i":[[0,0],[0.576,-2.979],[-0.325,-4.047],[-0.5,-3.784],[0.175,-1.255],[4.257,-4.252],[0,0],[2.98,-4.852],[10.837,-15.803],[2.203,-8.073]],"o":[[-1.803,1.18],[-0.451,2.472],[0.05,0.674],[0.276,2.079],[-0.426,3.034],[0,0],[-8.914,8.635],[-2.98,4.851],[-2.729,8.336],[0,0]],"v":[[30.292,-64.216],[26.724,-57.978],[26.536,-48.2],[27.362,-41.513],[27.513,-36.512],[20.489,-25.582],[8.931,-12.854],[-2.66,7.626],[-22.893,39.603],[-30.292,64.216]],"c":false}]},{"t":170.000006924242,"s":[{"i":[[0,0],[0.576,-2.979],[-0.325,-4.047],[-0.5,-3.784],[0.175,-1.255],[4.257,-4.252],[0,0],[2.98,-4.852],[5.509,-16.633],[2.203,-8.073]],"o":[[-1.803,1.18],[-0.451,2.472],[0.05,0.674],[0.276,2.079],[-0.426,3.034],[0,0],[-8.914,8.635],[-2.98,4.851],[-2.729,8.336],[0,0]],"v":[[30.292,-64.216],[26.724,-57.978],[26.536,-48.2],[27.362,-41.513],[27.513,-36.512],[20.489,-25.582],[6.931,-15.104],[-3.16,0.876],[-20.393,39.603],[-30.292,64.216]],"c":false}]}],"ix":2},"nm":"Path 1","mn":"ADBE Vector Shape - Group","hd":false},{"ty":"st","c":{"a":0,"k":[1,1,1,1],"ix":3},"o":{"a":0,"k":40,"ix":4},"w":{"a":0,"k":1.427,"ix":5},"lc":1,"lj":1,"ml":4,"bm":0,"nm":"Stroke 1","mn":"ADBE Vector Graphic - Stroke","hd":false},{"ty":"tr","p":{"a":0,"k":[86.917,85.478],"ix":2},"a":{"a":0,"k":[0,0],"ix":1},"s":{"a":0,"k":[100,100],"ix":3},"r":{"a":0,"k":0,"ix":6},"o":{"a":0,"k":100,"ix":7},"sk":{"a":0,"k":0,"ix":4},"sa":{"a":0,"k":0,"ix":5},"nm":"Transform"}],"nm":"Group 5","np":2,"cix":2,"bm":0,"ix":5,"mn":"ADBE Vector Group","hd":false},{"ty":"gr","it":[{"ind":0,"ty":"sh","ix":1,"ks":{"a":1,"k":[{"i":{"x":0.833,"y":0.833},"o":{"x":0.167,"y":0.167},"t":138,"s":[{"i":[[0,0],[-0.175,-2.041],[-0.325,-2.885],[1.452,-4.814],[1.077,-1.498],[1.703,-1.292],[3.982,-5.17]],"o":[[-0.225,1.087],[0.125,1.199],[0.551,5.956],[-0.876,2.847],[-0.776,1.086],[-5.083,3.84],[0,0]],"v":[[9.922,-25.287],[9.847,-20.595],[10.523,-14.469],[9.171,1.687],[6.241,8.204],[2.523,11.772],[-11.074,25.287]],"c":false}]},{"i":{"x":0.833,"y":0.833},"o":{"x":0.167,"y":0.167},"t":149,"s":[{"i":[[0,0],[-0.175,-2.041],[-0.325,-2.885],[1.452,-4.814],[1.077,-1.498],[1.703,-1.292],[3.982,-5.17]],"o":[[-0.225,1.087],[0.125,1.199],[0.551,5.956],[-0.876,2.847],[-0.776,1.086],[-5.083,3.84],[0,0]],"v":[[9.922,-25.287],[9.847,-20.595],[10.523,-14.469],[9.171,1.687],[6.241,8.204],[2.523,11.772],[-11.074,25.287]],"c":false}]},{"t":170.000006924242,"s":[{"i":[[0,0],[-0.175,-2.041],[-0.325,-2.885],[1.452,-4.814],[1.077,-1.498],[1.703,-1.292],[3.982,-5.17]],"o":[[-0.225,1.087],[0.125,1.199],[0.551,5.956],[-0.876,2.847],[-0.776,1.086],[-5.083,3.84],[0,0]],"v":[[9.922,-25.287],[9.847,-20.595],[10.523,-14.469],[9.171,1.687],[6.241,8.204],[2.523,11.772],[-11.074,25.287]],"c":false}]}],"ix":2},"nm":"Path 1","mn":"ADBE Vector Shape - Group","hd":false},{"ty":"st","c":{"a":0,"k":[1,1,1,1],"ix":3},"o":{"a":0,"k":40,"ix":4},"w":{"a":0,"k":1.427,"ix":5},"lc":1,"lj":1,"ml":4,"bm":0,"nm":"Stroke 1","mn":"ADBE Vector Graphic - Stroke","hd":false},{"ty":"tr","p":{"a":0,"k":[180.154,53.826],"ix":2},"a":{"a":0,"k":[0,0],"ix":1},"s":{"a":0,"k":[100,100],"ix":3},"r":{"a":0,"k":0,"ix":6},"o":{"a":0,"k":100,"ix":7},"sk":{"a":0,"k":0,"ix":4},"sa":{"a":0,"k":0,"ix":5},"nm":"Transform"}],"nm":"Group 6","np":2,"cix":2,"bm":0,"ix":6,"mn":"ADBE Vector Group","hd":false},{"ty":"gr","it":[{"ind":0,"ty":"sh","ix":1,"ks":{"a":1,"k":[{"i":{"x":0.833,"y":0.833},"o":{"x":0.167,"y":0.167},"t":0,"s":[{"i":[[0,0],[0.901,-9.01],[1.478,-4.908],[4.908,-5.957],[4.833,-5.62],[2.579,-3.371]],"o":[[-0.075,0.356],[-0.826,8.017],[-1.527,4.982],[-0.2,0.224],[-3.456,4.008],[0,0]],"v":[[15.306,-33.247],[14.122,-20.791],[10.667,-1.404],[1.014,15.004],[-6.535,23.77],[-15.587,34.84]],"c":false}]},{"i":{"x":0.833,"y":0.833},"o":{"x":0.167,"y":0.167},"t":138,"s":[{"i":[[0,0],[0.901,-9.01],[1.478,-4.908],[4.908,-5.957],[4.833,-5.62],[2.579,-3.371]],"o":[[-0.075,0.356],[-0.826,8.017],[-1.527,4.982],[-0.2,0.224],[-3.456,4.008],[0,0]],"v":[[15.588,-34.84],[14.122,-20.791],[10.667,-1.404],[1.014,15.004],[-6.535,23.77],[-15.587,34.84]],"c":false}]},{"i":{"x":0.833,"y":0.833},"o":{"x":0.167,"y":0.167},"t":149,"s":[{"i":[[0,0],[0.901,-9.01],[1.478,-4.908],[4.908,-5.957],[4.833,-5.62],[2.579,-3.371]],"o":[[-0.075,0.356],[-0.826,8.017],[-1.527,4.982],[-0.2,0.224],[-3.456,4.008],[0,0]],"v":[[15.588,-34.84],[14.122,-20.791],[10.667,-1.404],[1.014,15.004],[-6.535,23.77],[-15.587,34.84]],"c":false}]},{"i":{"x":0.833,"y":0.833},"o":{"x":0.167,"y":0.167},"t":170,"s":[{"i":[[0,0],[0.901,-9.01],[1.478,-4.908],[4.908,-5.957],[4.833,-5.62],[2.579,-3.371]],"o":[[-0.075,0.356],[-0.826,8.017],[-1.527,4.982],[-0.2,0.224],[-3.456,4.008],[0,0]],"v":[[15.588,-34.84],[14.122,-20.791],[10.667,-1.404],[1.014,15.004],[-6.535,23.77],[-15.587,34.84]],"c":false}]},{"t":663.000027004544,"s":[{"i":[[0,0],[0.901,-9.01],[1.478,-4.908],[4.908,-5.957],[4.833,-5.62],[2.579,-3.371]],"o":[[-0.075,0.356],[-0.826,8.017],[-1.527,4.982],[-0.2,0.224],[-3.456,4.008],[0,0]],"v":[[15.463,-33.34],[14.122,-20.791],[10.667,-1.404],[1.014,15.004],[-6.535,23.77],[-15.587,34.84]],"c":false}]}],"ix":2},"nm":"Path 1","mn":"ADBE Vector Shape - Group","hd":false},{"ty":"st","c":{"a":0,"k":[1,1,1,1],"ix":3},"o":{"a":0,"k":40,"ix":4},"w":{"a":0,"k":1.427,"ix":5},"lc":1,"lj":1,"ml":4,"bm":0,"nm":"Stroke 1","mn":"ADBE Vector Graphic - Stroke","hd":false},{"ty":"tr","p":{"a":0,"k":[167.014,54.107],"ix":2},"a":{"a":0,"k":[0,0],"ix":1},"s":{"a":0,"k":[100,100],"ix":3},"r":{"a":0,"k":0,"ix":6},"o":{"a":0,"k":100,"ix":7},"sk":{"a":0,"k":0,"ix":4},"sa":{"a":0,"k":0,"ix":5},"nm":"Transform"}],"nm":"Group 7","np":2,"cix":2,"bm":0,"ix":7,"mn":"ADBE Vector Group","hd":false},{"ty":"gr","it":[{"ind":0,"ty":"sh","ix":1,"ks":{"a":0,"k":{"i":[[3.005,-3.091],[4.182,-3.69],[11.294,-7.605],[3.18,-1.068],[30.824,-21.803],[8.188,-4.739],[1.552,-0.975],[9.315,-5.938],[0,0.581],[-0.401,4.514],[-2.78,9.534],[-25.365,25.231],[-3.431,2.566],[-5.709,1.555],[-10.366,-0.637],[-3.794,-1.645],[-0.702,-0.3],[-2.829,-2.884],[-1.803,-3.278],[-0.627,-1.215],[-1.23,-2.863],[-1.386,-0.384],[-0.455,-0.037],[-0.751,-0.43]],"o":[[-1.728,1.76],[-2.855,2.754],[-11.718,7.867],[-3.731,1.236],[-3.08,2.173],[-9.716,5.62],[-1.828,1.142],[-8.389,5.226],[-0.15,-2.866],[0.801,-8.972],[8.864,-30.307],[4.057,-4.046],[6.085,-4.571],[7.086,-1.929],[3.656,0.244],[2.535,1.099],[4.532,1.873],[1.878,1.93],[1.978,3.578],[0.901,1.746],[1.265,2.945],[1.546,0.428],[1.022,0.084],[1.402,0.825]],"v":[[72.304,-30.402],[63.44,-22.226],[51.968,-14.189],[29.62,-0.787],[-22.213,33.772],[-39.116,44.14],[-56.018,54.031],[-72.732,64.651],[-85.315,71.619],[-84.939,60.549],[-79.568,32.789],[-28.223,-50.518],[-16.992,-60.436],[0.699,-69.624],[26.878,-71.563],[37.245,-68.499],[42.859,-66.528],[53.808,-60.985],[58.955,-54.424],[63.237,-47.483],[65.748,-41.87],[69.149,-37.353],[72.428,-36.696],[74.708,-36.275]],"c":true},"ix":2},"nm":"Path 1","mn":"ADBE Vector Shape - Group","hd":false},{"ty":"fl","c":{"a":0,"k":[0.815699977501,0.211799995572,0.133300003351,1],"ix":4},"o":{"a":0,"k":100,"ix":5},"r":1,"bm":0,"nm":"Fill 1","mn":"ADBE Vector Graphic - Fill","hd":false},{"ty":"tr","p":{"a":0,"k":[131.535,83.89],"ix":2},"a":{"a":0,"k":[0,0],"ix":1},"s":{"a":0,"k":[100,100],"ix":3},"r":{"a":0,"k":0,"ix":6},"o":{"a":0,"k":100,"ix":7},"sk":{"a":0,"k":0,"ix":4},"sa":{"a":0,"k":0,"ix":5},"nm":"Transform"}],"nm":"Group 8","np":2,"cix":2,"bm":0,"ix":8,"mn":"ADBE Vector Group","hd":false},{"ty":"gr","it":[{"ind":0,"ty":"sh","ix":1,"ks":{"a":1,"k":[{"i":{"x":0.833,"y":0.833},"o":{"x":0.167,"y":0.167},"t":138,"s":[{"i":[[0,0],[13.963,-8.738],[4.334,-3.335],[0.838,-1.123],[4.601,-11.164],[3.513,-10.29],[1.73,-4.743],[0.553,-2.051],[-0.285,-7.169],[-0.998,-3.692]],"o":[[-8.916,1.052],[-5.029,3.156],[-3.834,2.925],[-5.671,7.562],[-1.356,3.281],[-0.089,0.267],[-1.034,2.871],[-1.534,5.76],[0.785,19.599],[0,0]],"v":[[42.675,-74.084],[8.355,-59.398],[-5.689,-49.661],[-12.697,-43.589],[-28.105,-15.502],[-35.408,4.855],[-38.137,12.371],[-40.517,19.754],[-42.39,39.148],[-39.715,74.084]],"c":false}]},{"i":{"x":0.833,"y":0.833},"o":{"x":0.167,"y":0.167},"t":149,"s":[{"i":[[0,0],[13.963,-8.738],[4.334,-3.335],[0.838,-1.123],[4.601,-11.164],[3.513,-10.29],[1.73,-4.743],[0.553,-2.051],[-0.285,-7.169],[-0.998,-3.692]],"o":[[-8.916,1.052],[-5.029,3.156],[-3.834,2.925],[-5.671,7.562],[-1.356,3.281],[-0.089,0.267],[-1.034,2.871],[-1.534,5.76],[0.785,19.599],[0,0]],"v":[[42.675,-74.084],[8.355,-59.398],[-5.689,-49.661],[-12.697,-43.589],[-28.105,-15.502],[-35.408,4.855],[-38.137,12.371],[-40.517,19.754],[-42.39,39.148],[-39.715,74.084]],"c":false}]},{"t":170.000006924242,"s":[{"i":[[0,0],[13.963,-8.738],[4.334,-3.335],[0.838,-1.123],[4.601,-11.164],[3.513,-10.29],[1.73,-4.743],[0.553,-2.051],[-0.285,-7.169],[-0.998,-3.692]],"o":[[-8.916,1.052],[-5.029,3.156],[-3.834,2.925],[-5.671,7.562],[-1.356,3.281],[-0.089,0.267],[-1.034,2.871],[-1.534,5.76],[0.785,19.599],[0,0]],"v":[[42.675,-74.084],[8.355,-59.398],[-5.689,-49.661],[-12.697,-43.589],[-28.105,-15.502],[-35.408,4.855],[-38.137,12.371],[-40.517,19.754],[-42.39,39.148],[-39.715,74.084]],"c":false}]}],"ix":2},"nm":"Path 1","mn":"ADBE Vector Shape - Group","hd":false},{"ty":"st","c":{"a":0,"k":[1,1,1,1],"ix":3},"o":{"a":0,"k":40,"ix":4},"w":{"a":0,"k":1.427,"ix":5},"lc":1,"lj":1,"ml":4,"bm":0,"nm":"Stroke 1","mn":"ADBE Vector Graphic - Stroke","hd":false},{"ty":"tr","p":{"a":0,"k":[86.448,81.165],"ix":2},"a":{"a":0,"k":[0,0],"ix":1},"s":{"a":0,"k":[100,100],"ix":3},"r":{"a":0,"k":0,"ix":6},"o":{"a":0,"k":100,"ix":7},"sk":{"a":0,"k":0,"ix":4},"sa":{"a":0,"k":0,"ix":5},"nm":"Transform"}],"nm":"Group 9","np":2,"cix":2,"bm":0,"ix":9,"mn":"ADBE Vector Group","hd":false},{"ty":"gr","it":[{"ind":0,"ty":"sh","ix":1,"ks":{"a":1,"k":[{"i":{"x":0.833,"y":0.833},"o":{"x":0.167,"y":0.167},"t":138,"s":[{"i":[[0,0],[16.014,-10.361],[5.225,-3.942],[1.07,-1.141],[5.118,-17.833],[1.337,-6.616],[0.285,-2.675],[0.659,-4.743],[0.499,-5.368],[-0.481,-4.636],[-0.767,-2.871]],"o":[[-8.81,1.034],[-5.546,3.585],[-4.351,3.299],[-6.438,6.866],[-1.783,6.224],[-1.052,5.118],[-0.339,2.996],[-0.5,3.531],[-0.179,2.086],[0.5,4.833],[0,0]],"v":[[44.361,-74.819],[7.125,-57.726],[-9.033,-46.437],[-17.164,-39.777],[-34.499,-2.729],[-39.18,16.531],[-41.186,28.221],[-42.684,39.83],[-44.182,53.179],[-43.727,63.263],[-41.827,74.819]],"c":false}]},{"i":{"x":0.833,"y":0.833},"o":{"x":0.167,"y":0.167},"t":149,"s":[{"i":[[0,0],[16.014,-10.361],[5.225,-3.942],[1.07,-1.141],[5.118,-17.833],[1.337,-6.616],[0.285,-2.675],[0.659,-4.743],[0.499,-5.368],[-0.481,-4.636],[-0.767,-2.871]],"o":[[-8.81,1.034],[-5.546,3.585],[-4.351,3.299],[-6.438,6.866],[-1.783,6.224],[-1.052,5.118],[-0.339,2.996],[-0.5,3.531],[-0.179,2.086],[0.5,4.833],[0,0]],"v":[[44.361,-74.819],[7.125,-57.726],[-9.033,-46.437],[-17.164,-39.777],[-34.499,-2.729],[-39.18,16.531],[-41.186,28.221],[-42.684,39.83],[-44.182,53.179],[-43.727,63.263],[-41.827,74.819]],"c":false}]},{"t":170.000006924242,"s":[{"i":[[0,0],[16.014,-10.361],[5.225,-3.942],[1.07,-1.141],[5.118,-17.833],[1.337,-6.616],[0.285,-2.675],[0.659,-4.743],[0.499,-5.368],[-0.481,-4.636],[-0.767,-2.871]],"o":[[-8.81,1.034],[-5.546,3.585],[-4.351,3.299],[-6.438,6.866],[-1.783,6.224],[-1.052,5.118],[-0.339,2.996],[-0.5,3.531],[-0.179,2.086],[0.5,4.833],[0,0]],"v":[[44.361,-74.819],[7.125,-57.726],[-9.033,-46.437],[-17.164,-39.777],[-34.499,-2.729],[-39.18,16.531],[-41.186,28.221],[-42.684,39.83],[-44.182,53.179],[-43.727,63.263],[-41.827,74.819]],"c":false}]}],"ix":2},"nm":"Path 1","mn":"ADBE Vector Shape - Group","hd":false},{"ty":"st","c":{"a":0,"k":[1,1,1,1],"ix":3},"o":{"a":0,"k":40,"ix":4},"w":{"a":0,"k":1.427,"ix":5},"lc":1,"lj":1,"ml":4,"bm":0,"nm":"Stroke 1","mn":"ADBE Vector Graphic - Stroke","hd":false},{"ty":"tr","p":{"a":0,"k":[55.605,78.102],"ix":2},"a":{"a":0,"k":[0,0],"ix":1},"s":{"a":0,"k":[100,100],"ix":3},"r":{"a":0,"k":0,"ix":6},"o":{"a":0,"k":100,"ix":7},"sk":{"a":0,"k":0,"ix":4},"sa":{"a":0,"k":0,"ix":5},"nm":"Transform"}],"nm":"Group 10","np":2,"cix":2,"bm":0,"ix":10,"mn":"ADBE Vector Group","hd":false},{"ty":"gr","it":[{"ind":0,"ty":"sh","ix":1,"ks":{"a":1,"k":[{"i":{"x":0.833,"y":0.833},"o":{"x":0.167,"y":0.167},"t":138,"s":[{"i":[[0,0],[13.571,-9.47],[4.315,-3.656],[0.928,-1.195],[6.741,-17.744],[1.784,-6.045],[0.054,-2.051],[0.695,-3.638],[-1.855,-6.991],[-1.587,-5.154],[-0.571,-2.104]],"o":[[-8.827,1.034],[-4.761,3.334],[-3.621,3.067],[-6.099,7.829],[-2.639,6.955],[-1.712,5.814],[-0.125,3.567],[-0.25,3.371],[0.321,1.195],[1.623,5.278],[0,0]],"v":[[42.029,-75.09],[8.43,-59.334],[-5.185,-48.848],[-12.007,-42.455],[-31.267,-4.096],[-37.901,15.405],[-40.549,27.202],[-41.779,38.009],[-39.372,53.551],[-36.51,63.074],[-33.059,75.09]],"c":false}]},{"i":{"x":0.833,"y":0.833},"o":{"x":0.167,"y":0.167},"t":149,"s":[{"i":[[0,0],[13.571,-9.47],[4.315,-3.656],[0.928,-1.195],[6.741,-17.744],[1.784,-6.045],[0.054,-2.051],[0.695,-3.638],[-1.855,-6.991],[-1.587,-5.154],[-0.571,-2.104]],"o":[[-8.827,1.034],[-4.761,3.334],[-3.621,3.067],[-6.099,7.829],[-2.639,6.955],[-1.712,5.814],[-0.125,3.567],[-0.25,3.371],[0.321,1.195],[1.623,5.278],[0,0]],"v":[[42.029,-75.09],[8.43,-59.334],[-5.185,-48.848],[-12.007,-42.455],[-31.267,-4.096],[-37.901,15.405],[-40.549,27.202],[-41.779,38.009],[-39.372,53.551],[-36.51,63.074],[-33.059,75.09]],"c":false}]},{"t":170.000006924242,"s":[{"i":[[0,0],[13.571,-9.47],[4.315,-3.656],[0.928,-1.195],[6.741,-17.744],[1.784,-6.045],[0.054,-2.051],[0.695,-3.638],[-1.855,-6.991],[-1.587,-5.154],[-0.571,-2.104]],"o":[[-8.827,1.034],[-4.761,3.334],[-3.621,3.067],[-6.099,7.829],[-2.639,6.955],[-1.712,5.814],[-0.125,3.567],[-0.25,3.371],[0.321,1.195],[1.623,5.278],[0,0]],"v":[[42.029,-75.09],[8.43,-59.334],[-5.185,-48.848],[-12.007,-42.455],[-31.267,-4.096],[-37.901,15.405],[-40.549,27.202],[-41.779,38.009],[-39.372,53.551],[-36.51,63.074],[-33.059,75.09]],"c":false}]}],"ix":2},"nm":"Path 1","mn":"ADBE Vector Shape - Group","hd":false},{"ty":"st","c":{"a":0,"k":[1,1,1,1],"ix":3},"o":{"a":0,"k":40,"ix":4},"w":{"a":0,"k":1.427,"ix":5},"lc":1,"lj":1,"ml":4,"bm":0,"nm":"Stroke 1","mn":"ADBE Vector Graphic - Stroke","hd":false},{"ty":"tr","p":{"a":0,"k":[67.299,79.443],"ix":2},"a":{"a":0,"k":[0,0],"ix":1},"s":{"a":0,"k":[100,100],"ix":3},"r":{"a":0,"k":0,"ix":6},"o":{"a":0,"k":100,"ix":7},"sk":{"a":0,"k":0,"ix":4},"sa":{"a":0,"k":0,"ix":5},"nm":"Transform"}],"nm":"Group 11","np":2,"cix":2,"bm":0,"ix":11,"mn":"ADBE Vector Group","hd":false},{"ty":"gr","it":[{"ind":0,"ty":"sh","ix":1,"ks":{"a":1,"k":[{"i":{"x":0.833,"y":0.833},"o":{"x":0.167,"y":0.167},"t":138,"s":[{"i":[[-0.779,1.851],[-10.81,0.733],[-10.16,-2.71],[0,0],[0,0],[15.415,-12.922],[5.814,0.784],[-1.909,10.914],[-3.46,12.358],[-3.763,9.737]],"o":[[-1.523,9.957],[7.581,-0.513],[10.836,2.889],[0,0],[0,0],[-23.397,-1.248],[-0.767,-4.744],[1.747,-10.022],[3.441,-12.198],[0.82,-2.119]],"v":[[-18.747,-49.892],[-2.734,-41.123],[24.596,-39.576],[42.244,-27.111],[17.755,30.539],[4.165,49.892],[-41.477,46.024],[-39.764,22.537],[-31.953,-11.034],[-21.146,-43.937]],"c":true}]},{"i":{"x":0.833,"y":0.833},"o":{"x":0.167,"y":0.167},"t":149,"s":[{"i":[[-0.779,1.851],[-10.81,0.733],[-10.16,-2.71],[0,0],[0,0],[15.415,-12.922],[5.814,0.784],[-1.909,10.914],[-3.46,12.358],[-3.763,9.737]],"o":[[-1.523,9.957],[7.581,-0.513],[10.836,2.889],[0,0],[0,0],[-23.397,-1.248],[-0.767,-4.744],[1.747,-10.022],[3.441,-12.198],[0.82,-2.119]],"v":[[-18.747,-49.892],[-2.734,-41.123],[24.596,-39.576],[42.244,-27.111],[17.755,30.539],[4.165,49.892],[-41.477,46.024],[-39.764,22.537],[-31.953,-11.034],[-21.146,-43.937]],"c":true}]},{"t":170.000006924242,"s":[{"i":[[-0.779,1.851],[-10.81,0.733],[-10.16,-2.71],[0,0],[0,0],[15.415,-12.922],[5.814,0.784],[-1.909,10.914],[-3.46,12.358],[-3.763,9.737]],"o":[[-1.523,9.957],[7.581,-0.513],[10.836,2.889],[0,0],[0,0],[-23.397,-1.248],[-0.767,-4.744],[1.747,-10.022],[3.441,-12.198],[0.82,-2.119]],"v":[[-18.747,-49.892],[-2.734,-41.123],[24.596,-39.576],[42.244,-27.111],[17.755,30.539],[4.165,49.892],[-41.477,46.024],[-39.764,22.537],[-31.953,-11.034],[-21.146,-43.937]],"c":true}]}],"ix":2},"nm":"Path 1","mn":"ADBE Vector Shape - Group","hd":false},{"ty":"fl","c":{"a":0,"k":[0.956900024414,0.51760002585,0.415699977501,1],"ix":4},"o":{"a":0,"k":100,"ix":5},"r":1,"bm":0,"nm":"Fill 1","mn":"ADBE Vector Graphic - Fill","hd":false},{"ty":"tr","p":{"a":0,"k":[42.281,105.695],"ix":2},"a":{"a":0,"k":[0,0],"ix":1},"s":{"a":0,"k":[100,100],"ix":3},"r":{"a":0,"k":0,"ix":6},"o":{"a":0,"k":100,"ix":7},"sk":{"a":0,"k":0,"ix":4},"sa":{"a":0,"k":0,"ix":5},"nm":"Transform"}],"nm":"Group 12","np":2,"cix":2,"bm":0,"ix":12,"mn":"ADBE Vector Group","hd":false},{"ty":"gr","it":[{"ind":0,"ty":"sh","ix":1,"ks":{"a":1,"k":[{"i":{"x":0.833,"y":0.833},"o":{"x":0.167,"y":0.167},"t":138,"s":[{"i":[[-4.922,-0.552],[-7.757,-1.159],[-5.208,-0.463],[-12.733,-4.85],[14.288,-11.075],[27.212,-23.919],[19.497,-14.452],[5.814,0.784],[-1.908,10.914],[-3.46,12.359],[-3.763,9.737],[-3.05,3.923],[-3.014,2.889],[-4.102,3.263],[-8.756,2.658],[-4.619,0.285]],"o":[[1.962,0.214],[6.795,1.017],[9.648,0.856],[30.222,11.505],[-38.893,30.076],[-10.94,9.616],[-23.397,-1.248],[-0.767,-4.744],[1.748,-10.022],[3.442,-12.198],[4.03,-10.415],[1.07,-1.374],[3.655,-3.477],[11.502,-9.167],[4.779,-1.444],[3.906,-0.25]],"v":[[5.415,-75.096],[19.994,-73.036],[37.997,-70.816],[71.568,-62.256],[57.658,-41.043],[-14.752,36.349],[-57.207,75.8],[-101.023,72.751],[-99.311,49.264],[-91.5,15.693],[-80.693,-17.209],[-70.073,-38.715],[-63.947,-45.109],[-52.311,-55.22],[-21.923,-72.956],[-7.826,-75.55]],"c":true}]},{"i":{"x":0.833,"y":0.833},"o":{"x":0.167,"y":0.167},"t":149,"s":[{"i":[[-4.922,-0.552],[-7.757,-1.159],[-5.208,-0.463],[-12.733,-4.85],[14.288,-11.075],[27.212,-23.919],[19.497,-14.452],[5.814,0.784],[-1.908,10.914],[-3.46,12.359],[-3.763,9.737],[-3.05,3.923],[-3.014,2.889],[-4.102,3.263],[-8.756,2.658],[-4.619,0.285]],"o":[[1.962,0.214],[6.795,1.017],[9.648,0.856],[30.222,11.505],[-38.893,30.076],[-10.94,9.616],[-23.397,-1.248],[-0.767,-4.744],[1.748,-10.022],[3.442,-12.198],[4.03,-10.415],[1.07,-1.374],[3.655,-3.477],[11.502,-9.167],[4.779,-1.444],[3.906,-0.25]],"v":[[5.415,-75.096],[19.994,-73.036],[37.997,-70.816],[71.568,-62.256],[57.658,-41.043],[-14.752,36.349],[-57.207,75.8],[-101.023,72.751],[-99.311,49.264],[-91.5,15.693],[-80.693,-17.209],[-70.073,-38.715],[-63.947,-45.109],[-52.311,-55.22],[-21.923,-72.956],[-7.826,-75.55]],"c":true}]},{"t":170.000006924242,"s":[{"i":[[-4.922,-0.552],[-7.757,-1.159],[-5.208,-0.463],[-12.733,-4.85],[14.288,-11.075],[27.212,-23.919],[19.497,-14.452],[5.814,0.784],[-1.908,10.914],[-3.46,12.359],[-3.763,9.737],[-3.05,3.923],[-3.014,2.889],[-4.102,3.263],[-8.756,2.658],[-4.619,0.285]],"o":[[1.962,0.214],[6.795,1.017],[9.648,0.856],[30.222,11.505],[-38.893,30.076],[-10.94,9.616],[-23.397,-1.248],[-0.767,-4.744],[1.748,-10.022],[3.442,-12.198],[4.03,-10.415],[1.07,-1.374],[3.655,-3.477],[11.502,-9.167],[4.779,-1.444],[3.906,-0.25]],"v":[[5.415,-75.096],[19.994,-73.036],[37.997,-70.816],[71.568,-62.256],[57.658,-41.043],[-14.752,36.349],[-57.207,75.8],[-101.023,72.751],[-99.311,49.264],[-91.5,15.693],[-80.693,-17.209],[-70.073,-38.715],[-63.947,-45.109],[-52.311,-55.22],[-21.923,-72.956],[-7.826,-75.55]],"c":true}]}],"ix":2},"nm":"Path 1","mn":"ADBE Vector Shape - Group","hd":false},{"ty":"fl","c":{"a":0,"k":[0.992200006223,0.576499968884,0.486300000957,1],"ix":4},"o":{"a":0,"k":100,"ix":5},"r":1,"bm":0,"nm":"Fill 1","mn":"ADBE Vector Graphic - Fill","hd":false},{"ty":"tr","p":{"a":0,"k":[101.827,78.967],"ix":2},"a":{"a":0,"k":[0,0],"ix":1},"s":{"a":0,"k":[100,100],"ix":3},"r":{"a":0,"k":0,"ix":6},"o":{"a":0,"k":100,"ix":7},"sk":{"a":0,"k":0,"ix":4},"sa":{"a":0,"k":0,"ix":5},"nm":"Transform"}],"nm":"Group 13","np":2,"cix":2,"bm":0,"ix":13,"mn":"ADBE Vector Group","hd":false}],"ip":0,"op":513.000020894918,"st":0,"bm":0}]},{"id":"comp_3","layers":[{"ddd":0,"ind":1,"ty":4,"nm":"la maskette","td":1,"sr":1,"ks":{"o":{"a":0,"k":100,"ix":11},"r":{"a":0,"k":0,"ix":10},"p":{"a":0,"k":[375,100,0],"ix":2},"a":{"a":0,"k":[0,0,0],"ix":1},"s":{"a":0,"k":[100,100,100],"ix":6}},"ao":0,"shapes":[{"ty":"gr","it":[{"ty":"rc","d":1,"s":{"a":0,"k":[395,100],"ix":2},"p":{"a":0,"k":[0,0],"ix":3},"r":{"a":0,"k":0,"ix":4},"nm":"Rectangle Path 1","mn":"ADBE Vector Shape - Rect","hd":false},{"ty":"st","c":{"a":0,"k":[0.380391977348,0.831372967888,0.345097979377,1],"ix":3},"o":{"a":0,"k":100,"ix":4},"w":{"a":0,"k":0,"ix":5},"lc":1,"lj":1,"ml":4,"bm":0,"nm":"Stroke 1","mn":"ADBE Vector Graphic - Stroke","hd":false},{"ty":"fl","c":{"a":0,"k":[0.576470947266,0.576470947266,0.576470947266,1],"ix":4},"o":{"a":0,"k":100,"ix":5},"r":1,"bm":0,"nm":"Fill 1","mn":"ADBE Vector Graphic - Fill","hd":false},{"ty":"tr","p":{"a":0,"k":[-177.5,-1],"ix":2},"a":{"a":0,"k":[0,0],"ix":1},"s":{"a":0,"k":[100,100],"ix":3},"r":{"a":0,"k":0,"ix":6},"o":{"a":0,"k":100,"ix":7},"sk":{"a":0,"k":0,"ix":4},"sa":{"a":0,"k":0,"ix":5},"nm":"Transform"}],"nm":"Rectangle 1","np":3,"cix":2,"bm":0,"ix":1,"mn":"ADBE Vector Group","hd":false}],"ip":0,"op":900.000036657751,"st":0,"bm":0},{"ddd":0,"ind":2,"ty":4,"nm":"Probe - chrome AE v4 Outlines","tt":1,"sr":1,"ks":{"o":{"a":0,"k":100,"ix":11},"r":{"a":0,"k":0,"ix":10},"p":{"a":0,"k":[423.685,103.989,0],"ix":2},"a":{"a":0,"k":[114,16,0],"ix":1},"s":{"a":0,"k":[200,200,100],"ix":6}},"ao":0,"shapes":[{"ty":"gr","it":[{"ind":0,"ty":"sh","ix":1,"ks":{"a":0,"k":{"i":[[0,0],[0,0],[0.054,0.845],[0,0]],"o":[[0,0],[0,0],[-0.054,-0.845],[0,0]],"v":[[-23.22,0.735],[22.866,1.317],[23.165,-0.1],[22.866,-1.317]],"c":true},"ix":2},"nm":"Path 1","mn":"ADBE Vector Shape - Group","hd":false},{"ty":"fl","c":{"a":0,"k":[0.29411797617,0.341175991881,0.43529399797,1],"ix":4},"o":{"a":0,"k":100,"ix":5},"r":1,"bm":0,"nm":"Fill 1","mn":"ADBE Vector Graphic - Fill","hd":false},{"ty":"tr","p":{"a":0,"k":[34.506,16.441],"ix":2},"a":{"a":0,"k":[0,0],"ix":1},"s":{"a":0,"k":[100,100],"ix":3},"r":{"a":0,"k":0,"ix":6},"o":{"a":0,"k":100,"ix":7},"sk":{"a":0,"k":0,"ix":4},"sa":{"a":0,"k":0,"ix":5},"nm":"Transform"}],"nm":"Group 1","np":2,"cix":2,"bm":0,"ix":1,"mn":"ADBE Vector Group","hd":false},{"ty":"gr","it":[{"ind":0,"ty":"sh","ix":1,"ks":{"a":0,"k":{"i":[[0,0],[0.049,-0.014],[-0.014,-0.049]],"o":[[-0.014,-0.049],[-0.049,0.014],[0,0]],"v":[[-0.217,-4.539],[-0.33,-4.601],[-0.392,-4.487]],"c":true},"ix":2},"nm":"Path 1","mn":"ADBE Vector Shape - Group","hd":false},{"ind":1,"ty":"sh","ix":2,"ks":{"a":0,"k":{"i":[[0,0],[0,0],[0,0]],"o":[[0,0],[0,0],[0,0]],"v":[[0.264,-0.001],[0.172,-0.004],[0.172,0.002]],"c":true},"ix":2},"nm":"Path 2","mn":"ADBE Vector Shape - Group","hd":false},{"ind":2,"ty":"sh","ix":3,"ks":{"a":0,"k":{"i":[[0,0],[-0.049,-0.014],[-0.014,0.049]],"o":[[-0.014,0.049],[0.049,0.014],[0,0]],"v":[[-0.392,4.487],[-0.33,4.601],[-0.217,4.539]],"c":true},"ix":2},"nm":"Path 3","mn":"ADBE Vector Shape - Group","hd":false},{"ind":3,"ty":"sh","ix":4,"ks":{"a":0,"k":{"i":[[0,0],[0.05,-1.515],[0,0],[0.429,1.474]],"o":[[0.424,1.455],[0,0],[0.051,-1.534],[0,0]],"v":[[-0.392,-4.487],[0.172,-0.004],[0.355,0.002],[-0.217,-4.539]],"c":true},"ix":2},"nm":"Path 4","mn":"ADBE Vector Shape - Group","hd":false},{"ind":4,"ty":"sh","ix":5,"ks":{"a":0,"k":{"i":[[0,0],[0.425,-1.456],[0,0],[0.051,1.535]],"o":[[0.051,1.516],[0,0],[0.43,-1.474],[0,0]],"v":[[0.172,0.002],[-0.392,4.487],[-0.217,4.539],[0.355,-0.004]],"c":true},"ix":2},"nm":"Path 5","mn":"ADBE Vector Shape - Group","hd":false},{"ty":"mm","mm":1,"nm":"Merge Paths 1","mn":"ADBE Vector Filter - Merge","hd":false},{"ty":"fl","c":{"a":0,"k":[0.67843095368,0.67843095368,0.67843095368,1],"ix":4},"o":{"a":0,"k":100,"ix":5},"r":1,"bm":0,"nm":"Fill 1","mn":"ADBE Vector Graphic - Fill","hd":false},{"ty":"tr","p":{"a":0,"k":[113.478,15.757],"ix":2},"a":{"a":0,"k":[0,0],"ix":1},"s":{"a":0,"k":[100,100],"ix":3},"r":{"a":0,"k":0,"ix":6},"o":{"a":0,"k":100,"ix":7},"sk":{"a":0,"k":0,"ix":4},"sa":{"a":0,"k":0,"ix":5},"nm":"Transform"}],"nm":"Group 2","np":7,"cix":2,"bm":0,"ix":2,"mn":"ADBE Vector Group","hd":false},{"ty":"gr","it":[{"ind":0,"ty":"sh","ix":1,"ks":{"a":0,"k":{"i":[[0,0],[0.074,-0.021],[-0.021,-0.074]],"o":[[-0.021,-0.074],[-0.074,0.021],[0,0]],"v":[[-0.171,-4.41],[-0.343,-4.507],[-0.439,-4.335]],"c":true},"ix":2},"nm":"Path 1","mn":"ADBE Vector Shape - Group","hd":false},{"ind":1,"ty":"sh","ix":2,"ks":{"a":0,"k":{"i":[[0,0],[0,0],[0,0]],"o":[[0,0],[0,0],[0,0]],"v":[[0.265,0.407],[0.125,0.402],[0.126,0.413]],"c":true},"ix":2},"nm":"Path 2","mn":"ADBE Vector Shape - Group","hd":false},{"ind":2,"ty":"sh","ix":3,"ks":{"a":0,"k":{"i":[[0,0],[-0.073,-0.025],[-0.025,0.073]],"o":[[-0.025,0.073],[0.073,0.025],[0,0]],"v":[[-0.437,4.326],[-0.35,4.503],[-0.173,4.416]],"c":true},"ix":2},"nm":"Path 3","mn":"ADBE Vector Shape - Group","hd":false},{"ind":3,"ty":"sh","ix":4,"ks":{"a":0,"k":{"i":[[0,0],[0.057,-1.599],[0,0],[0.439,1.568]],"o":[[0.431,1.541],[0,0],[0.058,-1.628],[0,0]],"v":[[-0.439,-4.335],[0.126,0.402],[0.404,0.412],[-0.171,-4.41]],"c":true},"ix":2},"nm":"Path 4","mn":"ADBE Vector Shape - Group","hd":false},{"ind":4,"ty":"sh","ix":5,"ks":{"a":0,"k":{"i":[[0,0],[0.427,-1.259],[0,0],[0.056,1.362]],"o":[[0.055,1.328],[0,0],[0.438,-1.291],[0,0]],"v":[[0.126,0.413],[-0.437,4.326],[-0.173,4.416],[0.404,0.401]],"c":true},"ix":2},"nm":"Path 5","mn":"ADBE Vector Shape - Group","hd":false},{"ty":"mm","mm":1,"nm":"Merge Paths 1","mn":"ADBE Vector Filter - Merge","hd":false},{"ty":"fl","c":{"a":0,"k":[0.341175991881,0.337254991718,0.337254991718,1],"ix":4},"o":{"a":0,"k":100,"ix":5},"r":1,"bm":0,"nm":"Fill 1","mn":"ADBE Vector Graphic - Fill","hd":false},{"ty":"tr","p":{"a":0,"k":[113.193,15.617],"ix":2},"a":{"a":0,"k":[0,0],"ix":1},"s":{"a":0,"k":[100,100],"ix":3},"r":{"a":0,"k":0,"ix":6},"o":{"a":0,"k":100,"ix":7},"sk":{"a":0,"k":0,"ix":4},"sa":{"a":0,"k":0,"ix":5},"nm":"Transform"}],"nm":"Group 3","np":7,"cix":2,"bm":0,"ix":3,"mn":"ADBE Vector Group","hd":false},{"ty":"gr","it":[{"ind":0,"ty":"sh","ix":1,"ks":{"a":0,"k":{"i":[[0.132,0.729],[0,0],[0,0],[0,0]],"o":[[0,0],[0,0],[0,0],[0.237,-0.771]],"v":[[-83.282,-1.128],[83.518,-0.846],[82.95,-0.564],[-83.518,1.128]],"c":true},"ix":2},"nm":"Path 1","mn":"ADBE Vector Shape - Group","hd":false},{"ty":"fl","c":{"a":0,"k":[1,1,1,1],"ix":4},"o":{"a":0,"k":100,"ix":5},"r":1,"bm":0,"nm":"Fill 1","mn":"ADBE Vector Graphic - Fill","hd":false},{"ty":"tr","p":{"a":0,"k":[141.342,16.604],"ix":2},"a":{"a":0,"k":[0,0],"ix":1},"s":{"a":0,"k":[100,100],"ix":3},"r":{"a":0,"k":0,"ix":6},"o":{"a":0,"k":100,"ix":7},"sk":{"a":0,"k":0,"ix":4},"sa":{"a":0,"k":0,"ix":5},"nm":"Transform"}],"nm":"Group 4","np":2,"cix":2,"bm":0,"ix":4,"mn":"ADBE Vector Group","hd":false},{"ty":"gr","it":[{"ind":0,"ty":"sh","ix":1,"ks":{"a":0,"k":{"i":[[0,0],[0,0],[0,0],[0,0]],"o":[[0,0],[0,0],[0,0],[0,0]],"v":[[2.916,1.676],[0.724,-9.508],[-2.916,-1.952],[-0.769,9.508]],"c":true},"ix":2},"nm":"Path 1","mn":"ADBE Vector Shape - Group","hd":false},{"ty":"fl","c":{"a":0,"k":[0.295833004222,0.295833004222,0.295833004222,1],"ix":4},"o":{"a":0,"k":100,"ix":5},"r":1,"bm":0,"nm":"Fill 1","mn":"ADBE Vector Graphic - Fill","hd":false},{"ty":"tr","p":{"a":0,"k":[3.769,15.492],"ix":2},"a":{"a":0,"k":[0,0],"ix":1},"s":{"a":0,"k":[100,100],"ix":3},"r":{"a":0,"k":0,"ix":6},"o":{"a":0,"k":100,"ix":7},"sk":{"a":0,"k":0,"ix":4},"sa":{"a":0,"k":0,"ix":5},"nm":"Transform"}],"nm":"Group 5","np":2,"cix":2,"bm":0,"ix":5,"mn":"ADBE Vector Group","hd":false},{"ty":"gr","it":[{"ind":0,"ty":"sh","ix":1,"ks":{"a":0,"k":{"i":[[0,0],[0,0],[0,0],[0,0]],"o":[[0,0],[0,0],[0,0],[0,0]],"v":[[0.335,3.914],[4.09,-3.914],[-0.456,-3.914],[-4.09,3.914]],"c":true},"ix":2},"nm":"Path 1","mn":"ADBE Vector Shape - Group","hd":false},{"ty":"fl","c":{"a":0,"k":[0.349019996793,0.349019996793,0.349019996793,1],"ix":4},"o":{"a":0,"k":100,"ix":5},"r":1,"bm":0,"nm":"Fill 1","mn":"ADBE Vector Graphic - Fill","hd":false},{"ty":"tr","p":{"a":0,"k":[7.09,21.086],"ix":2},"a":{"a":0,"k":[0,0],"ix":1},"s":{"a":0,"k":[100,100],"ix":3},"r":{"a":0,"k":0,"ix":6},"o":{"a":0,"k":100,"ix":7},"sk":{"a":0,"k":0,"ix":4},"sa":{"a":0,"k":0,"ix":5},"nm":"Transform"}],"nm":"Group 6","np":2,"cix":2,"bm":0,"ix":6,"mn":"ADBE Vector Group","hd":false},{"ty":"gr","it":[{"ind":0,"ty":"sh","ix":1,"ks":{"a":0,"k":{"i":[[0,0],[0,0],[0,0],[0,0]],"o":[[0,0],[0,0],[0,0],[0,0]],"v":[[-3.355,-5.584],[1.089,-5.498],[3.355,5.584],[-1.193,5.584]],"c":true},"ix":2},"nm":"Path 1","mn":"ADBE Vector Shape - Group","hd":false},{"ty":"fl","c":{"a":0,"k":[0.792156982422,0.792156982422,0.792156982422,1],"ix":4},"o":{"a":0,"k":100,"ix":5},"r":1,"bm":0,"nm":"Fill 1","mn":"ADBE Vector Graphic - Fill","hd":false},{"ty":"tr","p":{"a":0,"k":[7.827,11.584],"ix":2},"a":{"a":0,"k":[0,0],"ix":1},"s":{"a":0,"k":[100,100],"ix":3},"r":{"a":0,"k":0,"ix":6},"o":{"a":0,"k":100,"ix":7},"sk":{"a":0,"k":0,"ix":4},"sa":{"a":0,"k":0,"ix":5},"nm":"Transform"}],"nm":"Group 7","np":2,"cix":2,"bm":0,"ix":7,"mn":"ADBE Vector Group","hd":false},{"ty":"gr","it":[{"ind":0,"ty":"sh","ix":1,"ks":{"a":0,"k":{"i":[[0,0],[0,0.016],[-0.032,0.05]],"o":[[-0.092,0.126],[0.025,-0.053],[0,0]],"v":[[0.066,-0.085],[-0.066,0.069],[0.02,-0.085]],"c":true},"ix":2},"nm":"Path 1","mn":"ADBE Vector Shape - Group","hd":false},{"ty":"fl","c":{"a":0,"k":[0.137254991718,0.137254991718,0.137254991718,1],"ix":4},"o":{"a":0,"k":100,"ix":5},"r":1,"bm":0,"nm":"Fill 1","mn":"ADBE Vector Graphic - Fill","hd":false},{"ty":"tr","p":{"a":0,"k":[8.582,22.559],"ix":2},"a":{"a":0,"k":[0,0],"ix":1},"s":{"a":0,"k":[100,100],"ix":3},"r":{"a":0,"k":0,"ix":6},"o":{"a":0,"k":100,"ix":7},"sk":{"a":0,"k":0,"ix":4},"sa":{"a":0,"k":0,"ix":5},"nm":"Transform"}],"nm":"Group 8","np":2,"cix":2,"bm":0,"ix":8,"mn":"ADBE Vector Group","hd":false},{"ty":"gr","it":[{"ind":0,"ty":"sh","ix":1,"ks":{"a":0,"k":{"i":[[0,0],[-0.233,-0.446],[0,0],[-5.4,0],[-4.148,-1.26],[5.51,-0.286]],"o":[[0.234,0.234],[0.116,0.698],[0,0],[4.335,0.049],[-4.917,-2.503],[-8.436,0.054]],"v":[[-83.821,-1.831],[-83.297,-0.742],[-83.084,0.425],[71.033,-0.139],[83.821,1.835],[67.907,-1.549]],"c":true},"ix":2},"nm":"Path 1","mn":"ADBE Vector Shape - Group","hd":false},{"ty":"fl","c":{"a":0,"k":[1,1,1,1],"ix":4},"o":{"a":0,"k":100,"ix":5},"r":1,"bm":0,"nm":"Fill 1","mn":"ADBE Vector Graphic - Fill","hd":false},{"ty":"tr","p":{"a":0,"k":[141.043,13.923],"ix":2},"a":{"a":0,"k":[0,0],"ix":1},"s":{"a":0,"k":[100,100],"ix":3},"r":{"a":0,"k":0,"ix":6},"o":{"a":0,"k":100,"ix":7},"sk":{"a":0,"k":0,"ix":4},"sa":{"a":0,"k":0,"ix":5},"nm":"Transform"}],"nm":"Group 9","np":2,"cix":2,"bm":0,"ix":9,"mn":"ADBE Vector Group","hd":false},{"ty":"gr","it":[{"ind":0,"ty":"sh","ix":1,"ks":{"a":0,"k":{"i":[[0,0],[0,0],[0,0],[-6.252,0],[-1.342,0.682],[1.422,-0.564],[8.508,0.082]],"o":[[0,0],[0,0],[0,0],[6.252,0],[0,0],[-1.422,0.564],[-8.508,-0.082]],"v":[[-83.841,1.833],[-83.133,0.14],[-82.915,-1.551],[65.085,-0.991],[83.841,-1.833],[79.577,0.141],[65.653,1.551]],"c":true},"ix":2},"nm":"Path 1","mn":"ADBE Vector Shape - Group","hd":false},{"ty":"fl","c":{"a":0,"k":[0.219607992733,0.219607992733,0.219607992733,1],"ix":4},"o":{"a":0,"k":100,"ix":5},"r":1,"bm":0,"nm":"Fill 1","mn":"ADBE Vector Graphic - Fill","hd":false},{"ty":"tr","p":{"a":0,"k":[141.023,17.591],"ix":2},"a":{"a":0,"k":[0,0],"ix":1},"s":{"a":0,"k":[100,100],"ix":3},"r":{"a":0,"k":0,"ix":6},"o":{"a":0,"k":100,"ix":7},"sk":{"a":0,"k":0,"ix":4},"sa":{"a":0,"k":0,"ix":5},"nm":"Transform"}],"nm":"Group 10","np":2,"cix":2,"bm":0,"ix":10,"mn":"ADBE Vector Group","hd":false},{"ty":"gr","it":[{"ind":0,"ty":"sh","ix":1,"ks":{"a":0,"k":{"i":[[0,0],[-5.684,-3.666],[4.546,0],[0,0],[-0.074,1.46],[0.772,1.727]],"o":[[4.546,0],[-5.684,3.668],[0,0],[0.705,-1.309],[-0.115,-1.646],[0,0]],"v":[[65.646,-4.51],[84.402,0.002],[65.646,4.516],[-84.402,4.516],[-83.131,0.209],[-84.402,-4.516]],"c":false},"ix":2},"nm":"Path 1","mn":"ADBE Vector Shape - Group","hd":false},{"ty":"fl","c":{"a":0,"k":[0.682353001015,0.682353001015,0.682353001015,1],"ix":4},"o":{"a":0,"k":100,"ix":5},"r":1,"bm":0,"nm":"Fill 1","mn":"ADBE Vector Graphic - Fill","hd":false},{"ty":"tr","p":{"a":0,"k":[141.03,15.754],"ix":2},"a":{"a":0,"k":[0,0],"ix":1},"s":{"a":0,"k":[100,100],"ix":3},"r":{"a":0,"k":0,"ix":6},"o":{"a":0,"k":100,"ix":7},"sk":{"a":0,"k":0,"ix":4},"sa":{"a":0,"k":0,"ix":5},"nm":"Transform"}],"nm":"Group 11","np":2,"cix":2,"bm":0,"ix":11,"mn":"ADBE Vector Group","hd":false},{"ty":"gr","it":[{"ind":0,"ty":"sh","ix":1,"ks":{"a":0,"k":{"i":[[0,0],[0,0],[0,0],[-0.065,-0.075],[0.004,-0.099],[0,0],[0,0],[0.067,-0.068],[0.096,-0.006],[0,0]],"o":[[0,0],[0,0],[0.099,0.008],[0.066,0.074],[0,0],[0,0],[-0.007,0.095],[-0.068,0.067],[0,0],[0,0]],"v":[[-26.329,1.657],[-23.597,-9.457],[24.255,-4.783],[24.511,-4.653],[24.607,-4.383],[26.329,0.468],[24.191,5.057],[24.077,5.309],[23.823,5.423],[-25.425,9.457]],"c":false},"ix":2},"nm":"Path 1","mn":"ADBE Vector Shape - Group","hd":false},{"ty":"fl","c":{"a":0,"k":[0,0,0,1],"ix":4},"o":{"a":0,"k":100,"ix":5},"r":1,"bm":0,"nm":"Fill 1","mn":"ADBE Vector Graphic - Fill","hd":false},{"ty":"tr","p":{"a":0,"k":[32.425,15.543],"ix":2},"a":{"a":0,"k":[0,0],"ix":1},"s":{"a":0,"k":[100,100],"ix":3},"r":{"a":0,"k":0,"ix":6},"o":{"a":0,"k":100,"ix":7},"sk":{"a":0,"k":0,"ix":4},"sa":{"a":0,"k":0,"ix":5},"nm":"Transform"}],"nm":"Group 12","np":2,"cix":2,"bm":0,"ix":12,"mn":"ADBE Vector Group","hd":false}],"ip":0,"op":900.000036657751,"st":0,"bm":0}]},{"id":"comp_4","layers":[{"ddd":0,"ind":1,"ty":4,"nm":"Line white","sr":1,"ks":{"o":{"a":0,"k":100,"ix":11},"r":{"a":0,"k":0,"ix":10},"p":{"a":0,"k":[383,100,0],"ix":2},"a":{"a":0,"k":[0,0,0],"ix":1},"s":{"a":0,"k":[100,100,100],"ix":6}},"ao":0,"shapes":[{"ty":"gr","it":[{"ind":0,"ty":"sh","ix":1,"ks":{"a":0,"k":{"i":[[0,0],[0,0]],"o":[[0,0],[0,0]],"v":[[11.5,-99.5],[11.5,99]],"c":false},"ix":2},"nm":"Path 1","mn":"ADBE Vector Shape - Group","hd":false},{"ty":"st","c":{"a":0,"k":[1,1,1,1],"ix":3},"o":{"a":0,"k":100,"ix":4},"w":{"a":1,"k":[{"i":{"x":[0.833],"y":[0.833]},"o":{"x":[0.167],"y":[0.167]},"t":58,"s":[0]},{"i":{"x":[0.833],"y":[0.833]},"o":{"x":[0.167],"y":[0.167]},"t":74,"s":[4]},{"i":{"x":[0.833],"y":[0.833]},"o":{"x":[0.167],"y":[0.167]},"t":110,"s":[4]},{"t":120.0000048877,"s":[0]}],"ix":5},"lc":1,"lj":1,"ml":1,"bm":0,"d":[{"n":"d","nm":"dash","v":{"a":0,"k":8,"ix":1}},{"n":"o","nm":"offset","v":{"a":0,"k":0,"ix":7}}],"nm":"Stroke 1","mn":"ADBE Vector Graphic - Stroke","hd":false},{"ty":"fl","c":{"a":0,"k":[0.576470947266,0.576470947266,0.576470947266,1],"ix":4},"o":{"a":0,"k":100,"ix":5},"r":1,"bm":0,"nm":"Fill 1","mn":"ADBE Vector Graphic - Fill","hd":false},{"ty":"tr","p":{"a":0,"k":[0,0],"ix":2},"a":{"a":0,"k":[0,0],"ix":1},"s":{"a":0,"k":[100,100],"ix":3},"r":{"a":0,"k":0,"ix":6},"o":{"a":0,"k":100,"ix":7},"sk":{"a":0,"k":0,"ix":4},"sa":{"a":0,"k":0,"ix":5},"nm":"Transform"}],"nm":"Shape 1","np":3,"cix":2,"bm":0,"ix":1,"mn":"ADBE Vector Group","hd":false}],"ip":0,"op":900.000036657751,"st":0,"bm":0},{"ddd":0,"ind":2,"ty":4,"nm":"Line green","parent":5,"sr":1,"ks":{"o":{"a":0,"k":100,"ix":11},"r":{"a":0,"k":0,"ix":10},"p":{"a":0,"k":[106.863,14.005,0],"ix":2},"a":{"a":0,"k":[0,0,0],"ix":1},"s":{"a":0,"k":[50,50,100],"ix":6}},"ao":0,"shapes":[{"ty":"gr","it":[{"ind":0,"ty":"sh","ix":1,"ks":{"a":0,"k":{"i":[[0,0],[0,0]],"o":[[0,0],[0,0]],"v":[[11.5,-99.5],[11.5,99]],"c":false},"ix":2},"nm":"Path 1","mn":"ADBE Vector Shape - Group","hd":false},{"ty":"st","c":{"a":0,"k":[0.003921568859,1,0.003921568859,1],"ix":3},"o":{"a":0,"k":100,"ix":4},"w":{"a":0,"k":4,"ix":5},"lc":1,"lj":1,"ml":4,"bm":0,"nm":"Stroke 1","mn":"ADBE Vector Graphic - Stroke","hd":false},{"ty":"fl","c":{"a":0,"k":[0.576470947266,0.576470947266,0.576470947266,1],"ix":4},"o":{"a":0,"k":100,"ix":5},"r":1,"bm":0,"nm":"Fill 1","mn":"ADBE Vector Graphic - Fill","hd":false},{"ty":"tr","p":{"a":0,"k":[0,0],"ix":2},"a":{"a":0,"k":[0,0],"ix":1},"s":{"a":0,"k":[100,100],"ix":3},"r":{"a":0,"k":0,"ix":6},"o":{"a":1,"k":[{"i":{"x":[0.833],"y":[0.833]},"o":{"x":[0.167],"y":[0.167]},"t":110,"s":[100]},{"t":120.0000048877,"s":[0]}],"ix":7},"sk":{"a":0,"k":0,"ix":4},"sa":{"a":0,"k":0,"ix":5},"nm":"Transform"}],"nm":"Shape 1","np":3,"cix":2,"bm":0,"ix":1,"mn":"ADBE Vector Group","hd":false}],"ip":85.000003462121,"op":900.000036657751,"st":0,"bm":0},{"ddd":0,"ind":3,"ty":4,"nm":"Line red","parent":5,"sr":1,"ks":{"o":{"a":0,"k":100,"ix":11},"r":{"a":0,"k":0,"ix":10},"p":{"a":0,"k":[106.863,14.005,0],"ix":2},"a":{"a":0,"k":[0,0,0],"ix":1},"s":{"a":0,"k":[50,50,100],"ix":6}},"ao":0,"shapes":[{"ty":"gr","it":[{"ind":0,"ty":"sh","ix":1,"ks":{"a":0,"k":{"i":[[0,0],[0,0]],"o":[[0,0],[0,0]],"v":[[11.5,-99.5],[11.5,99]],"c":false},"ix":2},"nm":"Path 1","mn":"ADBE Vector Shape - Group","hd":false},{"ty":"st","c":{"a":0,"k":[0.980392158031,0,0,1],"ix":3},"o":{"a":0,"k":100,"ix":4},"w":{"a":1,"k":[{"i":{"x":[0.833],"y":[0.833]},"o":{"x":[0.167],"y":[0.167]},"t":58,"s":[0]},{"i":{"x":[0.833],"y":[0.833]},"o":{"x":[0.167],"y":[0.167]},"t":66,"s":[4]},{"i":{"x":[0.833],"y":[0.833]},"o":{"x":[0.167],"y":[0.167]},"t":110,"s":[4]},{"t":120.0000048877,"s":[0]}],"ix":5},"lc":1,"lj":1,"ml":4,"bm":0,"d":[{"n":"d","nm":"dash","v":{"a":0,"k":8,"ix":1}},{"n":"o","nm":"offset","v":{"a":0,"k":0,"ix":7}}],"nm":"Stroke 1","mn":"ADBE Vector Graphic - Stroke","hd":false},{"ty":"fl","c":{"a":0,"k":[0.576470947266,0.576470947266,0.576470947266,1],"ix":4},"o":{"a":0,"k":100,"ix":5},"r":1,"bm":0,"nm":"Fill 1","mn":"ADBE Vector Graphic - Fill","hd":false},{"ty":"tr","p":{"a":0,"k":[0,0],"ix":2},"a":{"a":0,"k":[0,0],"ix":1},"s":{"a":0,"k":[100,100],"ix":3},"r":{"a":0,"k":0,"ix":6},"o":{"a":0,"k":100,"ix":7},"sk":{"a":0,"k":0,"ix":4},"sa":{"a":0,"k":0,"ix":5},"nm":"Transform"}],"nm":"Shape 1","np":3,"cix":2,"bm":0,"ix":1,"mn":"ADBE Vector Group","hd":false}],"ip":0,"op":85.000003462121,"st":0,"bm":0},{"ddd":0,"ind":4,"ty":4,"nm":"la maskette","td":1,"sr":1,"ks":{"o":{"a":0,"k":100,"ix":11},"r":{"a":0,"k":0,"ix":10},"p":{"a":0,"k":[375,100,0],"ix":2},"a":{"a":0,"k":[0,0,0],"ix":1},"s":{"a":0,"k":[100,100,100],"ix":6}},"ao":0,"shapes":[{"ty":"gr","it":[{"ty":"rc","d":1,"s":{"a":0,"k":[395,100],"ix":2},"p":{"a":0,"k":[0,0],"ix":3},"r":{"a":0,"k":0,"ix":4},"nm":"Rectangle Path 1","mn":"ADBE Vector Shape - Rect","hd":false},{"ty":"st","c":{"a":0,"k":[0.380391977348,0.831372967888,0.345097979377,1],"ix":3},"o":{"a":0,"k":100,"ix":4},"w":{"a":0,"k":0,"ix":5},"lc":1,"lj":1,"ml":4,"bm":0,"nm":"Stroke 1","mn":"ADBE Vector Graphic - Stroke","hd":false},{"ty":"fl","c":{"a":0,"k":[0.576470947266,0.576470947266,0.576470947266,1],"ix":4},"o":{"a":0,"k":100,"ix":5},"r":1,"bm":0,"nm":"Fill 1","mn":"ADBE Vector Graphic - Fill","hd":false},{"ty":"tr","p":{"a":0,"k":[-177.5,-1],"ix":2},"a":{"a":0,"k":[0,0],"ix":1},"s":{"a":0,"k":[100,100],"ix":3},"r":{"a":0,"k":0,"ix":6},"o":{"a":0,"k":100,"ix":7},"sk":{"a":0,"k":0,"ix":4},"sa":{"a":0,"k":0,"ix":5},"nm":"Transform"}],"nm":"Rectangle 1","np":3,"cix":2,"bm":0,"ix":1,"mn":"ADBE Vector Group","hd":false}],"ip":0,"op":900.000036657751,"st":0,"bm":0},{"ddd":0,"ind":5,"ty":4,"nm":"Probe - chrome AE v4","tt":1,"sr":1,"ks":{"o":{"a":0,"k":100,"ix":11},"r":{"a":0,"k":0,"ix":10},"p":{"a":1,"k":[{"i":{"x":0.667,"y":1},"o":{"x":0.333,"y":0},"t":0,"s":[-253.815,103.989,0],"to":[104.215,0,0],"ti":[-143.157,0,0]},{"i":{"x":0.667,"y":0.961},"o":{"x":0.333,"y":0},"t":58,"s":[374.554,103.989,0],"to":[0.067,0,0],"ti":[-0.067,0,0]},{"i":{"x":0.667,"y":1},"o":{"x":0.333,"y":0.072},"t":77,"s":[396.004,103.989,0],"to":[10.153,0,0],"ti":[-7.403,0,0]},{"t":123.000005009893,"s":[423.685,103.989,0]}],"ix":2},"a":{"a":0,"k":[114,16,0],"ix":1},"s":{"a":0,"k":[200,200,100],"ix":6}},"ao":0,"shapes":[{"ty":"gr","it":[{"ind":0,"ty":"sh","ix":1,"ks":{"a":0,"k":{"i":[[0,0],[0,0],[0.054,0.845],[0,0]],"o":[[0,0],[0,0],[-0.054,-0.845],[0,0]],"v":[[-23.22,0.735],[22.866,1.317],[23.165,-0.1],[22.866,-1.317]],"c":true},"ix":2},"nm":"Path 1","mn":"ADBE Vector Shape - Group","hd":false},{"ty":"fl","c":{"a":0,"k":[0.29411797617,0.341175991881,0.43529399797,1],"ix":4},"o":{"a":0,"k":100,"ix":5},"r":1,"bm":0,"nm":"Fill 1","mn":"ADBE Vector Graphic - Fill","hd":false},{"ty":"tr","p":{"a":0,"k":[34.506,16.441],"ix":2},"a":{"a":0,"k":[0,0],"ix":1},"s":{"a":0,"k":[100,100],"ix":3},"r":{"a":0,"k":0,"ix":6},"o":{"a":0,"k":100,"ix":7},"sk":{"a":0,"k":0,"ix":4},"sa":{"a":0,"k":0,"ix":5},"nm":"Transform"}],"nm":"Group 1","np":2,"cix":2,"bm":0,"ix":1,"mn":"ADBE Vector Group","hd":false},{"ty":"gr","it":[{"ind":0,"ty":"sh","ix":1,"ks":{"a":0,"k":{"i":[[0,0],[0.049,-0.014],[-0.014,-0.049]],"o":[[-0.014,-0.049],[-0.049,0.014],[0,0]],"v":[[-0.217,-4.539],[-0.33,-4.601],[-0.392,-4.487]],"c":true},"ix":2},"nm":"Path 1","mn":"ADBE Vector Shape - Group","hd":false},{"ind":1,"ty":"sh","ix":2,"ks":{"a":0,"k":{"i":[[0,0],[0,0],[0,0]],"o":[[0,0],[0,0],[0,0]],"v":[[0.264,-0.001],[0.172,-0.004],[0.172,0.002]],"c":true},"ix":2},"nm":"Path 2","mn":"ADBE Vector Shape - Group","hd":false},{"ind":2,"ty":"sh","ix":3,"ks":{"a":0,"k":{"i":[[0,0],[-0.049,-0.014],[-0.014,0.049]],"o":[[-0.014,0.049],[0.049,0.014],[0,0]],"v":[[-0.392,4.487],[-0.33,4.601],[-0.217,4.539]],"c":true},"ix":2},"nm":"Path 3","mn":"ADBE Vector Shape - Group","hd":false},{"ind":3,"ty":"sh","ix":4,"ks":{"a":0,"k":{"i":[[0,0],[0.05,-1.515],[0,0],[0.429,1.474]],"o":[[0.424,1.455],[0,0],[0.051,-1.534],[0,0]],"v":[[-0.392,-4.487],[0.172,-0.004],[0.355,0.002],[-0.217,-4.539]],"c":true},"ix":2},"nm":"Path 4","mn":"ADBE Vector Shape - Group","hd":false},{"ind":4,"ty":"sh","ix":5,"ks":{"a":0,"k":{"i":[[0,0],[0.425,-1.456],[0,0],[0.051,1.535]],"o":[[0.051,1.516],[0,0],[0.43,-1.474],[0,0]],"v":[[0.172,0.002],[-0.392,4.487],[-0.217,4.539],[0.355,-0.004]],"c":true},"ix":2},"nm":"Path 5","mn":"ADBE Vector Shape - Group","hd":false},{"ty":"mm","mm":1,"nm":"Merge Paths 1","mn":"ADBE Vector Filter - Merge","hd":false},{"ty":"fl","c":{"a":0,"k":[0.67843095368,0.67843095368,0.67843095368,1],"ix":4},"o":{"a":0,"k":100,"ix":5},"r":1,"bm":0,"nm":"Fill 1","mn":"ADBE Vector Graphic - Fill","hd":false},{"ty":"tr","p":{"a":0,"k":[113.478,15.757],"ix":2},"a":{"a":0,"k":[0,0],"ix":1},"s":{"a":0,"k":[100,100],"ix":3},"r":{"a":0,"k":0,"ix":6},"o":{"a":0,"k":100,"ix":7},"sk":{"a":0,"k":0,"ix":4},"sa":{"a":0,"k":0,"ix":5},"nm":"Transform"}],"nm":"Group 2","np":7,"cix":2,"bm":0,"ix":2,"mn":"ADBE Vector Group","hd":false},{"ty":"gr","it":[{"ind":0,"ty":"sh","ix":1,"ks":{"a":0,"k":{"i":[[0,0],[0.074,-0.021],[-0.021,-0.074]],"o":[[-0.021,-0.074],[-0.074,0.021],[0,0]],"v":[[-0.171,-4.41],[-0.343,-4.507],[-0.439,-4.335]],"c":true},"ix":2},"nm":"Path 1","mn":"ADBE Vector Shape - Group","hd":false},{"ind":1,"ty":"sh","ix":2,"ks":{"a":0,"k":{"i":[[0,0],[0,0],[0,0]],"o":[[0,0],[0,0],[0,0]],"v":[[0.265,0.407],[0.125,0.402],[0.126,0.413]],"c":true},"ix":2},"nm":"Path 2","mn":"ADBE Vector Shape - Group","hd":false},{"ind":2,"ty":"sh","ix":3,"ks":{"a":0,"k":{"i":[[0,0],[-0.073,-0.025],[-0.025,0.073]],"o":[[-0.025,0.073],[0.073,0.025],[0,0]],"v":[[-0.437,4.326],[-0.35,4.503],[-0.173,4.416]],"c":true},"ix":2},"nm":"Path 3","mn":"ADBE Vector Shape - Group","hd":false},{"ind":3,"ty":"sh","ix":4,"ks":{"a":0,"k":{"i":[[0,0],[0.057,-1.599],[0,0],[0.439,1.568]],"o":[[0.431,1.541],[0,0],[0.058,-1.628],[0,0]],"v":[[-0.439,-4.335],[0.126,0.402],[0.404,0.412],[-0.171,-4.41]],"c":true},"ix":2},"nm":"Path 4","mn":"ADBE Vector Shape - Group","hd":false},{"ind":4,"ty":"sh","ix":5,"ks":{"a":0,"k":{"i":[[0,0],[0.427,-1.259],[0,0],[0.056,1.362]],"o":[[0.055,1.328],[0,0],[0.438,-1.291],[0,0]],"v":[[0.126,0.413],[-0.437,4.326],[-0.173,4.416],[0.404,0.401]],"c":true},"ix":2},"nm":"Path 5","mn":"ADBE Vector Shape - Group","hd":false},{"ty":"mm","mm":1,"nm":"Merge Paths 1","mn":"ADBE Vector Filter - Merge","hd":false},{"ty":"fl","c":{"a":0,"k":[0.341175991881,0.337254991718,0.337254991718,1],"ix":4},"o":{"a":0,"k":100,"ix":5},"r":1,"bm":0,"nm":"Fill 1","mn":"ADBE Vector Graphic - Fill","hd":false},{"ty":"tr","p":{"a":0,"k":[113.193,15.617],"ix":2},"a":{"a":0,"k":[0,0],"ix":1},"s":{"a":0,"k":[100,100],"ix":3},"r":{"a":0,"k":0,"ix":6},"o":{"a":0,"k":100,"ix":7},"sk":{"a":0,"k":0,"ix":4},"sa":{"a":0,"k":0,"ix":5},"nm":"Transform"}],"nm":"Group 3","np":7,"cix":2,"bm":0,"ix":3,"mn":"ADBE Vector Group","hd":false},{"ty":"gr","it":[{"ind":0,"ty":"sh","ix":1,"ks":{"a":0,"k":{"i":[[0.132,0.729],[0,0],[0,0],[0,0]],"o":[[0,0],[0,0],[0,0],[0.237,-0.771]],"v":[[-83.282,-1.128],[83.518,-0.846],[82.95,-0.564],[-83.518,1.128]],"c":true},"ix":2},"nm":"Path 1","mn":"ADBE Vector Shape - Group","hd":false},{"ty":"fl","c":{"a":0,"k":[1,1,1,1],"ix":4},"o":{"a":0,"k":100,"ix":5},"r":1,"bm":0,"nm":"Fill 1","mn":"ADBE Vector Graphic - Fill","hd":false},{"ty":"tr","p":{"a":0,"k":[141.342,16.604],"ix":2},"a":{"a":0,"k":[0,0],"ix":1},"s":{"a":0,"k":[100,100],"ix":3},"r":{"a":0,"k":0,"ix":6},"o":{"a":0,"k":100,"ix":7},"sk":{"a":0,"k":0,"ix":4},"sa":{"a":0,"k":0,"ix":5},"nm":"Transform"}],"nm":"Group 4","np":2,"cix":2,"bm":0,"ix":4,"mn":"ADBE Vector Group","hd":false},{"ty":"gr","it":[{"ind":0,"ty":"sh","ix":1,"ks":{"a":0,"k":{"i":[[0,0],[0,0],[0,0],[0,0]],"o":[[0,0],[0,0],[0,0],[0,0]],"v":[[2.916,1.676],[0.724,-9.508],[-2.916,-1.952],[-0.769,9.508]],"c":true},"ix":2},"nm":"Path 1","mn":"ADBE Vector Shape - Group","hd":false},{"ty":"fl","c":{"a":0,"k":[0.295833004222,0.295833004222,0.295833004222,1],"ix":4},"o":{"a":0,"k":100,"ix":5},"r":1,"bm":0,"nm":"Fill 1","mn":"ADBE Vector Graphic - Fill","hd":false},{"ty":"tr","p":{"a":0,"k":[3.769,15.492],"ix":2},"a":{"a":0,"k":[0,0],"ix":1},"s":{"a":0,"k":[100,100],"ix":3},"r":{"a":0,"k":0,"ix":6},"o":{"a":0,"k":100,"ix":7},"sk":{"a":0,"k":0,"ix":4},"sa":{"a":0,"k":0,"ix":5},"nm":"Transform"}],"nm":"Group 5","np":2,"cix":2,"bm":0,"ix":5,"mn":"ADBE Vector Group","hd":false},{"ty":"gr","it":[{"ind":0,"ty":"sh","ix":1,"ks":{"a":0,"k":{"i":[[0,0],[0,0],[0,0],[0,0]],"o":[[0,0],[0,0],[0,0],[0,0]],"v":[[0.335,3.914],[4.09,-3.914],[-0.456,-3.914],[-4.09,3.914]],"c":true},"ix":2},"nm":"Path 1","mn":"ADBE Vector Shape - Group","hd":false},{"ty":"fl","c":{"a":0,"k":[0.349019996793,0.349019996793,0.349019996793,1],"ix":4},"o":{"a":0,"k":100,"ix":5},"r":1,"bm":0,"nm":"Fill 1","mn":"ADBE Vector Graphic - Fill","hd":false},{"ty":"tr","p":{"a":0,"k":[7.09,21.086],"ix":2},"a":{"a":0,"k":[0,0],"ix":1},"s":{"a":0,"k":[100,100],"ix":3},"r":{"a":0,"k":0,"ix":6},"o":{"a":0,"k":100,"ix":7},"sk":{"a":0,"k":0,"ix":4},"sa":{"a":0,"k":0,"ix":5},"nm":"Transform"}],"nm":"Group 6","np":2,"cix":2,"bm":0,"ix":6,"mn":"ADBE Vector Group","hd":false},{"ty":"gr","it":[{"ind":0,"ty":"sh","ix":1,"ks":{"a":0,"k":{"i":[[0,0],[0,0],[0,0],[0,0]],"o":[[0,0],[0,0],[0,0],[0,0]],"v":[[-3.355,-5.584],[1.089,-5.498],[3.355,5.584],[-1.193,5.584]],"c":true},"ix":2},"nm":"Path 1","mn":"ADBE Vector Shape - Group","hd":false},{"ty":"fl","c":{"a":0,"k":[0.792156982422,0.792156982422,0.792156982422,1],"ix":4},"o":{"a":0,"k":100,"ix":5},"r":1,"bm":0,"nm":"Fill 1","mn":"ADBE Vector Graphic - Fill","hd":false},{"ty":"tr","p":{"a":0,"k":[7.827,11.584],"ix":2},"a":{"a":0,"k":[0,0],"ix":1},"s":{"a":0,"k":[100,100],"ix":3},"r":{"a":0,"k":0,"ix":6},"o":{"a":0,"k":100,"ix":7},"sk":{"a":0,"k":0,"ix":4},"sa":{"a":0,"k":0,"ix":5},"nm":"Transform"}],"nm":"Group 7","np":2,"cix":2,"bm":0,"ix":7,"mn":"ADBE Vector Group","hd":false},{"ty":"gr","it":[{"ind":0,"ty":"sh","ix":1,"ks":{"a":0,"k":{"i":[[0,0],[0,0.016],[-0.032,0.05]],"o":[[-0.092,0.126],[0.025,-0.053],[0,0]],"v":[[0.066,-0.085],[-0.066,0.069],[0.02,-0.085]],"c":true},"ix":2},"nm":"Path 1","mn":"ADBE Vector Shape - Group","hd":false},{"ty":"fl","c":{"a":0,"k":[0.137254991718,0.137254991718,0.137254991718,1],"ix":4},"o":{"a":0,"k":100,"ix":5},"r":1,"bm":0,"nm":"Fill 1","mn":"ADBE Vector Graphic - Fill","hd":false},{"ty":"tr","p":{"a":0,"k":[8.582,22.559],"ix":2},"a":{"a":0,"k":[0,0],"ix":1},"s":{"a":0,"k":[100,100],"ix":3},"r":{"a":0,"k":0,"ix":6},"o":{"a":0,"k":100,"ix":7},"sk":{"a":0,"k":0,"ix":4},"sa":{"a":0,"k":0,"ix":5},"nm":"Transform"}],"nm":"Group 8","np":2,"cix":2,"bm":0,"ix":8,"mn":"ADBE Vector Group","hd":false},{"ty":"gr","it":[{"ind":0,"ty":"sh","ix":1,"ks":{"a":0,"k":{"i":[[0,0],[-0.233,-0.446],[0,0],[-5.4,0],[-4.148,-1.26],[5.51,-0.286]],"o":[[0.234,0.234],[0.116,0.698],[0,0],[4.335,0.049],[-4.917,-2.503],[-8.436,0.054]],"v":[[-83.821,-1.831],[-83.297,-0.742],[-83.084,0.425],[71.033,-0.139],[83.821,1.835],[67.907,-1.549]],"c":true},"ix":2},"nm":"Path 1","mn":"ADBE Vector Shape - Group","hd":false},{"ty":"fl","c":{"a":0,"k":[1,1,1,1],"ix":4},"o":{"a":0,"k":100,"ix":5},"r":1,"bm":0,"nm":"Fill 1","mn":"ADBE Vector Graphic - Fill","hd":false},{"ty":"tr","p":{"a":0,"k":[141.043,13.923],"ix":2},"a":{"a":0,"k":[0,0],"ix":1},"s":{"a":0,"k":[100,100],"ix":3},"r":{"a":0,"k":0,"ix":6},"o":{"a":0,"k":100,"ix":7},"sk":{"a":0,"k":0,"ix":4},"sa":{"a":0,"k":0,"ix":5},"nm":"Transform"}],"nm":"Group 9","np":2,"cix":2,"bm":0,"ix":9,"mn":"ADBE Vector Group","hd":false},{"ty":"gr","it":[{"ind":0,"ty":"sh","ix":1,"ks":{"a":0,"k":{"i":[[0,0],[0,0],[0,0],[-6.252,0],[-1.342,0.682],[1.422,-0.564],[8.508,0.082]],"o":[[0,0],[0,0],[0,0],[6.252,0],[0,0],[-1.422,0.564],[-8.508,-0.082]],"v":[[-83.841,1.833],[-83.133,0.14],[-82.915,-1.551],[65.085,-0.991],[83.841,-1.833],[79.577,0.141],[65.653,1.551]],"c":true},"ix":2},"nm":"Path 1","mn":"ADBE Vector Shape - Group","hd":false},{"ty":"fl","c":{"a":0,"k":[0.219607992733,0.219607992733,0.219607992733,1],"ix":4},"o":{"a":0,"k":100,"ix":5},"r":1,"bm":0,"nm":"Fill 1","mn":"ADBE Vector Graphic - Fill","hd":false},{"ty":"tr","p":{"a":0,"k":[141.023,17.591],"ix":2},"a":{"a":0,"k":[0,0],"ix":1},"s":{"a":0,"k":[100,100],"ix":3},"r":{"a":0,"k":0,"ix":6},"o":{"a":0,"k":100,"ix":7},"sk":{"a":0,"k":0,"ix":4},"sa":{"a":0,"k":0,"ix":5},"nm":"Transform"}],"nm":"Group 10","np":2,"cix":2,"bm":0,"ix":10,"mn":"ADBE Vector Group","hd":false},{"ty":"gr","it":[{"ind":0,"ty":"sh","ix":1,"ks":{"a":0,"k":{"i":[[0,0],[-5.684,-3.666],[4.546,0],[0,0],[-0.074,1.46],[0.772,1.727]],"o":[[4.546,0],[-5.684,3.668],[0,0],[0.705,-1.309],[-0.115,-1.646],[0,0]],"v":[[65.646,-4.51],[84.402,0.002],[65.646,4.516],[-84.402,4.516],[-83.131,0.209],[-84.402,-4.516]],"c":false},"ix":2},"nm":"Path 1","mn":"ADBE Vector Shape - Group","hd":false},{"ty":"fl","c":{"a":0,"k":[0.682353001015,0.682353001015,0.682353001015,1],"ix":4},"o":{"a":0,"k":100,"ix":5},"r":1,"bm":0,"nm":"Fill 1","mn":"ADBE Vector Graphic - Fill","hd":false},{"ty":"tr","p":{"a":0,"k":[141.03,15.754],"ix":2},"a":{"a":0,"k":[0,0],"ix":1},"s":{"a":0,"k":[100,100],"ix":3},"r":{"a":0,"k":0,"ix":6},"o":{"a":0,"k":100,"ix":7},"sk":{"a":0,"k":0,"ix":4},"sa":{"a":0,"k":0,"ix":5},"nm":"Transform"}],"nm":"Group 11","np":2,"cix":2,"bm":0,"ix":11,"mn":"ADBE Vector Group","hd":false},{"ty":"gr","it":[{"ind":0,"ty":"sh","ix":1,"ks":{"a":0,"k":{"i":[[0,0],[0,0],[0,0],[-0.065,-0.075],[0.004,-0.099],[0,0],[0,0],[0.067,-0.068],[0.096,-0.006],[0,0]],"o":[[0,0],[0,0],[0.099,0.008],[0.066,0.074],[0,0],[0,0],[-0.007,0.095],[-0.068,0.067],[0,0],[0,0]],"v":[[-26.329,1.657],[-23.597,-9.457],[24.255,-4.783],[24.511,-4.653],[24.607,-4.383],[26.329,0.468],[24.191,5.057],[24.077,5.309],[23.823,5.423],[-25.425,9.457]],"c":false},"ix":2},"nm":"Path 1","mn":"ADBE Vector Shape - Group","hd":false},{"ty":"fl","c":{"a":0,"k":[0,0,0,1],"ix":4},"o":{"a":0,"k":100,"ix":5},"r":1,"bm":0,"nm":"Fill 1","mn":"ADBE Vector Graphic - Fill","hd":false},{"ty":"tr","p":{"a":0,"k":[32.425,15.543],"ix":2},"a":{"a":0,"k":[0,0],"ix":1},"s":{"a":0,"k":[100,100],"ix":3},"r":{"a":0,"k":0,"ix":6},"o":{"a":0,"k":100,"ix":7},"sk":{"a":0,"k":0,"ix":4},"sa":{"a":0,"k":0,"ix":5},"nm":"Transform"}],"nm":"Group 12","np":2,"cix":2,"bm":0,"ix":12,"mn":"ADBE Vector Group","hd":false}],"ip":0,"op":900.000036657751,"st":0,"bm":0},{"ddd":0,"ind":6,"ty":4,"nm":"Probe - chrome AE v4 faded","sr":1,"ks":{"o":{"a":0,"k":50,"ix":11},"r":{"a":0,"k":0,"ix":10},"p":{"a":1,"k":[{"i":{"x":0.667,"y":1},"o":{"x":0.333,"y":0},"t":0,"s":[-253.815,103.989,0],"to":[104.215,0,0],"ti":[-143.157,0,0]},{"i":{"x":0.667,"y":0.961},"o":{"x":0.333,"y":0},"t":58,"s":[374.554,103.989,0],"to":[0.067,0,0],"ti":[-0.067,0,0]},{"i":{"x":0.667,"y":1},"o":{"x":0.333,"y":0.072},"t":77,"s":[396.004,103.989,0],"to":[10.153,0,0],"ti":[-7.403,0,0]},{"t":123.000005009893,"s":[423.685,103.989,0]}],"ix":2},"a":{"a":0,"k":[114,16,0],"ix":1},"s":{"a":0,"k":[200,200,100],"ix":6}},"ao":0,"shapes":[{"ty":"gr","it":[{"ind":0,"ty":"sh","ix":1,"ks":{"a":0,"k":{"i":[[0,0],[0,0],[0.054,0.845],[0,0]],"o":[[0,0],[0,0],[-0.054,-0.845],[0,0]],"v":[[-23.22,0.735],[22.866,1.317],[23.165,-0.1],[22.866,-1.317]],"c":true},"ix":2},"nm":"Path 1","mn":"ADBE Vector Shape - Group","hd":false},{"ty":"fl","c":{"a":0,"k":[0.29411797617,0.341175991881,0.43529399797,1],"ix":4},"o":{"a":0,"k":100,"ix":5},"r":1,"bm":0,"nm":"Fill 1","mn":"ADBE Vector Graphic - Fill","hd":false},{"ty":"tr","p":{"a":0,"k":[34.506,16.441],"ix":2},"a":{"a":0,"k":[0,0],"ix":1},"s":{"a":0,"k":[100,100],"ix":3},"r":{"a":0,"k":0,"ix":6},"o":{"a":0,"k":100,"ix":7},"sk":{"a":0,"k":0,"ix":4},"sa":{"a":0,"k":0,"ix":5},"nm":"Transform"}],"nm":"Group 1","np":2,"cix":2,"bm":0,"ix":1,"mn":"ADBE Vector Group","hd":false},{"ty":"gr","it":[{"ind":0,"ty":"sh","ix":1,"ks":{"a":0,"k":{"i":[[0,0],[0.049,-0.014],[-0.014,-0.049]],"o":[[-0.014,-0.049],[-0.049,0.014],[0,0]],"v":[[-0.217,-4.539],[-0.33,-4.601],[-0.392,-4.487]],"c":true},"ix":2},"nm":"Path 1","mn":"ADBE Vector Shape - Group","hd":false},{"ind":1,"ty":"sh","ix":2,"ks":{"a":0,"k":{"i":[[0,0],[0,0],[0,0]],"o":[[0,0],[0,0],[0,0]],"v":[[0.264,-0.001],[0.172,-0.004],[0.172,0.002]],"c":true},"ix":2},"nm":"Path 2","mn":"ADBE Vector Shape - Group","hd":false},{"ind":2,"ty":"sh","ix":3,"ks":{"a":0,"k":{"i":[[0,0],[-0.049,-0.014],[-0.014,0.049]],"o":[[-0.014,0.049],[0.049,0.014],[0,0]],"v":[[-0.392,4.487],[-0.33,4.601],[-0.217,4.539]],"c":true},"ix":2},"nm":"Path 3","mn":"ADBE Vector Shape - Group","hd":false},{"ind":3,"ty":"sh","ix":4,"ks":{"a":0,"k":{"i":[[0,0],[0.05,-1.515],[0,0],[0.429,1.474]],"o":[[0.424,1.455],[0,0],[0.051,-1.534],[0,0]],"v":[[-0.392,-4.487],[0.172,-0.004],[0.355,0.002],[-0.217,-4.539]],"c":true},"ix":2},"nm":"Path 4","mn":"ADBE Vector Shape - Group","hd":false},{"ind":4,"ty":"sh","ix":5,"ks":{"a":0,"k":{"i":[[0,0],[0.425,-1.456],[0,0],[0.051,1.535]],"o":[[0.051,1.516],[0,0],[0.43,-1.474],[0,0]],"v":[[0.172,0.002],[-0.392,4.487],[-0.217,4.539],[0.355,-0.004]],"c":true},"ix":2},"nm":"Path 5","mn":"ADBE Vector Shape - Group","hd":false},{"ty":"mm","mm":1,"nm":"Merge Paths 1","mn":"ADBE Vector Filter - Merge","hd":false},{"ty":"fl","c":{"a":0,"k":[0.67843095368,0.67843095368,0.67843095368,1],"ix":4},"o":{"a":0,"k":100,"ix":5},"r":1,"bm":0,"nm":"Fill 1","mn":"ADBE Vector Graphic - Fill","hd":false},{"ty":"tr","p":{"a":0,"k":[113.478,15.757],"ix":2},"a":{"a":0,"k":[0,0],"ix":1},"s":{"a":0,"k":[100,100],"ix":3},"r":{"a":0,"k":0,"ix":6},"o":{"a":0,"k":100,"ix":7},"sk":{"a":0,"k":0,"ix":4},"sa":{"a":0,"k":0,"ix":5},"nm":"Transform"}],"nm":"Group 2","np":7,"cix":2,"bm":0,"ix":2,"mn":"ADBE Vector Group","hd":false},{"ty":"gr","it":[{"ind":0,"ty":"sh","ix":1,"ks":{"a":0,"k":{"i":[[0,0],[0.074,-0.021],[-0.021,-0.074]],"o":[[-0.021,-0.074],[-0.074,0.021],[0,0]],"v":[[-0.171,-4.41],[-0.343,-4.507],[-0.439,-4.335]],"c":true},"ix":2},"nm":"Path 1","mn":"ADBE Vector Shape - Group","hd":false},{"ind":1,"ty":"sh","ix":2,"ks":{"a":0,"k":{"i":[[0,0],[0,0],[0,0]],"o":[[0,0],[0,0],[0,0]],"v":[[0.265,0.407],[0.125,0.402],[0.126,0.413]],"c":true},"ix":2},"nm":"Path 2","mn":"ADBE Vector Shape - Group","hd":false},{"ind":2,"ty":"sh","ix":3,"ks":{"a":0,"k":{"i":[[0,0],[-0.073,-0.025],[-0.025,0.073]],"o":[[-0.025,0.073],[0.073,0.025],[0,0]],"v":[[-0.437,4.326],[-0.35,4.503],[-0.173,4.416]],"c":true},"ix":2},"nm":"Path 3","mn":"ADBE Vector Shape - Group","hd":false},{"ind":3,"ty":"sh","ix":4,"ks":{"a":0,"k":{"i":[[0,0],[0.057,-1.599],[0,0],[0.439,1.568]],"o":[[0.431,1.541],[0,0],[0.058,-1.628],[0,0]],"v":[[-0.439,-4.335],[0.126,0.402],[0.404,0.412],[-0.171,-4.41]],"c":true},"ix":2},"nm":"Path 4","mn":"ADBE Vector Shape - Group","hd":false},{"ind":4,"ty":"sh","ix":5,"ks":{"a":0,"k":{"i":[[0,0],[0.427,-1.259],[0,0],[0.056,1.362]],"o":[[0.055,1.328],[0,0],[0.438,-1.291],[0,0]],"v":[[0.126,0.413],[-0.437,4.326],[-0.173,4.416],[0.404,0.401]],"c":true},"ix":2},"nm":"Path 5","mn":"ADBE Vector Shape - Group","hd":false},{"ty":"mm","mm":1,"nm":"Merge Paths 1","mn":"ADBE Vector Filter - Merge","hd":false},{"ty":"fl","c":{"a":0,"k":[0.341175991881,0.337254991718,0.337254991718,1],"ix":4},"o":{"a":0,"k":100,"ix":5},"r":1,"bm":0,"nm":"Fill 1","mn":"ADBE Vector Graphic - Fill","hd":false},{"ty":"tr","p":{"a":0,"k":[113.193,15.617],"ix":2},"a":{"a":0,"k":[0,0],"ix":1},"s":{"a":0,"k":[100,100],"ix":3},"r":{"a":0,"k":0,"ix":6},"o":{"a":0,"k":100,"ix":7},"sk":{"a":0,"k":0,"ix":4},"sa":{"a":0,"k":0,"ix":5},"nm":"Transform"}],"nm":"Group 3","np":7,"cix":2,"bm":0,"ix":3,"mn":"ADBE Vector Group","hd":false},{"ty":"gr","it":[{"ind":0,"ty":"sh","ix":1,"ks":{"a":0,"k":{"i":[[0.132,0.729],[0,0],[0,0],[0,0]],"o":[[0,0],[0,0],[0,0],[0.237,-0.771]],"v":[[-83.282,-1.128],[83.518,-0.846],[82.95,-0.564],[-83.518,1.128]],"c":true},"ix":2},"nm":"Path 1","mn":"ADBE Vector Shape - Group","hd":false},{"ty":"fl","c":{"a":0,"k":[1,1,1,1],"ix":4},"o":{"a":0,"k":100,"ix":5},"r":1,"bm":0,"nm":"Fill 1","mn":"ADBE Vector Graphic - Fill","hd":false},{"ty":"tr","p":{"a":0,"k":[141.342,16.604],"ix":2},"a":{"a":0,"k":[0,0],"ix":1},"s":{"a":0,"k":[100,100],"ix":3},"r":{"a":0,"k":0,"ix":6},"o":{"a":0,"k":100,"ix":7},"sk":{"a":0,"k":0,"ix":4},"sa":{"a":0,"k":0,"ix":5},"nm":"Transform"}],"nm":"Group 4","np":2,"cix":2,"bm":0,"ix":4,"mn":"ADBE Vector Group","hd":false},{"ty":"gr","it":[{"ind":0,"ty":"sh","ix":1,"ks":{"a":0,"k":{"i":[[0,0],[0,0],[0,0],[0,0]],"o":[[0,0],[0,0],[0,0],[0,0]],"v":[[2.916,1.676],[0.724,-9.508],[-2.916,-1.952],[-0.769,9.508]],"c":true},"ix":2},"nm":"Path 1","mn":"ADBE Vector Shape - Group","hd":false},{"ty":"fl","c":{"a":0,"k":[0.295833004222,0.295833004222,0.295833004222,1],"ix":4},"o":{"a":0,"k":100,"ix":5},"r":1,"bm":0,"nm":"Fill 1","mn":"ADBE Vector Graphic - Fill","hd":false},{"ty":"tr","p":{"a":0,"k":[3.769,15.492],"ix":2},"a":{"a":0,"k":[0,0],"ix":1},"s":{"a":0,"k":[100,100],"ix":3},"r":{"a":0,"k":0,"ix":6},"o":{"a":0,"k":100,"ix":7},"sk":{"a":0,"k":0,"ix":4},"sa":{"a":0,"k":0,"ix":5},"nm":"Transform"}],"nm":"Group 5","np":2,"cix":2,"bm":0,"ix":5,"mn":"ADBE Vector Group","hd":false},{"ty":"gr","it":[{"ind":0,"ty":"sh","ix":1,"ks":{"a":0,"k":{"i":[[0,0],[0,0],[0,0],[0,0]],"o":[[0,0],[0,0],[0,0],[0,0]],"v":[[0.335,3.914],[4.09,-3.914],[-0.456,-3.914],[-4.09,3.914]],"c":true},"ix":2},"nm":"Path 1","mn":"ADBE Vector Shape - Group","hd":false},{"ty":"fl","c":{"a":0,"k":[0.349019996793,0.349019996793,0.349019996793,1],"ix":4},"o":{"a":0,"k":100,"ix":5},"r":1,"bm":0,"nm":"Fill 1","mn":"ADBE Vector Graphic - Fill","hd":false},{"ty":"tr","p":{"a":0,"k":[7.09,21.086],"ix":2},"a":{"a":0,"k":[0,0],"ix":1},"s":{"a":0,"k":[100,100],"ix":3},"r":{"a":0,"k":0,"ix":6},"o":{"a":0,"k":100,"ix":7},"sk":{"a":0,"k":0,"ix":4},"sa":{"a":0,"k":0,"ix":5},"nm":"Transform"}],"nm":"Group 6","np":2,"cix":2,"bm":0,"ix":6,"mn":"ADBE Vector Group","hd":false},{"ty":"gr","it":[{"ind":0,"ty":"sh","ix":1,"ks":{"a":0,"k":{"i":[[0,0],[0,0],[0,0],[0,0]],"o":[[0,0],[0,0],[0,0],[0,0]],"v":[[-3.355,-5.584],[1.089,-5.498],[3.355,5.584],[-1.193,5.584]],"c":true},"ix":2},"nm":"Path 1","mn":"ADBE Vector Shape - Group","hd":false},{"ty":"fl","c":{"a":0,"k":[0.792156982422,0.792156982422,0.792156982422,1],"ix":4},"o":{"a":0,"k":100,"ix":5},"r":1,"bm":0,"nm":"Fill 1","mn":"ADBE Vector Graphic - Fill","hd":false},{"ty":"tr","p":{"a":0,"k":[7.827,11.584],"ix":2},"a":{"a":0,"k":[0,0],"ix":1},"s":{"a":0,"k":[100,100],"ix":3},"r":{"a":0,"k":0,"ix":6},"o":{"a":0,"k":100,"ix":7},"sk":{"a":0,"k":0,"ix":4},"sa":{"a":0,"k":0,"ix":5},"nm":"Transform"}],"nm":"Group 7","np":2,"cix":2,"bm":0,"ix":7,"mn":"ADBE Vector Group","hd":false},{"ty":"gr","it":[{"ind":0,"ty":"sh","ix":1,"ks":{"a":0,"k":{"i":[[0,0],[0,0.016],[-0.032,0.05]],"o":[[-0.092,0.126],[0.025,-0.053],[0,0]],"v":[[0.066,-0.085],[-0.066,0.069],[0.02,-0.085]],"c":true},"ix":2},"nm":"Path 1","mn":"ADBE Vector Shape - Group","hd":false},{"ty":"fl","c":{"a":0,"k":[0.137254991718,0.137254991718,0.137254991718,1],"ix":4},"o":{"a":0,"k":100,"ix":5},"r":1,"bm":0,"nm":"Fill 1","mn":"ADBE Vector Graphic - Fill","hd":false},{"ty":"tr","p":{"a":0,"k":[8.582,22.559],"ix":2},"a":{"a":0,"k":[0,0],"ix":1},"s":{"a":0,"k":[100,100],"ix":3},"r":{"a":0,"k":0,"ix":6},"o":{"a":0,"k":100,"ix":7},"sk":{"a":0,"k":0,"ix":4},"sa":{"a":0,"k":0,"ix":5},"nm":"Transform"}],"nm":"Group 8","np":2,"cix":2,"bm":0,"ix":8,"mn":"ADBE Vector Group","hd":false},{"ty":"gr","it":[{"ind":0,"ty":"sh","ix":1,"ks":{"a":0,"k":{"i":[[0,0],[-0.233,-0.446],[0,0],[-5.4,0],[-4.148,-1.26],[5.51,-0.286]],"o":[[0.234,0.234],[0.116,0.698],[0,0],[4.335,0.049],[-4.917,-2.503],[-8.436,0.054]],"v":[[-83.821,-1.831],[-83.297,-0.742],[-83.084,0.425],[71.033,-0.139],[83.821,1.835],[67.907,-1.549]],"c":true},"ix":2},"nm":"Path 1","mn":"ADBE Vector Shape - Group","hd":false},{"ty":"fl","c":{"a":0,"k":[1,1,1,1],"ix":4},"o":{"a":0,"k":100,"ix":5},"r":1,"bm":0,"nm":"Fill 1","mn":"ADBE Vector Graphic - Fill","hd":false},{"ty":"tr","p":{"a":0,"k":[141.043,13.923],"ix":2},"a":{"a":0,"k":[0,0],"ix":1},"s":{"a":0,"k":[100,100],"ix":3},"r":{"a":0,"k":0,"ix":6},"o":{"a":0,"k":100,"ix":7},"sk":{"a":0,"k":0,"ix":4},"sa":{"a":0,"k":0,"ix":5},"nm":"Transform"}],"nm":"Group 9","np":2,"cix":2,"bm":0,"ix":9,"mn":"ADBE Vector Group","hd":false},{"ty":"gr","it":[{"ind":0,"ty":"sh","ix":1,"ks":{"a":0,"k":{"i":[[0,0],[0,0],[0,0],[-6.252,0],[-1.342,0.682],[1.422,-0.564],[8.508,0.082]],"o":[[0,0],[0,0],[0,0],[6.252,0],[0,0],[-1.422,0.564],[-8.508,-0.082]],"v":[[-83.841,1.833],[-83.133,0.14],[-82.915,-1.551],[65.085,-0.991],[83.841,-1.833],[79.577,0.141],[65.653,1.551]],"c":true},"ix":2},"nm":"Path 1","mn":"ADBE Vector Shape - Group","hd":false},{"ty":"fl","c":{"a":0,"k":[0.219607992733,0.219607992733,0.219607992733,1],"ix":4},"o":{"a":0,"k":100,"ix":5},"r":1,"bm":0,"nm":"Fill 1","mn":"ADBE Vector Graphic - Fill","hd":false},{"ty":"tr","p":{"a":0,"k":[141.023,17.591],"ix":2},"a":{"a":0,"k":[0,0],"ix":1},"s":{"a":0,"k":[100,100],"ix":3},"r":{"a":0,"k":0,"ix":6},"o":{"a":0,"k":100,"ix":7},"sk":{"a":0,"k":0,"ix":4},"sa":{"a":0,"k":0,"ix":5},"nm":"Transform"}],"nm":"Group 10","np":2,"cix":2,"bm":0,"ix":10,"mn":"ADBE Vector Group","hd":false},{"ty":"gr","it":[{"ind":0,"ty":"sh","ix":1,"ks":{"a":0,"k":{"i":[[0,0],[-5.684,-3.666],[4.546,0],[0,0],[-0.074,1.46],[0.772,1.727]],"o":[[4.546,0],[-5.684,3.668],[0,0],[0.705,-1.309],[-0.115,-1.646],[0,0]],"v":[[65.646,-4.51],[84.402,0.002],[65.646,4.516],[-84.402,4.516],[-83.131,0.209],[-84.402,-4.516]],"c":false},"ix":2},"nm":"Path 1","mn":"ADBE Vector Shape - Group","hd":false},{"ty":"fl","c":{"a":0,"k":[0.682353001015,0.682353001015,0.682353001015,1],"ix":4},"o":{"a":0,"k":100,"ix":5},"r":1,"bm":0,"nm":"Fill 1","mn":"ADBE Vector Graphic - Fill","hd":false},{"ty":"tr","p":{"a":0,"k":[141.03,15.754],"ix":2},"a":{"a":0,"k":[0,0],"ix":1},"s":{"a":0,"k":[100,100],"ix":3},"r":{"a":0,"k":0,"ix":6},"o":{"a":0,"k":100,"ix":7},"sk":{"a":0,"k":0,"ix":4},"sa":{"a":0,"k":0,"ix":5},"nm":"Transform"}],"nm":"Group 11","np":2,"cix":2,"bm":0,"ix":11,"mn":"ADBE Vector Group","hd":false},{"ty":"gr","it":[{"ind":0,"ty":"sh","ix":1,"ks":{"a":0,"k":{"i":[[0,0],[0,0],[0,0],[-0.065,-0.075],[0.004,-0.099],[0,0],[0,0],[0.067,-0.068],[0.096,-0.006],[0,0]],"o":[[0,0],[0,0],[0.099,0.008],[0.066,0.074],[0,0],[0,0],[-0.007,0.095],[-0.068,0.067],[0,0],[0,0]],"v":[[-26.329,1.657],[-23.597,-9.457],[24.255,-4.783],[24.511,-4.653],[24.607,-4.383],[26.329,0.468],[24.191,5.057],[24.077,5.309],[23.823,5.423],[-25.425,9.457]],"c":false},"ix":2},"nm":"Path 1","mn":"ADBE Vector Shape - Group","hd":false},{"ty":"fl","c":{"a":0,"k":[0,0,0,1],"ix":4},"o":{"a":0,"k":100,"ix":5},"r":1,"bm":0,"nm":"Fill 1","mn":"ADBE Vector Graphic - Fill","hd":false},{"ty":"tr","p":{"a":0,"k":[32.425,15.543],"ix":2},"a":{"a":0,"k":[0,0],"ix":1},"s":{"a":0,"k":[100,100],"ix":3},"r":{"a":0,"k":0,"ix":6},"o":{"a":0,"k":100,"ix":7},"sk":{"a":0,"k":0,"ix":4},"sa":{"a":0,"k":0,"ix":5},"nm":"Transform"}],"nm":"Group 12","np":2,"cix":2,"bm":0,"ix":12,"mn":"ADBE Vector Group","hd":false}],"ip":0,"op":900.000036657751,"st":0,"bm":0}]}],"layers":[{"ddd":0,"ind":1,"ty":0,"nm":"temperature_purple_internal","refId":"comp_0","sr":1,"ks":{"o":{"a":0,"k":100,"ix":11},"r":{"a":0,"k":0,"ix":10},"p":{"a":0,"k":[498,261,0],"ix":2},"a":{"a":0,"k":[60,60,0],"ix":1},"s":{"a":0,"k":[100,100,100],"ix":6}},"ao":0,"w":120,"h":120,"ip":240.0000097754,"op":360.000014663101,"st":240.0000097754,"bm":0},{"ddd":0,"ind":6,"ty":0,"nm":"ins fish salmon fillet animation","refId":"comp_2","sr":1,"ks":{"o":{"a":0,"k":100,"ix":11},"r":{"a":0,"k":0,"ix":10},"p":{"a":1,"k":[{"i":{"x":0.667,"y":1},"o":{"x":0.333,"y":0},"t":41,"s":[375,300,0],"to":[29.667,-19,0],"ti":[-29.667,19,0]},{"i":{"x":0.667,"y":0.667},"o":{"x":0.333,"y":0.333},"t":68,"s":[553,186,0],"to":[0,0,0],"ti":[0,0,0]},{"i":{"x":0.667,"y":1},"o":{"x":0.333,"y":0},"t":199,"s":[553,186,0],"to":[0,0,0],"ti":[0,0,0]},{"i":{"x":0.667,"y":0.667},"o":{"x":0.167,"y":0.167},"t":226,"s":[371,301,0],"to":[0,0,0],"ti":[0,0,0]},{"i":{"x":0.667,"y":1},"o":{"x":0.167,"y":0},"t":347,"s":[371,301,0],"to":[0,0,0],"ti":[-0.667,0.167,0]},{"t":375.000015274063,"s":[375,300,0]}],"ix":2},"a":{"a":0,"k":[375,300,0],"ix":1},"s":{"a":1,"k":[{"i":{"x":[0.667,0.667,0.667],"y":[1,1,1]},"o":{"x":[0.333,0.333,0.333],"y":[0,0,0]},"t":41,"s":[100,100,100]},{"i":{"x":[0.833,0.833,0.833],"y":[1,1,1]},"o":{"x":[0.167,0.167,0.167],"y":[0,0,0]},"t":68,"s":[180,180,100]},{"i":{"x":[0.833,0.833,0.833],"y":[1,1,1]},"o":{"x":[0.167,0.167,0.167],"y":[0,0,0]},"t":347,"s":[180,180,100]},{"t":375.000015274063,"s":[100,100,100]}],"ix":6}},"ao":0,"w":750,"h":600,"ip":-1.00000004073083,"op":452.000018410337,"st":-43.0000017514259,"bm":0}],"markers":[{"tm":138.000005620855,"cm":"0","dr":0},{"tm":390.000015885026,"cm":"","dr":0}]}