{"v":"5.9.0","fr":60,"ip":0,"op":420,"w":54,"h":49,"nm":"Pro tip animation – Version 3","ddd":0,"assets":[],"layers":[{"ddd":0,"ind":1,"ty":4,"nm":"Path 199","sr":1,"ks":{"o":{"a":1,"k":[{"i":{"x":[0.574],"y":[0.866]},"o":{"x":[0.226],"y":[0]},"t":0,"s":[100]},{"i":{"x":[0.842],"y":[1]},"o":{"x":[0.297],"y":[-37.31]},"t":10,"s":[0]},{"i":{"x":[0.667],"y":[1]},"o":{"x":[0.333],"y":[0]},"t":50,"s":[0]},{"i":{"x":[0.667],"y":[1]},"o":{"x":[0.167],"y":[0]},"t":80,"s":[100]},{"i":{"x":[0.667],"y":[1]},"o":{"x":[0.333],"y":[0]},"t":110,"s":[0]},{"i":{"x":[0.667],"y":[1]},"o":{"x":[0.167],"y":[0]},"t":140,"s":[100]},{"i":{"x":[0.667],"y":[1]},"o":{"x":[0.333],"y":[0]},"t":170,"s":[0]},{"t":200,"s":[100]}],"ix":11},"r":{"a":0,"k":0,"ix":10},"p":{"a":0,"k":[36.925,9.604,0],"ix":2,"l":2},"a":{"a":0,"k":[1.925,2.604,0],"ix":1,"l":2},"s":{"a":0,"k":[100,100,100],"ix":6,"l":2}},"ao":0,"shapes":[{"ty":"gr","it":[{"ind":0,"ty":"sh","ix":1,"ks":{"a":0,"k":{"i":[[-0.479,-0.276],[0.276,-0.479],[0,0],[0.479,0.276],[-0.276,0.478],[0,0]],"o":[[0.479,0.276],[0,0],[-0.276,0.479],[-0.479,-0.276],[0,0],[0.276,-0.479]],"v":[[3.348,0.134],[3.715,1.499],[1.867,4.708],[0.501,5.075],[0.134,3.709],[1.983,0.501]],"c":true},"ix":2},"nm":"Path 1","mn":"ADBE Vector Shape - Group","hd":false},{"ty":"fl","c":{"a":0,"k":[0.003921568627,0.003921568627,0.003921568627,1],"ix":4},"o":{"a":0,"k":100,"ix":5},"r":1,"bm":0,"nm":"Fill 1","mn":"ADBE Vector Graphic - Fill","hd":false},{"ty":"tr","p":{"a":0,"k":[0,0],"ix":2},"a":{"a":0,"k":[0,0],"ix":1},"s":{"a":0,"k":[100,100],"ix":3},"r":{"a":0,"k":0,"ix":6},"o":{"a":0,"k":100,"ix":7},"sk":{"a":0,"k":0,"ix":4},"sa":{"a":0,"k":0,"ix":5},"nm":"Transform"}],"nm":"Path 199","np":3,"cix":2,"bm":0,"ix":1,"mn":"ADBE Vector Group","hd":false}],"ip":-2,"op":446,"st":-2,"bm":0},{"ddd":0,"ind":2,"ty":4,"nm":"Path 198","sr":1,"ks":{"o":{"a":1,"k":[{"i":{"x":[0.589],"y":[0.844]},"o":{"x":[0.246],"y":[0]},"t":0,"s":[100]},{"i":{"x":[0.691],"y":[1]},"o":{"x":[0.258],"y":[-39.067]},"t":10,"s":[0]},{"i":{"x":[0.667],"y":[1]},"o":{"x":[0.333],"y":[0]},"t":50,"s":[0]},{"i":{"x":[0.667],"y":[1]},"o":{"x":[0.167],"y":[0]},"t":80,"s":[100]},{"i":{"x":[0.667],"y":[1]},"o":{"x":[0.333],"y":[0]},"t":110,"s":[0]},{"i":{"x":[0.667],"y":[1]},"o":{"x":[0.167],"y":[0]},"t":140,"s":[100]},{"i":{"x":[0.667],"y":[1]},"o":{"x":[0.333],"y":[0]},"t":170,"s":[0]},{"t":200,"s":[100]}],"ix":11},"r":{"a":0,"k":0,"ix":10},"p":{"a":0,"k":[42.599,17.925,0],"ix":2,"l":2},"a":{"a":0,"k":[2.599,1.925,0],"ix":1,"l":2},"s":{"a":0,"k":[100,100,100],"ix":6,"l":2}},"ao":0,"shapes":[{"ty":"gr","it":[{"ind":0,"ty":"sh","ix":1,"ks":{"a":0,"k":{"i":[[-0.276,-0.478],[0.478,-0.276],[0,0],[0.277,0.478],[-0.478,0.276],[0,0]],"o":[[0.276,0.478],[0,0],[-0.478,0.277],[-0.276,-0.478],[0,0],[0.478,-0.276]],"v":[[5.064,0.5],[4.699,1.866],[1.501,3.715],[0.134,3.35],[0.5,1.983],[3.698,0.134]],"c":true},"ix":2},"nm":"Path 1","mn":"ADBE Vector Shape - Group","hd":false},{"ty":"fl","c":{"a":0,"k":[0.003921568627,0.003921568627,0.003921568627,1],"ix":4},"o":{"a":0,"k":100,"ix":5},"r":1,"bm":0,"nm":"Fill 1","mn":"ADBE Vector Graphic - Fill","hd":false},{"ty":"tr","p":{"a":0,"k":[0,0],"ix":2},"a":{"a":0,"k":[0,0],"ix":1},"s":{"a":0,"k":[100,100],"ix":3},"r":{"a":0,"k":0,"ix":6},"o":{"a":0,"k":100,"ix":7},"sk":{"a":0,"k":0,"ix":4},"sa":{"a":0,"k":0,"ix":5},"nm":"Transform"}],"nm":"Path 198","np":3,"cix":2,"bm":0,"ix":1,"mn":"ADBE Vector Group","hd":false}],"ip":0,"op":446,"st":0,"bm":0},{"ddd":0,"ind":3,"ty":4,"nm":"Path 197","sr":1,"ks":{"o":{"a":1,"k":[{"i":{"x":[0.589],"y":[0.844]},"o":{"x":[0.246],"y":[0]},"t":0,"s":[100]},{"i":{"x":[0.691],"y":[1]},"o":{"x":[0.258],"y":[-39.067]},"t":10,"s":[0]},{"i":{"x":[0.667],"y":[1]},"o":{"x":[0.333],"y":[0]},"t":50,"s":[0]},{"i":{"x":[0.667],"y":[1]},"o":{"x":[0.167],"y":[0]},"t":80,"s":[100]},{"i":{"x":[0.667],"y":[1]},"o":{"x":[0.333],"y":[0]},"t":110,"s":[0]},{"i":{"x":[0.667],"y":[1]},"o":{"x":[0.167],"y":[0]},"t":140,"s":[100]},{"i":{"x":[0.667],"y":[1]},"o":{"x":[0.333],"y":[0]},"t":170,"s":[0]},{"t":200,"s":[100]}],"ix":11},"r":{"a":0,"k":0,"ix":10},"p":{"a":0,"k":[11.604,17.925,0],"ix":2,"l":2},"a":{"a":0,"k":[2.604,1.925,0],"ix":1,"l":2},"s":{"a":0,"k":[100,100,100],"ix":6,"l":2}},"ao":0,"shapes":[{"ty":"gr","it":[{"ind":0,"ty":"sh","ix":1,"ks":{"a":0,"k":{"i":[[-0.276,0.479],[-0.479,-0.276],[0,0],[0.276,-0.479],[0.478,0.276],[0,0]],"o":[[0.276,-0.479],[0,0],[0.479,0.276],[-0.276,0.479],[0,0],[-0.479,-0.276]],"v":[[0.134,0.501],[1.499,0.134],[4.708,1.983],[5.075,3.348],[3.709,3.715],[0.501,1.867]],"c":true},"ix":2},"nm":"Path 1","mn":"ADBE Vector Shape - Group","hd":false},{"ty":"fl","c":{"a":0,"k":[0.003921568627,0.003921568627,0.003921568627,1],"ix":4},"o":{"a":0,"k":100,"ix":5},"r":1,"bm":0,"nm":"Fill 1","mn":"ADBE Vector Graphic - Fill","hd":false},{"ty":"tr","p":{"a":0,"k":[0,0],"ix":2},"a":{"a":0,"k":[0,0],"ix":1},"s":{"a":0,"k":[100,100],"ix":3},"r":{"a":0,"k":0,"ix":6},"o":{"a":0,"k":100,"ix":7},"sk":{"a":0,"k":0,"ix":4},"sa":{"a":0,"k":0,"ix":5},"nm":"Transform"}],"nm":"Path 197","np":3,"cix":2,"bm":0,"ix":1,"mn":"ADBE Vector Group","hd":false}],"ip":0,"op":446,"st":0,"bm":0},{"ddd":0,"ind":4,"ty":4,"nm":"Path 196","sr":1,"ks":{"o":{"a":1,"k":[{"i":{"x":[0.589],"y":[0.844]},"o":{"x":[0.246],"y":[0]},"t":0,"s":[100]},{"i":{"x":[0.691],"y":[1]},"o":{"x":[0.258],"y":[-39.067]},"t":10,"s":[0]},{"i":{"x":[0.667],"y":[1]},"o":{"x":[0.333],"y":[0]},"t":50,"s":[0]},{"i":{"x":[0.667],"y":[1]},"o":{"x":[0.167],"y":[0]},"t":80,"s":[100]},{"i":{"x":[0.667],"y":[1]},"o":{"x":[0.333],"y":[0]},"t":110,"s":[0]},{"i":{"x":[0.667],"y":[1]},"o":{"x":[0.167],"y":[0]},"t":140,"s":[100]},{"i":{"x":[0.667],"y":[1]},"o":{"x":[0.333],"y":[0]},"t":170,"s":[0]},{"t":200,"s":[100]}],"ix":11},"r":{"a":0,"k":0,"ix":10},"p":{"a":0,"k":[16.93,9.604,0],"ix":2,"l":2},"a":{"a":0,"k":[1.93,2.604,0],"ix":1,"l":2},"s":{"a":0,"k":[100,100,100],"ix":6,"l":2}},"ao":0,"shapes":[{"ty":"gr","it":[{"ind":0,"ty":"sh","ix":1,"ks":{"a":0,"k":{"i":[[-0.478,0.277],[-0.277,-0.478],[0,0],[0.478,-0.277],[0.277,0.478],[0,0]],"o":[[0.478,-0.277],[0,0],[0.277,0.478],[-0.478,0.277],[0,0],[-0.277,-0.478]],"v":[[0.499,0.135],[1.865,0.499],[3.724,3.707],[3.36,5.073],[1.994,4.71],[0.135,1.502]],"c":true},"ix":2},"nm":"Path 1","mn":"ADBE Vector Shape - Group","hd":false},{"ty":"fl","c":{"a":0,"k":[0.003921568627,0.003921568627,0.003921568627,1],"ix":4},"o":{"a":0,"k":100,"ix":5},"r":1,"bm":0,"nm":"Fill 1","mn":"ADBE Vector Graphic - Fill","hd":false},{"ty":"tr","p":{"a":0,"k":[0,0],"ix":2},"a":{"a":0,"k":[0,0],"ix":1},"s":{"a":0,"k":[100,100],"ix":3},"r":{"a":0,"k":0,"ix":6},"o":{"a":0,"k":100,"ix":7},"sk":{"a":0,"k":0,"ix":4},"sa":{"a":0,"k":0,"ix":5},"nm":"Transform"}],"nm":"Path 196","np":3,"cix":2,"bm":0,"ix":1,"mn":"ADBE Vector Group","hd":false}],"ip":0,"op":446,"st":0,"bm":0},{"ddd":0,"ind":5,"ty":4,"nm":"Path 195","sr":1,"ks":{"o":{"a":1,"k":[{"i":{"x":[0.589],"y":[0.844]},"o":{"x":[0.246],"y":[0]},"t":0,"s":[100]},{"i":{"x":[0.691],"y":[1]},"o":{"x":[0.258],"y":[-39.067]},"t":10,"s":[0]},{"i":{"x":[0.667],"y":[1]},"o":{"x":[0.333],"y":[0]},"t":50,"s":[0]},{"i":{"x":[0.667],"y":[1]},"o":{"x":[0.167],"y":[0]},"t":80,"s":[100]},{"i":{"x":[0.667],"y":[1]},"o":{"x":[0.333],"y":[0]},"t":110,"s":[0]},{"i":{"x":[0.667],"y":[1]},"o":{"x":[0.167],"y":[0]},"t":140,"s":[100]},{"i":{"x":[0.667],"y":[1]},"o":{"x":[0.333],"y":[0]},"t":170,"s":[0]},{"t":200,"s":[100]}],"ix":11},"r":{"a":0,"k":0,"ix":10},"p":{"a":0,"k":[27.178,6.854,0],"ix":2,"l":2},"a":{"a":0,"k":[1,2.854,0],"ix":1,"l":2},"s":{"a":0,"k":[100,100,100],"ix":6,"l":2}},"ao":0,"shapes":[{"ty":"gr","it":[{"ind":0,"ty":"sh","ix":1,"ks":{"a":0,"k":{"i":[[-0.552,0],[0,-0.552],[0,0],[0.552,0],[0,0.552],[0,0]],"o":[[0.552,0],[0,0],[0,0.552],[-0.552,0],[0,0],[0,-0.552]],"v":[[1,0],[2,1],[2,4.708],[1,5.708],[0,4.708],[0,1]],"c":true},"ix":2},"nm":"Path 1","mn":"ADBE Vector Shape - Group","hd":false},{"ty":"fl","c":{"a":0,"k":[0.003921568627,0.003921568627,0.003921568627,1],"ix":4},"o":{"a":0,"k":100,"ix":5},"r":1,"bm":0,"nm":"Fill 1","mn":"ADBE Vector Graphic - Fill","hd":false},{"ty":"tr","p":{"a":0,"k":[0,0],"ix":2},"a":{"a":0,"k":[0,0],"ix":1},"s":{"a":0,"k":[100,100],"ix":3},"r":{"a":0,"k":0,"ix":6},"o":{"a":0,"k":100,"ix":7},"sk":{"a":0,"k":0,"ix":4},"sa":{"a":0,"k":0,"ix":5},"nm":"Transform"}],"nm":"Path 195","np":3,"cix":2,"bm":0,"ix":1,"mn":"ADBE Vector Group","hd":false}],"ip":0,"op":446,"st":0,"bm":0},{"ddd":0,"ind":6,"ty":4,"nm":"filament","sr":1,"ks":{"o":{"a":1,"k":[{"i":{"x":[0.589],"y":[0.844]},"o":{"x":[0.246],"y":[0]},"t":0,"s":[100]},{"i":{"x":[0.691],"y":[1]},"o":{"x":[0.258],"y":[-39.067]},"t":10,"s":[0]},{"i":{"x":[0.667],"y":[1]},"o":{"x":[0.333],"y":[0]},"t":50,"s":[0]},{"i":{"x":[0.667],"y":[1]},"o":{"x":[0.167],"y":[0]},"t":80,"s":[100]},{"i":{"x":[0.667],"y":[1]},"o":{"x":[0.333],"y":[0]},"t":110,"s":[0]},{"i":{"x":[0.667],"y":[1]},"o":{"x":[0.167],"y":[0]},"t":140,"s":[100]},{"i":{"x":[0.667],"y":[1]},"o":{"x":[0.333],"y":[0]},"t":170,"s":[0]},{"t":200,"s":[100]}],"ix":11},"r":{"a":0,"k":0,"ix":10},"p":{"a":0,"k":[27,25.5,0],"ix":2,"l":2},"a":{"a":0,"k":[6,5.5,0],"ix":1,"l":2},"s":{"a":0,"k":[100,100,100],"ix":6,"l":2}},"ao":0,"shapes":[{"ty":"gr","it":[{"ind":0,"ty":"sh","ix":1,"ks":{"a":0,"k":{"i":[[0,0],[1.376,2.255],[-0.557,-1.966],[0,0]],"o":[[0,0],[-1.294,-2.115],[0.778,2.747],[0,0]],"v":[[3.866,11],[3.866,1.052],[0.067,2.316],[6.004,4.758]],"c":false},"ix":2},"nm":"Path 1","mn":"ADBE Vector Shape - Group","hd":false},{"ind":1,"ty":"sh","ix":2,"ks":{"a":0,"k":{"i":[[0,0],[-1.376,2.255],[0.557,-1.966],[0,0]],"o":[[0,0],[1.294,-2.115],[-0.778,2.747],[0,0]],"v":[[8.134,11],[8.134,1.052],[11.933,2.316],[5.996,4.758]],"c":false},"ix":2},"nm":"Path 2","mn":"ADBE Vector Shape - Group","hd":false},{"ty":"st","c":{"a":0,"k":[0.003921568627,0.003921568627,0.003921568627,1],"ix":3},"o":{"a":0,"k":100,"ix":4},"w":{"a":0,"k":2,"ix":5},"lc":2,"lj":2,"bm":0,"nm":"Stroke 1","mn":"ADBE Vector Graphic - Stroke","hd":false},{"ty":"tr","p":{"a":0,"k":[0,0],"ix":2},"a":{"a":0,"k":[0,0],"ix":1},"s":{"a":0,"k":[100,100],"ix":3},"r":{"a":0,"k":0,"ix":6},"o":{"a":0,"k":100,"ix":7},"sk":{"a":0,"k":0,"ix":4},"sa":{"a":0,"k":0,"ix":5},"nm":"Transform"}],"nm":"Path 193","np":4,"cix":2,"bm":0,"ix":1,"mn":"ADBE Vector Group","hd":false}],"ip":0,"op":446,"st":0,"bm":0},{"ddd":0,"ind":7,"ty":4,"nm":"bulb outline","sr":1,"ks":{"o":{"a":0,"k":100,"ix":11},"r":{"a":0,"k":0,"ix":10},"p":{"a":0,"k":[27,29,0],"ix":2,"l":2},"a":{"a":0,"k":[12,17,0],"ix":1,"l":2},"s":{"a":0,"k":[100,100,100],"ix":6,"l":2}},"ao":0,"shapes":[{"ty":"gr","it":[{"ind":0,"ty":"sh","ix":1,"ks":{"a":0,"k":{"i":[[-0.036,3.491],[-6.609,0],[-0.005,-6.542],[2.781,-2.168],[0.248,-0.432],[0,-0.468],[0,0],[0,0],[0,0],[0,0],[0,0],[0,0],[0,0],[0,0],[0,0],[0,0],[0,0],[0,0],[0,0],[0,0],[0,0],[0,0],[0,0],[0,0],[0,0],[0,0],[0,0],[0,0],[0,0],[0,0],[0,0],[0,0],[0,0],[0,0],[0,0],[0,0],[0,0],[0,0],[0,0],[0,0],[0,0],[0,0],[0,0],[0,0],[0,0],[0,0],[0,0],[0,0],[0,0],[0,0],[0,0],[0,0],[0,0],[0,0],[0,0],[0,0],[0,0],[0,0],[0,0],[0,0],[0,0],[0,0],[0,0],[0,0],[0,0],[0,0],[0,0],[0,0],[0,0],[0,0],[0,0],[0,0],[0,0],[0,0],[0,0],[0,0],[0,0],[0,0],[0,0],[0,0],[0,0],[0,0],[0,0],[0,0],[0,0],[0,0],[0,0],[0,0],[0,0],[0,0],[0,0],[0,0],[0,0],[0,0],[0,0],[0,0],[0,0],[0,0],[0,0],[0,0],[0,0],[0,0],[0,0],[0,0],[0,0],[0,0],[0,0],[0,0],[0,0],[0,0],[0,0],[0,0],[0,0],[0,0],[0,0],[0,0],[0,0],[0,0],[0,0],[0,0],[0,0],[0,0],[0,0],[0,0],[0,0],[0,0],[0,0],[0,0],[0,0],[0,0],[0,0],[0,0],[0,0],[0,0],[0,0],[0,0],[0,0],[0,0],[0,0],[0,0],[0,0],[0,0],[0,0],[0,0],[0,0],[0,0],[0,0],[0,0],[0,0],[0,0],[0,0],[0,0],[0,0],[0,0],[0,0],[0,0],[0,0],[0,0],[0,0],[0,0],[0,0],[0,0],[0,0],[0,0],[0,0],[0,0],[0,0],[0,0],[0,0],[0,0],[0,0],[0,0],[0,0],[0,0],[0,0],[0,0],[0,0],[0,0],[0,0],[0,0],[0,0],[0,0],[0,0],[0,0],[0,0],[0,0],[0,0],[0,0],[0,0],[0,0],[0,0],[0,0],[0,0],[0,0],[0,0],[0,0],[0,0],[0,0],[0,0],[0,0],[0,0],[0,0],[0,0],[0,0],[0,0],[0,0],[0,0],[0,0],[0,0],[0,0],[0,0],[0,0],[0,0],[0,0],[0,0],[0,0],[0,0],[0,0],[0,0],[0,0],[0,0],[0,0],[0,0],[0,0],[0,0],[0,0],[0,0],[0,0],[0,0],[0,0],[0,0],[0,0],[0,0],[0,0],[0,0],[0,0],[0,0],[0,0],[0,0],[0,0],[0,0],[0,0],[0,0],[0,0],[0,0],[0,0],[0,0],[0,0],[0,0],[0,0],[0,0],[0,0],[0,0],[0,0],[0,0],[0,0],[0,0],[0,0],[0,0],[0,0],[0,0],[0,0],[0,0],[0,0],[0,0],[0,0],[0,0],[0,0],[0,0],[0,0],[0,0],[0,0],[0,0],[0,0],[0,0],[0,0],[0,0],[0,0],[0,0],[0,0],[0,0],[0,0],[0,0],[0,0],[0,0],[0,0],[0,0],[0,0],[0,0],[0,0],[0,0],[0,0],[0,0],[0,0],[0,0],[0,0],[0,0],[0,0],[0,0],[0,0],[0,0],[0,0],[0,0],[0,0],[0,0],[0,0],[0,0],[0,0],[0,0],[0,0],[0,0],[0,0],[0,0],[0,0],[0,0],[0,0],[0,0],[0,0],[0,0],[0,0],[0,0],[0,0],[0,0],[0,0],[0,0],[0,0],[0,0],[0,0],[0,0],[0,0],[0,0],[0,0],[0,0],[0,0],[0,0],[0,0],[0,0],[0,0],[0,0],[0,0],[0,0],[0,0],[0,0],[0,0],[0,0],[0,0],[0,0],[0,0],[0,0],[0,0],[0,0],[0,0],[0,0],[0,0],[0,0],[0,0],[0,0],[0,0],[0,0],[0,0],[0,0],[0,0],[0,0],[0,0],[0,0],[0,0],[0,0],[0,0],[0,0],[0,0],[0,0],[0,0],[0,0],[0,0],[0,0],[0,0],[0,0],[0,0],[0,0],[0,0],[0,0],[0,0],[0,0],[0,0],[0,0],[0,0],[0,0],[0,0],[0,0],[0,0],[0,0],[0,0],[0,0],[0,0],[0,0],[0,0],[0,0],[0,0],[0,0],[0,0],[0,0],[0,0],[0,0],[0,0],[0,0],[0,0],[0,0],[0,0],[0,0],[0,0],[0,0],[0,0],[0,0],[0,0],[0,0],[0,0],[0,0],[0,0],[0,0],[0,0],[0,0],[0,0],[0,0],[0,0],[0,0],[0,0],[0,0],[0,0],[0,0],[0,0],[0,0],[0,0],[0,0],[0,0],[0,0],[0,0],[0,0],[0,0],[0,0],[0,0],[0,0],[0,0],[0,0],[0,0],[0,0],[0,0],[0,0],[0,0],[0,0],[0,0],[0,0],[0,0],[0,0],[0,0],[0,0],[0,0],[0,0],[0,0],[0,0],[0,0],[0,0],[0,0],[0,0],[0,0],[0,0],[0,0],[0,0],[0,0],[0,0],[0,0],[0,0],[0,0],[0,0],[0,0],[0,0],[0,0],[0,0],[0,0],[0,0],[0,0],[0,0],[0,0],[0,0],[0,0],[0,0],[0,0],[0,0],[0,0],[0,0],[0,0],[0,0],[0,0],[0,0],[0,0],[0,0],[0,0],[0,0],[0,0],[0,0],[0,0],[0,0],[0,0],[0,0],[0,0],[0,0],[0.184,-0.271],[0.286,-0.074],[0.146,0.022],[0.049,0.013],[0.011,0.003],[0,0],[-0.118,0.516],[-0.517,-0.118],[0,0],[-0.371,0.646],[-1.04,1.104],[-0.041,0.031],[0.055,2.92],[0,0],[5.575,0],[0,-5.454],[0,0],[0,0],[-2.325,-1.829],[-0.033,-0.035],[-0.378,-0.661],[-0.01,-0.66],[0,0],[0,0],[0.002,-0.068],[0,0],[0,0],[0.001,-0.032],[0,0],[0.113,-0.517],[0.519,0.113],[0,0],[0.024,0.007],[0.221,0.229],[0.056,0.239],[-0.001,0.149],[-0.002,0.059],[0,0],[0,0.055],[0,0],[0.204,0.357],[1.021,1.091]],"o":[[0.003,-6.535],[6.607,0],[0.063,3.5],[-1.02,1.085],[-0.205,0.357],[0,0],[0,0],[0,0],[0,0],[0,0],[0,0],[0,0],[0,0],[0,0],[0,0],[0,0],[0,0],[0,0],[0,0],[0,0],[0,0],[0,0],[0,0],[0,0],[0,0],[0,0],[0,0],[0,0],[0,0],[0,0],[0,0],[0,0],[0,0],[0,0],[0,0],[0,0],[0,0],[0,0],[0,0],[0,0],[0,0],[0,0],[0,0],[0,0],[0,0],[0,0],[0,0],[0,0],[0,0],[0,0],[0,0],[0,0],[0,0],[0,0],[0,0],[0,0],[0,0],[0,0],[0,0],[0,0],[0,0],[0,0],[0,0],[0,0],[0,0],[0,0],[0,0],[0,0],[0,0],[0,0],[0,0],[0,0],[0,0],[0,0],[0,0],[0,0],[0,0],[0,0],[0,0],[0,0],[0,0],[0,0],[0,0],[0,0],[0,0],[0,0],[0,0],[0,0],[0,0],[0,0],[0,0],[0,0],[0,0],[0,0],[0,0],[0,0],[0,0],[0,0],[0,0],[0,0],[0,0],[0,0],[0,0],[0,0],[0,0],[0,0],[0,0],[0,0],[0,0],[0,0],[0,0],[0,0],[0,0],[0,0],[0,0],[0,0],[0,0],[0,0],[0,0],[0,0],[0,0],[0,0],[0,0],[0,0],[0,0],[0,0],[0,0],[0,0],[0,0],[0,0],[0,0],[0,0],[0,0],[0,0],[0,0],[0,0],[0,0],[0,0],[0,0],[0,0],[0,0],[0,0],[0,0],[0,0],[0,0],[0,0],[0,0],[0,0],[0,0],[0,0],[0,0],[0,0],[0,0],[0,0],[0,0],[0,0],[0,0],[0,0],[0,0],[0,0],[0,0],[0,0],[0,0],[0,0],[0,0],[0,0],[0,0],[0,0],[0,0],[0,0],[0,0],[0,0],[0,0],[0,0],[0,0],[0,0],[0,0],[0,0],[0,0],[0,0],[0,0],[0,0],[0,0],[0,0],[0,0],[0,0],[0,0],[0,0],[0,0],[0,0],[0,0],[0,0],[0,0],[0,0],[0,0],[0,0],[0,0],[0,0],[0,0],[0,0],[0,0],[0,0],[0,0],[0,0],[0,0],[0,0],[0,0],[0,0],[0,0],[0,0],[0,0],[0,0],[0,0],[0,0],[0,0],[0,0],[0,0],[0,0],[0,0],[0,0],[0,0],[0,0],[0,0],[0,0],[0,0],[0,0],[0,0],[0,0],[0,0],[0,0],[0,0],[0,0],[0,0],[0,0],[0,0],[0,0],[0,0],[0,0],[0,0],[0,0],[0,0],[0,0],[0,0],[0,0],[0,0],[0,0],[0,0],[0,0],[0,0],[0,0],[0,0],[0,0],[0,0],[0,0],[0,0],[0,0],[0,0],[0,0],[0,0],[0,0],[0,0],[0,0],[0,0],[0,0],[0,0],[0,0],[0,0],[0,0],[0,0],[0,0],[0,0],[0,0],[0,0],[0,0],[0,0],[0,0],[0,0],[0,0],[0,0],[0,0],[0,0],[0,0],[0,0],[0,0],[0,0],[0,0],[0,0],[0,0],[0,0],[0,0],[0,0],[0,0],[0,0],[0,0],[0,0],[0,0],[0,0],[0,0],[0,0],[0,0],[0,0],[0,0],[0,0],[0,0],[0,0],[0,0],[0,0],[0,0],[0,0],[0,0],[0,0],[0,0],[0,0],[0,0],[0,0],[0,0],[0,0],[0,0],[0,0],[0,0],[0,0],[0,0],[0,0],[0,0],[0,0],[0,0],[0,0],[0,0],[0,0],[0,0],[0,0],[0,0],[0,0],[0,0],[0,0],[0,0],[0,0],[0,0],[0,0],[0,0],[0,0],[0,0],[0,0],[0,0],[0,0],[0,0],[0,0],[0,0],[0,0],[0,0],[0,0],[0,0],[0,0],[0,0],[0,0],[0,0],[0,0],[0,0],[0,0],[0,0],[0,0],[0,0],[0,0],[0,0],[0,0],[0,0],[0,0],[0,0],[0,0],[0,0],[0,0],[0,0],[0,0],[0,0],[0,0],[0,0],[0,0],[0,0],[0,0],[0,0],[0,0],[0,0],[0,0],[0,0],[0,0],[0,0],[0,0],[0,0],[0,0],[0,0],[0,0],[0,0],[0,0],[0,0],[0,0],[0,0],[0,0],[0,0],[0,0],[0,0],[0,0],[0,0],[0,0],[0,0],[0,0],[0,0],[0,0],[0,0],[0,0],[0,0],[0,0],[0,0],[0,0],[0,0],[0,0],[0,0],[0,0],[0,0],[0,0],[0,0],[0,0],[0,0],[0,0],[0,0],[0,0],[0,0],[0,0],[0,0],[0,0],[0,0],[0,0],[0,0],[0,0],[0,0],[0,0],[0,0],[0,0],[0,0],[0,0],[0,0],[0,0],[0,0],[0,0],[0,0],[0,0],[0,0],[0,0],[0,0],[0,0],[0,0],[0,0],[0,0],[0,0],[0,0],[0,0],[0,0],[0,0],[0,0],[0,0],[0,0],[0,0],[0,0],[0,0],[0,0],[0,0],[0,0],[0,0],[0,0],[0,0],[0,0],[0,0],[0,0],[0,0],[0,0],[0,0],[0,0],[0,0],[0,0],[0,0],[0,0],[0,0],[0,0],[0,0],[0,0],[0,0],[0,0],[0,0],[0,0],[0,0],[0,0],[0,0],[0,0],[0,0],[0,0],[0,0],[0,0],[0,0],[0,0],[0,0],[0,0],[0,0],[0,0],[0,0],[0,0],[-0.019,0.311],[-0.225,0.331],[-0.266,0.068],[-0.078,-0.012],[-0.013,-0.003],[0,0],[-0.517,-0.118],[0.119,-0.516],[0,0],[0.021,-0.568],[0.38,-0.662],[0.035,-0.037],[2.341,-1.8],[0,0],[0,-5.462],[-5.574,0],[0,0],[0,0],[-0.031,2.915],[0.038,0.03],[1.04,1.109],[0.423,0.74],[0,0],[0,0],[0,0.086],[0,0],[0,0],[-0.001,0.041],[0,0],[0.519,0.113],[-0.113,0.517],[0,0],[-0.025,-0.005],[-0.278,-0.084],[-0.226,-0.234],[-0.052,-0.223],[0.001,-0.068],[0,0],[0.002,-0.068],[0,0],[-0.008,-0.473],[-0.247,-0.431],[-2.749,-2.191]],"v":[[0.001,11.816],[11.999,0],[23.998,11.812],[19.688,20.811],[17.932,22.926],[17.688,23.984],[17.688,23.986],[17.688,23.989],[17.688,23.992],[17.688,23.995],[17.688,23.997],[17.688,24],[17.688,24.003],[17.688,24.005],[17.688,24.008],[17.688,24.011],[17.688,24.013],[17.688,24.016],[17.688,24.018],[17.688,24.021],[17.688,24.023],[17.688,24.026],[17.688,24.028],[17.688,24.031],[17.688,24.033],[17.688,24.036],[17.688,24.038],[17.688,24.04],[17.688,24.043],[17.688,24.045],[17.688,24.048],[17.688,24.05],[17.688,24.052],[17.688,24.055],[17.688,24.057],[17.688,24.059],[17.688,24.061],[17.688,24.063],[17.688,24.066],[17.688,24.068],[17.688,24.069],[17.688,24.069],[17.688,24.069],[17.688,24.069],[17.688,24.069],[17.688,24.069],[17.688,24.069],[17.688,24.069],[17.688,24.069],[17.688,24.07],[17.688,24.07],[17.688,24.07],[17.688,24.07],[17.688,24.07],[17.688,24.07],[17.688,24.07],[17.688,24.07],[17.688,24.07],[17.688,24.07],[17.688,24.071],[17.688,24.071],[17.688,24.071],[17.688,24.071],[17.688,24.071],[17.688,24.072],[17.688,24.072],[17.688,24.072],[17.688,24.072],[17.688,24.072],[17.688,24.072],[17.688,24.073],[17.688,24.073],[17.688,24.073],[17.688,24.073],[17.688,24.074],[17.688,24.074],[17.688,24.074],[17.688,24.074],[17.688,24.075],[17.688,24.075],[17.688,24.075],[17.688,24.076],[17.688,24.076],[17.688,24.076],[17.688,24.076],[17.688,24.077],[17.688,24.077],[17.688,24.077],[17.688,24.078],[17.688,24.078],[17.688,24.078],[17.688,24.078],[17.688,24.079],[17.688,24.079],[17.688,24.079],[17.688,24.08],[17.688,24.08],[17.688,24.08],[17.688,24.081],[17.688,24.081],[17.688,24.081],[17.688,24.082],[17.688,24.082],[17.688,24.083],[17.688,24.083],[17.688,24.083],[17.688,24.084],[17.688,24.084],[17.688,24.085],[17.688,24.085],[17.688,24.085],[17.688,24.085],[17.688,24.086],[17.688,24.086],[17.688,24.087],[17.688,24.087],[17.688,24.087],[17.688,24.088],[17.688,24.088],[17.688,24.089],[17.688,24.089],[17.688,24.089],[17.688,24.09],[17.688,24.09],[17.688,24.09],[17.688,24.091],[17.688,24.091],[17.688,24.092],[17.688,24.092],[17.688,24.092],[17.688,24.093],[17.688,24.094],[17.688,24.094],[17.688,24.094],[17.688,24.095],[17.688,24.095],[17.688,24.096],[17.688,24.096],[17.688,24.096],[17.688,24.097],[17.688,24.098],[17.688,24.098],[17.688,24.098],[17.688,24.099],[17.688,24.099],[17.688,24.1],[17.688,24.1],[17.688,24.1],[17.688,24.101],[17.688,24.102],[17.688,24.102],[17.688,24.102],[17.688,24.103],[17.688,24.103],[17.688,24.104],[17.688,24.104],[17.688,24.105],[17.688,24.105],[17.688,24.106],[17.688,24.106],[17.688,24.107],[17.688,24.107],[17.688,24.107],[17.688,24.108],[17.688,24.108],[17.688,24.109],[17.688,24.109],[17.688,24.11],[17.688,24.11],[17.688,24.111],[17.688,24.111],[17.688,24.112],[17.688,24.112],[17.688,24.113],[17.688,24.113],[17.688,24.114],[17.688,24.114],[17.688,24.115],[17.688,24.115],[17.688,24.116],[17.688,24.116],[17.688,24.116],[17.688,24.117],[17.688,24.118],[17.688,24.118],[17.688,24.118],[17.688,24.119],[17.688,24.12],[17.688,24.12],[17.688,24.12],[17.688,24.121],[17.688,24.121],[17.688,24.122],[17.688,24.122],[17.688,24.123],[17.688,24.123],[17.688,24.124],[17.688,24.124],[17.688,24.125],[17.688,24.125],[17.688,24.126],[17.688,24.126],[17.688,24.126],[17.688,24.127],[17.688,24.128],[17.688,24.128],[17.688,24.129],[17.688,24.129],[17.688,24.13],[17.688,24.13],[17.688,24.131],[17.688,24.131],[17.688,24.131],[17.688,24.132],[17.688,24.133],[17.688,24.133],[17.688,24.133],[17.688,24.134],[17.688,24.134],[17.688,24.135],[17.688,24.136],[17.688,24.136],[17.688,24.136],[17.688,24.137],[17.688,24.137],[17.688,24.138],[17.688,24.139],[17.688,24.139],[17.688,24.139],[17.688,24.14],[17.688,24.14],[17.688,24.141],[17.688,24.141],[17.688,24.142],[17.688,24.142],[17.688,24.143],[17.688,24.143],[17.688,24.144],[17.688,24.144],[17.688,24.145],[17.688,24.145],[17.688,24.146],[17.688,24.146],[17.688,24.146],[17.688,24.147],[17.688,24.148],[17.688,24.148],[17.688,24.149],[17.688,24.149],[17.688,24.149],[17.688,24.15],[17.688,24.15],[17.688,24.151],[17.688,24.151],[17.688,24.152],[17.688,24.152],[17.688,24.153],[17.688,24.153],[17.688,24.154],[17.688,24.154],[17.688,24.154],[17.688,24.155],[17.688,24.156],[17.688,24.156],[17.688,24.156],[17.688,24.157],[17.688,24.157],[17.688,24.158],[17.688,24.158],[17.688,24.159],[17.688,24.159],[17.688,24.16],[17.688,24.16],[17.688,24.161],[17.688,24.161],[17.688,24.161],[17.688,24.162],[17.688,24.162],[17.688,24.163],[17.688,24.163],[17.688,24.163],[17.688,24.164],[17.688,24.165],[17.688,24.165],[17.688,24.165],[17.688,24.166],[17.688,24.166],[17.688,24.167],[17.688,24.167],[17.688,24.168],[17.688,24.168],[17.688,24.168],[17.688,24.169],[17.688,24.169],[17.688,24.17],[17.688,24.17],[17.688,24.17],[17.688,24.171],[17.688,24.172],[17.688,24.172],[17.688,24.172],[17.688,24.173],[17.688,24.173],[17.688,24.174],[17.688,24.174],[17.688,24.174],[17.688,24.175],[17.688,24.175],[17.688,24.176],[17.688,24.176],[17.688,24.176],[17.688,24.177],[17.688,24.177],[17.688,24.178],[17.688,24.178],[17.688,24.178],[17.688,24.179],[17.688,24.179],[17.688,24.18],[17.688,24.18],[17.688,24.18],[17.688,24.181],[17.688,24.181],[17.688,24.182],[17.688,24.182],[17.688,24.182],[17.688,24.183],[17.688,24.183],[17.688,24.184],[17.688,24.184],[17.688,24.184],[17.688,24.185],[17.688,24.185],[17.688,24.185],[17.688,24.186],[17.688,24.186],[17.688,24.187],[17.688,24.187],[17.688,24.187],[17.688,24.188],[17.688,24.188],[17.688,24.188],[17.688,24.189],[17.688,24.189],[17.688,24.189],[17.688,24.19],[17.688,24.19],[17.688,24.19],[17.688,24.191],[17.688,24.191],[17.688,24.191],[17.688,24.192],[17.688,24.192],[17.688,24.193],[17.688,24.193],[17.688,24.193],[17.688,24.194],[17.688,24.194],[17.688,24.194],[17.688,24.195],[17.688,24.195],[17.688,24.195],[17.688,24.196],[17.688,24.196],[17.688,24.196],[17.688,24.197],[17.688,24.197],[17.688,24.197],[17.688,24.198],[17.688,24.198],[17.688,24.199],[17.688,24.199],[17.688,24.199],[17.688,24.2],[17.688,24.2],[17.688,24.2],[17.688,24.2],[17.688,24.201],[17.688,24.201],[17.688,24.201],[17.688,24.202],[17.688,24.202],[17.688,24.202],[17.688,24.202],[17.688,24.203],[17.688,24.203],[17.688,24.203],[17.688,24.204],[17.688,24.204],[17.688,24.204],[17.688,24.204],[17.688,24.204],[17.688,24.205],[17.688,24.205],[17.688,24.205],[17.688,24.206],[17.688,24.206],[17.688,24.206],[17.688,24.206],[17.688,24.207],[17.688,24.207],[17.688,24.207],[17.688,24.207],[17.688,24.208],[17.688,24.208],[17.688,24.208],[17.688,24.208],[17.688,24.208],[17.688,24.209],[17.688,24.209],[17.688,24.209],[17.688,24.209],[17.688,24.21],[17.688,24.21],[17.688,24.21],[17.688,24.21],[17.688,24.21],[17.688,24.211],[17.688,24.211],[17.688,24.211],[17.688,24.211],[17.688,24.212],[17.688,24.212],[17.688,24.212],[17.688,24.212],[17.688,24.212],[17.688,24.213],[17.688,24.213],[17.688,24.213],[17.688,24.213],[17.688,24.213],[17.688,24.213],[17.688,24.214],[17.688,24.214],[17.688,24.214],[17.688,24.214],[17.688,24.214],[17.688,24.214],[17.688,24.215],[17.688,24.215],[17.688,24.215],[17.688,24.215],[17.688,24.215],[17.688,24.216],[17.688,24.216],[17.688,24.216],[17.688,24.216],[17.688,24.216],[17.688,24.216],[17.688,24.217],[17.688,24.217],[17.688,24.217],[17.688,24.217],[17.688,24.217],[17.688,24.217],[17.688,24.217],[17.688,24.217],[17.688,24.218],[17.688,24.218],[17.688,24.218],[17.688,24.218],[17.688,24.218],[17.688,24.218],[17.688,24.218],[17.688,24.219],[17.688,24.219],[17.688,24.219],[17.688,24.219],[17.688,24.219],[17.688,24.219],[17.688,24.219],[17.688,24.219],[17.688,24.219],[17.688,24.219],[17.688,24.219],[17.688,24.22],[17.688,24.22],[17.688,24.22],[17.688,24.22],[17.688,24.22],[17.688,24.22],[17.688,24.22],[17.688,24.22],[17.688,24.22],[17.688,24.22],[17.688,24.22],[17.688,24.221],[17.688,24.221],[17.688,24.221],[17.688,24.221],[17.688,24.221],[17.688,24.221],[17.688,24.221],[17.688,24.221],[17.688,24.221],[17.688,24.221],[17.688,24.221],[17.688,24.221],[17.688,24.221],[17.688,24.221],[17.688,24.221],[17.688,24.221],[17.688,24.221],[17.688,24.221],[17.684,24.221],[17.4,25.113],[16.576,25.691],[15.927,25.721],[15.734,25.682],[15.697,25.672],[11.315,24.67],[10.593,23.521],[11.745,22.801],[15.771,23.721],[16.264,21.973],[18.339,19.444],[18.453,19.341],[22.076,11.839],[22.076,11.821],[11.999,1.917],[1.923,11.821],[1.923,11.831],[1.923,11.831],[5.555,19.348],[5.661,19.445],[7.729,21.978],[8.232,23.969],[8.232,23.984],[8.232,24.531],[8.228,24.768],[8.227,24.791],[8.227,24.791],[8.224,24.899],[16.515,26.699],[17.249,27.84],[16.106,28.572],[7.597,26.725],[7.523,26.706],[6.752,26.254],[6.356,25.514],[6.302,24.929],[6.306,24.733],[6.307,24.71],[6.31,24.531],[6.31,23.991],[6.059,22.927],[4.306,20.807]],"c":true},"ix":2},"nm":"Path 1","mn":"ADBE Vector Shape - Group","hd":false},{"ind":1,"ty":"sh","ix":2,"ks":{"a":0,"k":{"i":[[-0.116,0.517],[-0.518,-0.116],[0,0],[0.116,-0.516],[0.518,0.116],[0,0]],"o":[[0.116,-0.517],[0,0],[0.518,0.116],[-0.116,0.517],[0,0],[-0.518,-0.116]],"v":[[6.848,28.367],[7.996,27.641],[16.409,29.523],[17.137,30.668],[15.989,31.394],[7.576,29.512]],"c":true},"ix":2},"nm":"Path 2","mn":"ADBE Vector Shape - Group","hd":false},{"ind":2,"ty":"sh","ix":3,"ks":{"a":0,"k":{"i":[[0,0],[0.115,-0.517],[-0.518,-0.114],[0,0],[-0.115,0.517],[0.518,0.114]],"o":[[-0.518,-0.114],[-0.115,0.517],[0,0],[0.518,0.114],[0.115,-0.517],[0,0]],"v":[[8.521,30.6],[7.375,31.329],[8.106,32.472],[14.937,33.977],[16.083,33.248],[15.352,32.105]],"c":true},"ix":2},"nm":"Path 3","mn":"ADBE Vector Shape - Group","hd":false},{"ty":"fl","c":{"a":0,"k":[0.003921568627,0.003921568627,0.003921568627,1],"ix":4},"o":{"a":0,"k":100,"ix":5},"r":1,"bm":0,"nm":"Fill 1","mn":"ADBE Vector Graphic - Fill","hd":false},{"ty":"tr","p":{"a":0,"k":[0,0],"ix":2},"a":{"a":0,"k":[0,0],"ix":1},"s":{"a":0,"k":[100,100],"ix":3},"r":{"a":0,"k":0,"ix":6},"o":{"a":0,"k":100,"ix":7},"sk":{"a":0,"k":0,"ix":4},"sa":{"a":0,"k":0,"ix":5},"nm":"Transform"}],"nm":"Path 194","np":5,"cix":2,"bm":0,"ix":1,"mn":"ADBE Vector Group","hd":false}],"ip":0,"op":446,"st":0,"bm":0}],"markers":[]}